Workbook

Sheet Index
A1: 20 CONSTRUCTION DATA ANALYSIS PROBLEMS — FOR WT PARTNERSHIP
A2: Prepared by Gulzar | Data Analyst | Construction-Tech Domain
A4: # | B4: Problem Title | C4: Domain | D4: Sheet Name | E4: Rows in Dataset
A5: 1 | B5: Project Cost Overrun Analysis | C5: Cost Management | D5: P01-CostOverrun | E5: 50
A6: 2 | B6: Material Price Fluctuation Tracker | C6: Procurement | D6: P02-MaterialPrice | E6: 90
A7: 3 | B7: BOQ Variance Analysis | C7: Quantity Surveying | D7: P03-BOQVariance | E7: 60
A8: 4 | B8: Labour Productivity by Trade | C8: Resource Management | D8: P04-LabourProd | E8: 80
A9: 5 | B9: Tender Bid Comparison | C9: Commercial | D9: P05-TenderBid | E9: 40
A10: 6 | B10: Project Delay Root Cause | C10: Project Management | D10: P06-DelayRCA | E10: 60
A11: 7 | B11: Monthly Cash Flow Tracking | C11: Financial Management | D11: P07-CashFlow | E11: 48
A12: 8 | B12: Change Order Impact Analysis | C12: Contract Management | D12: P08-ChangeOrder | E12: 45
A13: 9 | B13: Subcontractor Performance Scorecard | C13: Vendor Management | D13: P09-SubconScore | E13: 30
A14: 10 | B14: Construction Cost Benchmarking | C14: Cost Intelligence | D14: P10-Benchmark | E14: 40
A15: 11 | B15: Risk Register & Probability Matrix | C15: Risk Management | D15: P11-RiskRegister | E15: 35
A16: 12 | B16: Earned Value Management (EVM) | C16: Project Controls | D16: P12-EVM | E16: 36
... A24: 20 | B24: Multi-Project Portfolio Dashboard Data | C24: Portfolio Management | D24: P20-Portfolio | E24: 25

Sheet Analysis Dashboard 
A2: Sheet Name | B2: P01-CostOverrun
B3: Q1. Which country has the highest average cost overrun percentage?
B4: Q2. What is the total budget vs actual cost for each project type? Which type has the worst variance?
B5: Q3. Identify the Top 5 projects with the highest absolute cost overrun (in USD).
B6: Q4. Is there a correlation between project duration and cost overrun percentage?
B7: Q5. Create a pivot table showing average overrun % by Country × Project Type.
B8: Q6. What percentage of projects came in under budget vs over budget?
B9: Q7. Which city has the most cost-efficient project delivery?
A11: Sheet Name | B11: P02-MaterialPrice
B12: Q1. Which material has shown the highest average price increase over 18 months?
B13: Q2. Create a line chart showing monthly price trend for TMT Steel and Cement.
B14: Q3. Which country has the most volatile material pricing? (Use standard deviation)
B15: Q4. Identify the top 3 materials with price increase > 15% — flag them as procurement risk.
B16: Q5. What is the average price change % by material across all months?
B17: Q6. If WT needs 500 MT of steel next quarter, what is the projected cost based on the trend?
A19: Sheet Name | B19: P03-BOQVariance
B20: Q1. Which project has the highest total BOQ variance (in USD)?
B21: Q2. Which trade consistently exceeds BOQ quantities across all 3 projects?
B22: Q3. Identify the top 5 BOQ items with the highest quantity variance %.
B23: Q4. What is the total financial impact of quantity overruns per project?
B24: Q5. Create a waterfall chart showing BOQ Amount vs Actual Amount per trade for Project WT-DC-MUM-01.
B25: Q6. Which items have negative variance (came under BOQ)? What's the saving?
A27: Sheet Name | B27: P04-LabourProd
B28: Q1. Which trade has the highest average productivity per man-hour?
B29: Q2. Is there a productivity difference between projects in India vs Australia?
B30: Q3. Create a box plot (or summary stats) of productivity by trade — which has the most variance?
B31: Q4. On which dates did productivity drop below the 25th percentile? What was the trade?
B32: Q5. What is the optimal crew size (workers count) that maximises productivity for Civil & Structure?
B33: Q6. Calculate total man-hours consumed per project and rank them.
A35: Sheet Name | B35: P05-TenderBid
B36: Q1. For each tender package, which contractor offers the lowest bid? Is the lowest bid always the best choice?
B37: Q2. Create a weighted scoring model: 40% Price, 20% Time, 15% Experience, 15% Safety, 10% Defects. Rank contractors.
B38: Q3. Which contractors appear in multiple packages? What is their average bid competitiveness?
B39: Q4. Identify any contractor with Safety Rating < 3.5 AND Defect Rate > 8% — flag as HIGH RISK.
B40: Q5. What is the total project cost if WT selects the lowest bidder for each package vs the highest-scored bidder?
B41: Q6. Create a scatter plot of Bid Amount vs Completion Days — are cheaper bids slower?
A43: Sheet Name | B43: P06-DelayRCA
B44: Q1. What is the most frequent delay cause category? Create a Pareto chart.
B45: Q2. Which responsible party causes the most total delay days?
B46: Q3. For Project WT-DC-MUM-01, what is the cumulative delay and the dominant cause?
B47: Q4. Is there a seasonal pattern in delays? (Hint: check Weather delays by month)
B48: Q5. Which activity is most delay-prone across all projects?
B49: Q6. Calculate the estimated cost of delay per project if the daily burn rate is $15,000.
A51: Sheet Name | B51: P07-CashFlow
B52: Q1. Which project had negative net cash flow for the most months?
B53: Q2. What is the cumulative cash position for each project at end of December 2024?
B54: Q3. Create a line chart of monthly net cash flow for all 4 projects.
B55: Q4. In which months did actual inflow fall below 70% of planned? Flag as collection risk.
B56: Q5. What is the total cash surplus/deficit across all projects?
B57: Q6. Calculate the cash flow forecast accuracy: (Actual Inflow / Planned Inflow) × 100.
A59: Sheet Name | B59: P08-ChangeOrder
B60: Q1. What is the total approved cost impact of all change orders per project?
B61: Q2. Who initiates the most change orders — Client, Consultant, or Contractor?
B62: Q3. What % of change orders are still Pending or Under Review? What is the potential cost exposure?
B63: Q4. Is there a correlation between cost impact and time impact of VOs?
B64: Q5. Which project has the highest change order frequency per month?
B65: Q6. Create a stacked bar chart: Approved vs Pending vs Rejected VO costs per project.
A67: Sheet Name | B67: P09-SubconScore
B68: Q1. Rank all subcontractors by their weighted score. Who are the top 3 and bottom 3?
B69: Q2. Which trade has the lowest average quality score?
B70: Q3. Is there a negative correlation between defect count and quality score?
B71: Q4. Create a radar chart for the top-performing subcontractor showing all 5 dimensions.
B72: Q5. Which subcontractors should be blacklisted (weighted score < 3.0 AND defects > 15)?
B73: Q6. Compare subcontractor performance across the 3 projects — is any project a consistent outlier?
A75: Sheet Name | B75: P10-Benchmark
B76: Q1. What is the average cost per sqm by country? Visualise as a bar chart.
B77: Q2. Which project type has the highest and lowest cost per sqm globally?
B78: Q3. Has cost per sqm increased year-over-year? Show the trend by country.
B79: Q4. Create a benchmark table: Project Type × Country showing avg cost/sqm.
B80: Q5. Identify outliers — projects where cost/sqm is >1.5× the country average for that type.
B81: Q6. If WT pitches a 50,000 sqm Data Centre in Mumbai, what should the budget estimate be based on this data?
A83: Sheet Name | B83: P12-EVM
B84: Q1. In which month does the project first show a negative Schedule Variance (SV)?
B85: Q2. What is the CPI trend? Is the project getting more or less cost-efficient over time?
B86: Q3. Based on EAC at Month 36, what is the projected cost overrun?
B87: Q4. Create a line chart with PV, EV, and AC — the classic S-curve.
B88: Q5. At what month does SPI drop below 0.90 (critical schedule delay)?
B89: Q6. If management wants CPI ≥ 1.0 by Month 24, how much cost needs to be recovered?
A91: Sheet Name | B91: P13-LeadTime
B92: Q1. What is the average lead time (order to delivery) by material?
B93: Q2. Which supplier has the worst on-time delivery rate?
B94: Q3. How many POs were delivered late? What is the average delay in days?
B95: Q4. Is there a country-level difference in procurement lead times?
B96: Q5. Which material has the longest and most unpredictable lead time (highest std deviation)?
B97: Q6. Create a supplier reliability scorecard based on on-time delivery %.
A99: Sheet Name | B99: P14-PaymentAging
B100: Q1. What is the total outstanding amount across all projects?
B101: Q2. Which client has the highest overdue amount (paid after due date)?
B102: Q3. Create an aging bucket analysis: 0–30 days, 31–60 days, 61–90 days, 90+ days.
B103: Q4. What is the average days-to-pay by client?
B104: Q5. Which project has the worst collection rate (Paid / Invoiced)?
B105: Q6. If WT charges 1.5% monthly interest on overdue amounts, what is the total interest receivable?
A107: Sheet Name | B107: P15-Portfolio
B108: Q1. How many projects are In Progress, On Hold, Completed, and Planning? Show as a pie chart.
B109: Q2. What is the total portfolio budget and total spent? What is the overall budget variance?
B110: Q3. Which projects have CPI < 0.90 AND SPI < 0.90? These are 'red zone' — list them.
B111: Q4. Create a bubble chart: X = SPI, Y = CPI, Size = Budget. Which quadrant has the most projects?
B112: Q5. What is the average completion % by country?
B113: Q6. Build a traffic-light summary: Green (CPI≥1, SPI≥1), Amber (either <1), Red (both <0.9). Count per category.
B114: Q7. If WT's board asks 'how is our portfolio doing?' — write a 3-line executive summary using this data.

Sheet Data Story
A1: THE STORY OF THE PORTFOLIO — 15 PROBLEMS, ONE NARRATIVE
A2: WT Partnership construction data | 50 projects, 25-project portfolio, 3 countries | Every chapter below is tagged to one of the 15 analysed problems. Evidence column is a live link to the Analysis report.
A4: THE STORY IN ONE SHOT
A5: WT wins work in the cheapest-bid market and prices it off benchmarks that are already drifting (P05, P10). The job then leaks value in three places at once: quantities and variations grow beyond the BOQ (P01, P03, P08), the site loses days to other people's decisions and to its own productivity swings (P04, P06, P09, P12), and the supply chain delivers late and dearer than planned (P02, P13). By the time the work is built the money is still outside the business — cash is negative, invoices are ageing, the portfolio is amber (P07, P14, P15). Nine out of ten projects finish over budget, 2024 closed $7.3m cash-negative, $11.9m sits uncollected and 72% of live projects are amber. The cause is not one failure; it is one chain, and it breaks in the same order every time.
A7: Ch | B7: Tag | C7: Chapter headline | D7: The story — what the data is telling us | E7: Evidence (live link to Analysis report) | F7: So what - the move
A8: ACT I — THE PROMISE: how the job is won and priced
A9: 1 | B9: P05 | C9: We buy the cheapest number, not the best bid | D9: Across 5 packages and 13 contractors, the lowest bidder is not the best bidder on 2 of 5 packages. Cheap bids also quote longer programmes (r = -0.25), and 4 bids fail both the safety and defect screens - yet they price competitively enough to win. The discount we celebrate at award is a liability we inherit on site. | E9: ='Analysis report'!A366 -> ANSWER: Awarding every package to the cheapest bid totals $1,01,30,539 (avg score 76.0/100). Awarding to the highest-scored bid totals $1,17,16,950 (avg score 79.1) — $15,86,411 (15.7%) more. That premium buys better programme, safety and defect performance. | F9: Award on the weighted score, not price alone. Hard-gate any bid with safety < 3.5 or defects > 8% before commercial evaluation.
A10: 2 | B10: P10 | C10: The rate base we price from is a moving target | D10: Benchmarks span $670/sqm in India to $3,677/sqm in Australia, and by type from $1,732/sqm (Data Centre) to $3,859/sqm (Hotel). Global rates look flat (-10.2% since 2022) but India has moved +81.6% in the same window. A single blended rate hides a 2.2x spread and an escalating market. | E10: ='Analysis report'!A656 -> ANSWER: Australia is the most expensive market at $3,677/sqm, India the cheapest at $670/sqm — a 448.5% premium. Global average: $2,430/sqm. | F10: Price every pursuit off the country x type cell, then add an explicit escalation line — never a portfolio average.
A11: ACT II — THE BUILD-UP: where the budget quietly disappears
A12: 3 | B12: P01 | C12: Overrun is the norm, not the exception | D12: 45 of 50 projects finished over budget — $2.15bn planned became $2.53bn spent, a 17.6% portfolio overrun. Residential Towers are worst at 26.3%; the single biggest hit is WT-1028 at $2.47cr (33.1%). Duration explains none of it (r = -0.16), so this is not 'long jobs drift' — it is estimating and control, not time. | E12: ='Analysis report'!A26 -> ANSWER: Worst variance = Residential Tower at 26.3% ($6,26,62,924 over budget). Best = Shopping Mall at 3.4%. Portfolio total: $2,15,23,99,053 budget vs $2,53,19,47,246 actual (17.6%). | F12: Stop treating overrun as project-specific. Re-baseline the estimating allowance by type, starting with Residential Tower and Hospital.
A13: 4 | B13: P03 | C13: The BOQ is measured out, line by line | D13: 72 BOQ lines across 3 projects show $18.3L of gross overrun against only $2.4L of savings — net $15.9L, 9.9% above BOQ. MEP-Electrical is over BOQ on 3 of 3 projects; Plastering on the Auckland hospital is 28.9% over. This is the micro-version of Chapter 3: the overrun is assembled from trades, not accidents. | E13: ='Analysis report'!A192 -> ANSWER: Gross overrun impact is $18,28,491 against $2,37,902 of savings, a net $15,90,589 across the three projects. Worst project: WT-OFF-SYD-02 at $7,16,910 net. | F13: Put MEP-Electrical and wet trades on remeasure-and-report monthly, not at final account.
A14: 5 | B14: P08 | C14: Variations: a live book we have not closed | D14: 45 VOs worth $1.43cr in total. $41.9L is approved, but 15 VOs (33%) worth $33.0L are still pending or under review — unquantified exposure sitting outside the forecast. Consultants raise the most VOs (36%); clients drive the most value ($53.0L). Cost and delay are unrelated (r = 0.12), so cheap variations still bite the programme. | E14: ='Analysis report'!A561 -> ANSWER: 15 of 45 change orders (33.3%) are still Pending or Under Review, carrying $32,97,152 of unquantified cost exposure (23.0% of all VO value). That is the number to put in the risk register until these are determined. | F14: Move the $33.0L undetermined VO book into the risk register this month and force a 30-day determination rule.
A15: ACT III — THE GRIND: the site loses days it never gets back
A16: 6 | B16: P04 | C16: Productivity is not low — it is wildly inconsistent | D16: Across 80 crew-days, Civil & Structure averages 3.54 units/man-hour but with the highest variance of any trade (CV 56.4%); the best crew band delivers 4.16 against 2.68 for the weakest. 20 of 80 days fall below the 25th percentile. The problem is not the workforce's ceiling, it is the floor — broken work fronts and unstable crew sizes. | E16: ='Analysis report'!A239 -> ANSWER: Civil & Structure shows the most variance (std dev 2.00, CV 56.4%); the most consistent is MEP - HVAC (std dev 1.13). High variance points to unstable crew mix or interrupted work fronts. | F16: Standardise crew size to the proven 11–15 band and protect work fronts; chase the bad days, not the average.
A17: 7 | B17: P06 | C17: 1,467 lost days — and most are decisions, not weather | D17: 60 delay events cost 1,467 days, roughly $2.20cr at $15k/day. The top cause is RFI response delay (18.3% of events); consultants own 339 days, the most of any party. Weather accounts for only 10.8%, peaking in November. Testing & Commissioning absorbs 291 days — delay concentrates at the end, where there is no float left. | E17: ='Analysis report'!A463 -> ANSWER: At $15,000/day the portfolio's 1,467 delay days cost roughly $2,20,05,000. The most exposed project is WT-DC-MUM-01 at $57,30,000 (382 days); the least is WT-HOS-AKL-03 at $30,75,000. | F17: Put an SLA on RFI turnaround with the consultant, and start T&C planning at 60% completion, not at handover.
A18: 8 | B18: P09 | C18: Subcontractor scoring is not discriminating | D18: 30 scorecards average 3.43 with only 0.08 points separating the best and worst project. Civil & Structure scores lowest on quality (2.45) and carries 48 defects, yet defect count barely correlates with the quality score (r = -0.09). Two subcontractors breach blacklist criteria. The scorecard is currently describing everyone as average. | E18: ='Analysis report'!A639 -> ANSWER: 2 scorecard(s) breach both blacklist criteria and are listed above. Separately 4 score below 3.0 and 13 carry more than 15 defects. | F18: Rewrite the scoring weights so defects actually move the score, and act on the two blacklist breaches.
A19: 9 | B19: P12 | C19: EVM confirms it: behind and getting worse | D19: Over 36 months, SV is negative in 31 of them and CPI declines from 1.042 to 0.900 — efficiency is eroding, not recovering. SPI closes at 0.794. EAC lands at $2.78cr against a $2.50cr BAC, an 11.1% forecast overrun. Everything in Acts II and III shows up here as one number. | E19: ='Analysis report'!A728 -> ANSWER: EAC at Month 36 is $2,77,85,221 against a BAC of $2,50,00,000 — a projected OVERRUN of $27,85,221 (11.1%). Variance at Completion is -$27,85,221. | F19: Treat EAC vs BAC as the monthly board metric; a recovery plan is due while CPI is 0.90, not when it is 0.80.
A20: ACT IV — THE SQUEEZE: the supply chain sets our programme
A21: 10 | B21: P02 | C21: Materials inflate faster than the contingency | D21: Average material price movement is 7.5%, but RMC M30 (14.8%), Aggregate 20mm (14.6%) and Cement (11.9%) run at double that, and 20 of 90 monthly records exceed 15%. India is the most volatile market (9.8pp std dev). A fixed-price contract priced on a 5% allowance is under-funded before work starts. | E21: ='Analysis report'!A140 -> ANSWER: No material's AVERAGE increase exceeds 15% (highest is RMC M30 at 14.8%), though 20 of 90 individual monthly records are above 15%. Treat the top 3 — RMC M30 (14.8%), Aggregate (20mm) (14.6%), Cement (OPC 53) (11.9%) — as procurement risk and forward-buy / lock rates. | F21: Forward-buy or rate-lock the top 3 movers at award; index-link where the client will accept it.
A22: 11 | B22: P13 | C22: 70% of purchase orders land late | D22: 35 of 50 POs arrive after the expected date, on an average 36.9-day lead time. Copper wiring takes 69 days; vitrified tiles swing between 18 and 74 days (sd 39.6). Not one of the 10 suppliers clears a 90% on-time rate — portfolio on-time performance is 30%. The delay days in Chapter 7 start in this chapter. | E22: ='Analysis report'!A844 -> ANSWER: The scorecard above ranks all 10 suppliers. 0 rate A (90%+ on time), 0 rate B, 0 are watch-list and 10 should be replaced. Portfolio on-time performance is 30.0%. | F22: Dual-source copper and tiles, carry buffer stock, and rebuild the procurement schedule on actual — not quoted — lead times.
A23: ACT V — THE RECKONING: the work is built, the money is not in
A24: 12 | B24: P07 | C24: 2024 closed $7.3m cash-negative | D24: Collected $4.30cr against $5.03cr spent — a $73.2L deficit, with 3 of 4 projects individually negative and the deepest trough in Sep-2024. 17 of 48 project-months collected under 70% of plan, and forecast accuracy is only 76.9%. We are not just collecting badly; we are forecasting badly. | E24: ='Analysis report'!A481 -> ANSWER: At 31-Dec-2024 the portfolio sits at -$73,16,487 cumulative cash. 3 of 4 projects are cash-negative. Best: WT-DC-MUM-01 at $8,39,758; worst: WT-HOS-AKL-03 at -$38,67,202. Collections came in $1,28,96,910 below plan. | F24: Re-forecast cash monthly off actual certification history, and escalate any project-month below 70% of plan within the week.
A25: 13 | B25: P14 | C25: $11.9m outstanding — and most of it is old | D25: $1.19cr remains unpaid on $4.17cr invoiced (71.6% collection). $1.09cr of that is past due and 62.7% of it sits in the 90+ day bucket. Average time to payment is 58 days against ~30-day terms; Brookfield alone holds $41.4L. At 1.5%/month the overdue book has earned $7.98L of claimable interest. | E25: ='Analysis report'!A874 -> ANSWER: Of $1,18,56,858 outstanding, $1,09,01,155 is past due and splits as: $9,98,469 (9.2%) 0–30 days, $30,71,180 (28.2%) 31–60 days, $0 (0.0%) 61–90 days and $68,31,506 (62.7%) 90+ days. The remaining $9,55,703 is not yet due. Average age of past-due debt: 80 days. | F25: Escalate the 90+ bucket to formal recovery and start charging contractual interest — $7.98L is already claimable.
A26: 14 | B26: P15 | C26: The portfolio verdict: amber, and standing still | D26: Of 25 projects, 4 are green, 18 amber and 3 red. 8 are On Hold — tying up $50.6cr of budget doing nothing. 11 projects (44%) sit in the 'late and over cost' quadrant against only 4 true performers. Spend is 48.5% against 49.8% completion, so the portfolio looks on track on paper while the indices say otherwise. | E26: ='Analysis report'!A977 -> ANSWER: The busiest quadrant is "Late and over cost" with 11 of 25 projects (44.0%) and $63,55,84,316 of budget. Only 4 projects are true stars (both indices at or above 1.00). | F26: Force a decision on the 8 on-hold projects (restart or release capital) and put the 3 red projects on recovery plans before taking new work.
A27: 15 | B27: P11 | C27: The missing chapter: risk was never registered | D27: P11 — Risk Register & Probability Matrix — is the one problem of the fifteen with no data sheet in this workbook. That is not a formatting gap, it is the reason the other fourteen chapters read the way they do: the $33.0L of undetermined VOs, the 90+ day debt, the 8 on-hold projects and the 3 red projects are all live risks that nobody scored, owned or priced in advance. Every chapter above is a risk that was managed after it happened. | E27: ="Index lists "&COUNTA(Index!D5:D24)&" problems; 14 have data sheets, P11 (Risk Register) does not. P16-P20 are out of scope for this story." -> Index lists 20 problems; 14 have data sheets, P11 (Risk Register) does not. P16-P20 are out of scope for this story. | F27: Stand up the risk register first: score the exposures already named in Chapters 5, 12, 13 and 14 and give each one an owner and a number.
A29: THE CHAIN, IN ONE LINE
A30: Cheap bid (P05) + drifting rate base (P10) → quantities and variations grow (P01, P03, P08) → site loses 1,467 days to RFIs, suppliers and unstable crews (P04, P06, P09, P13) → materials inflate past the allowance (P02) → EVM confirms 11% overrun (P12) → cash goes negative and debt ages (P07, P14) → portfolio turns amber (P15) — and none of it was ever on a risk register (P11).
A32: THE FIVE MOVES THAT BREAK THE CHAIN
A33: 1. Award on weighted score with a safety/defect hard gate — stop importing the problem at tender (P05, P09).
A34: 2. Re-baseline estimating by country x type and index the top 3 material movers — price the market we are actually in (P10, P02).
A35: 3. Determine the $33.0L VO book within 30 days and remeasure MEP/wet trades monthly — close the leak while it is small (P08, P03, P01).
A36: 4. SLA the RFI turnaround, dual-source the two worst-lead-time materials and fix crew size at the proven band — buy back the 1,467 days (P06, P13, P04, P12).
A37: 5. Re-forecast cash monthly, charge interest on the 90+ bucket and force a restart-or-release call on the 8 on-hold projects (P07, P14, P15, P11).
A39: Sources: every figure traces to the 'Analysis report' sheet (live formulas in column E) and the charts on 'Q&A Chart Dashboard'. Currency shown as in source (Indian digit grouping; cr = crore, L = lakh).

Sheet KPI Dashboard
B1: WT PARTNERSHIP | CONSTRUCTION ANALYTICS DASHBOARD | AB1: CHART DATA — live links to 'Analysis report'. Do not delete; every chart on this dashboard reads from these tables.
AB2: T1 Cost variance by project type (P01 Q2)
B3: Every KPI and chart below is a live formula link to the 'Analysis report' sheet (15 problems, 20 source datasets). Change the source data and this dashboard refreshes automatically. | AB3: Project Type | AC3: Variance %
AB4: ='Analysis report'!A15 -> Residential Tower | AC4: ='Analysis report'!E15 -> 0.26303254
B5: PORTFOLIO BUDGET (USD) | G5: SPEND TO DATE (USD) | L5: AVG PORTFOLIO COMPLETION | Q5: RED-ZONE PROJECTS | AB5: ='Analysis report'!A16 -> IT Park | AC5: ='Analysis report'!E16 -> 0.21567487
B6: ='Analysis report'!B927 -> 1425725823 | G6: ='Analysis report'!D927 -> 690772336 | L6: ='Analysis report'!F928 -> 0.4976 | Q6: ='Analysis report'!B932 -> 3 | AB6: ='Analysis report'!A17 -> University Campus | AC6: ='Analysis report'!E17 -> 0.21727468
B7: =TEXT('Analysis report'!B923,"0")&" live projects | India · Australia · New Zealand" -> 25 live projects | India · Australia · New Zealand | G7: =TEXT('Analysis report'!D927/'Analysis report'!B927,"0.0%")&" of budget drawn" -> 48.5% of budget drawn | L7: ="Avg CPI "&TEXT('Analysis report'!F984,"0.00")&" (target 1.00)" -> Avg CPI 0.93 (target 1.00) | Q7: ="CPI & SPI < 0.90 | "&TEXT('Analysis report'!E990,"$#,##0")&" budget at risk" -> CPI & SPI < 0.90 | $8,75,29,465 budget at risk | AB7: ='Analysis report'!A18 -> Industrial Warehouse | AC7: ='Analysis report'!E18 -> 0.14692435
AB8: ='Analysis report'!A19 -> Data Centre | AC8: ='Analysis report'!E19 -> 0.1216082
B9: PORTFOLIO COST OVERRUN % | G9: PROJECTS OVER BUDGET | L9: TOTAL DELAY DAYS | Q9: NET CASH POSITION (2024) | AB9: ='Analysis report'!A20 -> Hospital | AC9: ='Analysis report'!E20 -> 0.24714839
B10: ='Analysis report'!E25 -> 0.17633728 | G10: ='Analysis report'!C59 -> 0.9 | L10: ='Analysis report'!B462 -> 1467 | Q10: ='Analysis report'!B522 -> -7316487 | AB10: ='Analysis report'!A21 -> Commercial Office | AC10: ='Analysis report'!E21 -> 0.1456331
B11: =TEXT('Analysis report'!D25,"$#,##0")&" over budget on 50 projects" -> $37,95,48,193 over budget on 50 projects | G11: =TEXT('Analysis report'!B59,"0")&" of "&TEXT('Analysis report'!B61,"0")&" projects exceeded budget" -> 45 of 50 projects exceeded budget | L11: ="Cost of delay "&TEXT('Analysis report'!C462,"$#,##0")&" @ $15k/day" -> Cost of delay $2,20,05,000 @ $15k/day | Q11: ="Collection forecast accuracy "&TEXT('Analysis report'!D531,"0.0%") -> Collection forecast accuracy 76.9% | AB11: ='Analysis report'!A22 -> Hotel | AC11: ='Analysis report'!E22 -> 0.13721378
AB12: ='Analysis report'!A23 -> Metro Station | AC12: ='Analysis report'!E23 -> 0.13531167
B13: OUTSTANDING RECEIVABLES | G13: UNRESOLVED VO EXPOSURE | L13: SUPPLIER ON-TIME DELIVERY | Q13: EVM PROJECTED OVERRUN | AB13: ='Analysis report'!A24 -> Shopping Mall | AC13: ='Analysis report'!E24 -> 0.033802807
B14: ='Analysis report'!F848 -> 11856858 | G14: ='Analysis report'!D560 -> 3297152 | L14: =1-'Analysis report'!D816 -> 0.3 | Q14: ='Analysis report'!D727 -> 0.11140886
B15: =TEXT('Analysis report'!C872,"$#,##0")&" of it is 90+ days overdue ("&TEXT('Analysis report'!C872/'Analysis report'!F848,"0.0%")&")" -> $68,31,506 of it is 90+ days overdue (57.6%) | G15: =TEXT('Analysis report'!B560,"0")&" of 45 variations pending / under review" -> 15 of 45 variations pending / under review | L15: =TEXT('Analysis report'!B816,"0")&" of "&TEXT('Analysis report'!F816,"0")&" POs late, avg "&TEXT('Analysis report'!D817,"0.0")&" days" -> 35 of 50 POs late, avg 5.9 days | Q15: ="EAC "&TEXT('Analysis report'!D726,"$#,##0")&" vs BAC "&TEXT('Analysis report'!B726,"$#,##0") -> EAC $2,77,85,221 vs BAC $2,50,00,000 | AB15: T2 Top 5 cost overruns (P01 Q3)
AB16: Project | AC16: Absolute Overrun USD
AB17: ='Analysis report'!C30 -> Residential Tower Per-29 | AC17: ='Analysis report'!E30 -> 24654239
B18: 1. COST & BUDGET PERFORMANCE — where the overrun is coming from | AB18: ='Analysis report'!C31 -> Residential Tower Hyd-33 | AC18: ='Analysis report'!E31 -> 21628203
AB19: ='Analysis report'!C32 -> IT Park Syd-34 | AC19: ='Analysis report'!E32 -> 19739335
AB20: ='Analysis report'!C33 -> University Campus Kol-35 | AC20: ='Analysis report'!E33 -> 19335358
AB21: ='Analysis report'!C34 -> Industrial Warehouse Can-44 | AC21: ='Analysis report'!E34 -> 19116067
AB23: T3 Cost per sqm by country (P10 Q1)
AB24: Country | AC24: Avg Cost per sqm USD
AB25: ='Analysis report'!A652 -> Australia | AC25: ='Analysis report'!B652 -> 3677.1111
AB26: ='Analysis report'!A653 -> India | AC26: ='Analysis report'!B653 -> 670.4
AB27: ='Analysis report'!A654 -> New Zealand | AC27: ='Analysis report'!B654 -> 2993
AB29: T4 Cost overrun by country (P01 Q1)
AB30: Country | AC30: Avg Cost Overrun %
AB31: ='Analysis report'!A8 -> Australia | AC31: ='Analysis report'!B8 -> 0.16732437
AB32: ='Analysis report'!A9 -> India | AC32: ='Analysis report'!B9 -> 0.15763933
AB33: ='Analysis report'!A10 -> New Zealand | AC33: ='Analysis report'!B10 -> 0.19747604
AB35: T5 Delay cause Pareto (P06 Q1)
AB36: Delay Cause | AC36: Events | AD36: Cumulative %
AB37: ='Analysis report'!B387 -> RFI Response Delay | AC37: ='Analysis report'!C387 -> 11 | AD37: ='Analysis report'!E387 -> 0.18333333
AB38: ='Analysis report'!B388 -> Permit Delay | AC38: ='Analysis report'!C388 -> 8 | AD38: ='Analysis report'!E388 -> 0.31666667
B39: 2. GEOGRAPHY — cost levels and overrun by country | AB39: ='Analysis report'!B389 -> Material Delay | AC39: ='Analysis report'!C389 -> 8 | AD39: ='Analysis report'!E389 -> 0.45
AB40: ='Analysis report'!B390 -> Client Decision Pending | AC40: ='Analysis report'!C390 -> 6 | AD40: ='Analysis report'!E390 -> 0.55
AB41: ='Analysis report'!B391 -> Labour Shortage | AC41: ='Analysis report'!C391 -> 5 | AD41: ='Analysis report'!E391 -> 0.63333333
AB42: ='Analysis report'!B392 -> Equipment Breakdown | AC42: ='Analysis report'!C392 -> 5 | AD42: ='Analysis report'!E392 -> 0.71666667
AB43: ='Analysis report'!B393 -> Rework | AC43: ='Analysis report'!C393 -> 5 | AD43: ='Analysis report'!E393 -> 0.8
AB44: ='Analysis report'!B394 -> Weather | AC44: ='Analysis report'!C394 -> 5 | AD44: ='Analysis report'!E394 -> 0.88333333
AB45: ='Analysis report'!B395 -> Design Change | AC45: ='Analysis report'!C395 -> 4 | AD45: ='Analysis report'!E395 -> 0.95
AB46: ='Analysis report'!B396 -> Subcontractor Default | AC46: ='Analysis report'!C396 -> 3 | AD46: ='Analysis report'!E396 -> 1
AB48: T6 Delay days by activity (P06 Q5)
AB49: Activity | AC49: Delay Days
AB50: ='Analysis report'!A443 -> Foundation | AC50: ='Analysis report'!C443 -> 128
AB51: ='Analysis report'!A444 -> Superstructure | AC51: ='Analysis report'!C444 -> 84
AB52: ='Analysis report'!A445 -> MEP Rough-In | AC52: ='Analysis report'!C445 -> 201
AB53: ='Analysis report'!A446 -> Facade Installation | AC53: ='Analysis report'!C446 -> 133
AB54: ='Analysis report'!A447 -> Interior Works | AC54: ='Analysis report'!C447 -> 182
AB55: ='Analysis report'!A448 -> External Works | AC55: ='Analysis report'!C448 -> 143
AB56: ='Analysis report'!A449 -> Landscape | AC56: ='Analysis report'!C449 -> 183
AB57: ='Analysis report'!A450 -> Testing & Commissioning | AC57: ='Analysis report'!C450 -> 291
AB58: ='Analysis report'!A451 -> Handover Prep | AC58: ='Analysis report'!C451 -> 122
B60: 3. SCHEDULE & DELAY ROOT CAUSE — 1,467 delay days explained | AB60: T7 EVM S-curve (P12 Q4)
AB61: Month | AC61: PV | AD61: EV | AE61: AC
AB62: ='Analysis report'!A732 -> Month 1 | AC62: ='Analysis report'!B732 -> 713955 | AD62: ='Analysis report'!C732 -> 583077 | AE62: ='Analysis report'!D732 -> 559427
AB63: ='Analysis report'!A733 -> Month 2 | AC63: ='Analysis report'!B733 -> 1375080 | AD63: ='Analysis report'!C733 -> 1314419 | AE63: ='Analysis report'!D733 -> 1552686
AB64: ='Analysis report'!A734 -> Month 3 | AC64: ='Analysis report'!B734 -> 1996674 | AD64: ='Analysis report'!C734 -> 1848591 | AE64: ='Analysis report'!D734 -> 2172516
AB65: ='Analysis report'!A735 -> Month 4 | AC65: ='Analysis report'!B735 -> 2659718 | AD65: ='Analysis report'!C735 -> 2790438 | AE65: ='Analysis report'!D735 -> 2676937
AB66: ='Analysis report'!A736 -> Month 5 | AC66: ='Analysis report'!B736 -> 3522912 | AD66: ='Analysis report'!C736 -> 3497510 | AE66: ='Analysis report'!D736 -> 3244267
AB67: ='Analysis report'!A737 -> Month 6 | AC67: ='Analysis report'!B737 -> 4311364 | AD67: ='Analysis report'!C737 -> 4279745 | AE67: ='Analysis report'!D737 -> 4009086
AB68: ='Analysis report'!A738 -> Month 7 | AC68: ='Analysis report'!B738 -> 5076108 | AD68: ='Analysis report'!C738 -> 3884193 | AE68: ='Analysis report'!D738 -> 4572625
AB69: ='Analysis report'!A739 -> Month 8 | AC69: ='Analysis report'!B739 -> 5518420 | AD69: ='Analysis report'!C739 -> 5338129 | AE69: ='Analysis report'!D739 -> 5598832
AB70: ='Analysis report'!A740 -> Month 9 | AC70: ='Analysis report'!B740 -> 6176705 | AD70: ='Analysis report'!C740 -> 5423142 | AE70: ='Analysis report'!D740 -> 5456673
AB71: ='Analysis report'!A741 -> Month 10 | AC71: ='Analysis report'!B741 -> 7227989 | AD71: ='Analysis report'!C741 -> 6017261 | AE71: ='Analysis report'!D741 -> 6220665
AB72: ='Analysis report'!A742 -> Month 11 | AC72: ='Analysis report'!B742 -> 7370482 | AD72: ='Analysis report'!C742 -> 6885739 | AE72: ='Analysis report'!D742 -> 7471668
AB73: ='Analysis report'!A743 -> Month 12 | AC73: ='Analysis report'!B743 -> 8456065 | AD73: ='Analysis report'!C743 -> 7607646 | AE73: ='Analysis report'!D743 -> 8861641
... AB80: ='Analysis report'!A750 -> Month 19 | AC80: ='Analysis report'!B750 -> 12569110 | AD80: ='Analysis report'!C750 -> 11678398 | AE80: ='Analysis report'!D750 -> 10613223
B81: 4. EARNED VALUE & PROJECT HEALTH — are we on cost and on time? | AB81: ='Analysis report'!A751 -> Month 20 | AC81: ='Analysis report'!B751 -> 14320401 | AD81: ='Analysis report'!C751 -> 11947221 | AE81: ='Analysis report'!D751 -> 13650848
AB82: ='Analysis report'!A752 -> Month 21 | AC82: ='Analysis report'!B752 -> 14542039 | AD82: ='Analysis report'!C752 -> 12465870 | AE82: ='Analysis report'!D752 -> 13403261
AB83: ='Analysis report'!A753 -> Month 22 | AC83: ='Analysis report'!B753 -> 14869497 | AD83: ='Analysis report'!C753 -> 11864184 | AE83: ='Analysis report'!D753 -> 11559952
AB84: ='Analysis report'!A754 -> Month 23 | AC84: ='Analysis report'!B754 -> 15558785 | AD84: ='Analysis report'!C754 -> 14160157 | AE84: ='Analysis report'!D754 -> 16105354
AB85: ='Analysis report'!A755 -> Month 24 | AC85: ='Analysis report'!B755 -> 17061766 | AD85: ='Analysis report'!C755 -> 16707135 | AE85: ='Analysis report'!D755 -> 19786940
AB86: ='Analysis report'!A756 -> Month 25 | AC86: ='Analysis report'!B756 -> 17492521 | AD86: ='Analysis report'!C756 -> 18276175 | AE86: ='Analysis report'!D756 -> 18578220
AB87: ='Analysis report'!A757 -> Month 26 | AC87: ='Analysis report'!B757 -> 18841344 | AD87: ='Analysis report'!C757 -> 19735602 | AE87: ='Analysis report'!D757 -> 18790535
AB88: ='Analysis report'!A758 -> Month 27 | AC88: ='Analysis report'!B758 -> 18256033 | AD88: ='Analysis report'!C758 -> 15433674 | AE88: ='Analysis report'!D758 -> 17307808
AB89: ='Analysis report'!A759 -> Month 28 | AC89: ='Analysis report'!B759 -> 19169856 | AD89: ='Analysis report'!C759 -> 17779442 | AE89: ='Analysis report'!D759 -> 19753597
AB90: ='Analysis report'!A760 -> Month 29 | AC90: ='Analysis report'!B760 -> 19840193 | AD90: ='Analysis report'!C760 -> 18258838 | AE90: ='Analysis report'!D760 -> 17211341
AB91: ='Analysis report'!A761 -> Month 30 | AC91: ='Analysis report'!B761 -> 21767434 | AD91: ='Analysis report'!C761 -> 21789398 | AE91: ='Analysis report'!D761 -> 24907904
AB92: ='Analysis report'!A762 -> Month 31 | AC92: ='Analysis report'!B762 -> 22540417 | AD92: ='Analysis report'!C762 -> 20571227 | AE92: ='Analysis report'!D762 -> 19597529
AB93: ='Analysis report'!A763 -> Month 32 | AC93: ='Analysis report'!B763 -> 21195474 | AD93: ='Analysis report'!C763 -> 16253757 | AE93: ='Analysis report'!D763 -> 17562165
... AB97: ='Analysis report'!A767 -> Month 36 | AC97: ='Analysis report'!B767 -> 23898889 | AD97: ='Analysis report'!C767 -> 18983212 | AE97: ='Analysis report'!D767 -> 21098110
AB99: T8 SPI vs CPI bubble (P15 Q4)
AB100: SPI | AC100: CPI | AD100: Budget USD
AB101: ='Analysis report'!A946 -> 0.91 | AC101: ='Analysis report'!B946 -> 0.79 | AD101: ='Analysis report'!C946 -> 95528859
B102: 5. CASH FLOW & RECEIVABLES — the liquidity problem | AB102: ='Analysis report'!A947 -> 1 | AC102: ='Analysis report'!B947 -> 1.12 | AD102: ='Analysis report'!C947 -> 93252435
AB103: ='Analysis report'!A948 -> 1.06 | AC103: ='Analysis report'!B948 -> 0.99 | AD103: ='Analysis report'!C948 -> 60343779
AB104: ='Analysis report'!A949 -> 0.9 | AC104: ='Analysis report'!B949 -> 1.04 | AD104: ='Analysis report'!C949 -> 53319528
AB105: ='Analysis report'!A950 -> 0.81 | AC105: ='Analysis report'!B950 -> 1.09 | AD105: ='Analysis report'!C950 -> 45512501
AB106: ='Analysis report'!A951 -> 0.78 | AC106: ='Analysis report'!B951 -> 0.86 | AD106: ='Analysis report'!C951 -> 17655004
AB107: ='Analysis report'!A952 -> 1.16 | AC107: ='Analysis report'!B952 -> 1.04 | AD107: ='Analysis report'!C952 -> 17335296
AB108: ='Analysis report'!A953 -> 1.11 | AC108: ='Analysis report'!B953 -> 0.79 | AD108: ='Analysis report'!C953 -> 97555887
AB109: ='Analysis report'!A954 -> 1.16 | AC109: ='Analysis report'!B954 -> 0.88 | AD109: ='Analysis report'!C954 -> 15533057
AB110: ='Analysis report'!A955 -> 1.02 | AC110: ='Analysis report'!B955 -> 1 | AD110: ='Analysis report'!C955 -> 92614538
AB111: ='Analysis report'!A956 -> 0.86 | AC111: ='Analysis report'!B956 -> 1.03 | AD111: ='Analysis report'!C956 -> 47857940
AB112: ='Analysis report'!A957 -> 0.75 | AC112: ='Analysis report'!B957 -> 0.92 | AD112: ='Analysis report'!C957 -> 84877290
AB113: ='Analysis report'!A958 -> 0.72 | AC113: ='Analysis report'!B958 -> 0.91 | AD113: ='Analysis report'!C958 -> 16079017
AB114: ='Analysis report'!A959 -> 0.77 | AC114: ='Analysis report'!B959 -> 0.97 | AD114: ='Analysis report'!C959 -> 98666595
... AB122: ='Analysis report'!A967 -> 0.7 | AC122: ='Analysis report'!B967 -> 0.91 | AD122: ='Analysis report'!C967 -> 12124981
...

Sheet P01-CostOverrun
A1: c
A2: Scenario: WT manages 50 projects across India, Australia & NZ. Analyse which projects exceeded budget and why.
A4: Project_ID | B4: Project_Name | C4: City | D4: Country | E4: Type | F4: Budgeted_Cost_USD | G4: Actual_Cost_USD | H4: Duration_Months | I4: Variance_USD | J4: Variance_% | K4: Absolute_Variance_USD
A5: WT-1028 | B5: Residential Tower Per-29 | C5: Perth | D5: Australia | E5: Residential Tower | F5: 74394227 | G5: 99048466 | H5: 39 | I5: =G5-F5 -> 24654239 | J5: =I5/F5 -> 0.33139989 | K5: =ABS(I5) -> 24654239
A6: WT-1032 | B6: Residential Tower Hyd-33 | C6: Hyderabad | D6: India | E6: Residential Tower | F6: 65791320 | G6: 87419523 | H6: 16 | I6: =G6-F6 -> 21628203 | J6: =I6/F6 -> 0.32873946 | K6: =ABS(I6) -> 21628203
A7: WT-1033 | B7: IT Park Syd-34 | C7: Sydney | D7: Australia | E7: IT Park | F7: 58792612 | G7: 78531947 | H7: 40 | I7: =G7-F7 -> 19739335 | J7: =I7/F7 -> 0.33574516 | K7: =ABS(I7) -> 19739335
A8: WT-1034 | B8: University Campus Kol-35 | C8: Kolkata | D8: India | E8: University Campus | F8: 55551839 | G8: 74887197 | H8: 47 | I8: =G8-F8 -> 19335358 | J8: =I8/F8 -> 0.34805973 | K8: =ABS(I8) -> 19335358
A9: WT-1043 | B9: Industrial Warehouse Can-44 | C9: Canberra | D9: Australia | E9: Industrial Warehouse | F9: 64682989 | G9: 83799056 | H9: 9 | I9: =G9-F9 -> 19116067 | J9: =I9/F9 -> 0.29553469 | K9: =ABS(I9) -> 19116067
A10: WT-1031 | B10: Data Centre Del-32 | C10: Delhi | D10: India | E10: Data Centre | F10: 67228535 | G10: 85811127 | H10: 40 | I10: =G10-F10 -> 18582592 | J10: =I10/F10 -> 0.2764093 | K10: =ABS(I10) -> 18582592
A11: WT-1024 | B11: Data Centre Mum-25 | C11: Mumbai | D11: India | E11: Data Centre | F11: 74070937 | G11: 92614679 | H11: 47 | I11: =G11-F11 -> 18543742 | J11: =I11/F11 -> 0.25035112 | K11: =ABS(I11) -> 18543742
A12: WT-1026 | B12: University Campus Mum-27 | C12: Mumbai | D12: India | E12: University Campus | F12: 69187530 | G12: 86815466 | H12: 38 | I12: =G12-F12 -> 17627936 | J12: =I12/F12 -> 0.25478487 | K12: =ABS(I12) -> 17627936
A13: WT-1049 | B13: Hospital Auc-50 | C13: Auckland | D13: New Zealand | E13: Hospital | F13: 55826716 | G13: 73187548 | H13: 16 | I13: =G13-F13 -> 17360832 | J13: =I13/F13 -> 0.31097713 | K13: =ABS(I13) -> 17360832
A14: WT-1027 | B14: University Campus Che-28 | C14: Chennai | D14: India | E14: University Campus | F14: 70137358 | G14: 83715114 | H14: 15 | I14: =G14-F14 -> 13577756 | J14: =I14/F14 -> 0.19358807 | K14: =ABS(I14) -> 13577756
A15: WT-1044 | B15: Commercial Office Che-45 | C15: Chennai | D15: India | E15: Commercial Office | F15: 56038913 | G15: 69560286 | H15: 12 | I15: =G15-F15 -> 13521373 | J15: =I15/F15 -> 0.24128543 | K15: =ABS(I15) -> 13521373
A16: WT-1015 | B16: Hospital Chr-16 | C16: Christchurch | D16: New Zealand | E16: Hospital | F16: 45524491 | G16: 58596428 | H16: 9 | I16: =G16-F16 -> 13071937 | J16: =I16/F16 -> 0.28714076 | K16: =ABS(I16) -> 13071937
... A54: WT-1047 | B54: IT Park Gol-48 | C54: Gold Coast | D54: Australia | E54: IT Park | F54: 15141087 | G54: 14690417 | H54: 40 | I54: =G54-F54 -> -450670 | J54: =I54/F54 -> -0.029764706 | K54: =ABS(I54) -> 450670
A56: ANALYSIS QUESTIONS
A57: Q1. Which country has the highest average cost overrun percentage?
A58: Q2. What is the total budget vs actual cost for each project type? Which type has the worst variance?
A59: Q3. Identify the Top 5 projects with the highest absolute cost overrun (in USD).
A60: Q4. Is there a correlation between project duration and cost overrun percentage?
A61: Q5. Create a pivot table showing average overrun % by Country × Project Type.
A62: Q6. What percentage of projects came in under budget vs over budget?
A63: Q7. Which city has the most cost-efficient project delivery?

Sheet P01
A1: Cost Over Run Analysis
A4: Q1
A7: Country | B7: Average of Variance_%
A8: Australia | B8: 0.16732437
A9: India | B9: 0.15763933
A10: New Zealand | B10: 0.19747604
A11: Grand Total | B11: 0.16612198
A13: The Country with the highest average cost overrun percentage is Newzealand, with an average overrun of 19.75%
A15: Q2
A18: Project Type | B18: Total Budget | C18: Actual Cost | D18: Total Variance | E18: Average of Variance_%
A19: Commercial Office | B19: 139292114 | C19: 159577657 | D19: 20285543 | E19: 0.13323602
A20: Data Centre | B20: 377404871 | C20: 423300399 | D20: 45895528 | E20: 0.10730588
A21: Hospital | B21: 202218749 | C21: 252196787 | D21: 49978038 | E21: 0.25210129
A22: Hotel | B22: 276402274 | C22: 314328476 | D22: 37926202 | E22: 0.13762155
A23: Industrial Warehouse | B23: 162936980 | C23: 186876390 | D23: 23939410 | E23: 0.1314705
A24: IT Park | B24: 207257585 | C24: 251957838 | D24: 44700253 | E24: 0.18258894
A25: Metro Station | B25: 194389591 | C25: 220692772 | D25: 26303181 | E25: 0.15213723
A26: Residential Tower | B26: 238232594 | C26: 300895518 | D26: 62662924 | E26: 0.24593854
A27: Shopping Mall | B27: 49683626 | C27: 51363072 | D27: 1679446 | E27: 0.033802807
A28: University Campus | B28: 304580669 | C28: 370758337 | D28: 66177668 | E28: 0.21100059
A29: Grand Total | B29: 2152399053 | C29: 2531947246 | D29: 379548193 | E29: 0.16612198
A31: Hospital has the worst variance percentage with an average cost overrun of 25.21%. But university campus has the highest total cost variance at USD 66,177,668.
A34: Q3
A37: Residential Tower Per-29
A38: Residential Tower Hyd-33 | B38: This Five project are having highest absolute cost over run variance in USD, this found by sorting and highlighted via conditional formatting of top 5.
A39: IT Park Syd-34
A40: University Campus Kol-35
A41: Industrial Warehouse Can-44
A43: Q4
A46: =CORREL('P01-CostOverrun'!H5:H54,'P01-CostOverrun'!J5:J54) -> -0.15637931
A48: There is a weak negative correlation (-0.156) between project duration and cost overrun percentage. This suggests that longer project durations are slightly associated with lower cost overrun percentages in this dataset. However, the relationship is very weak and does not establish causation.
A52: Q5
A55: Average of Variance_% | B55: Column Labels
A56: Row Labels | B56: Commercial Office | C56: Data Centre | D56: Hospital | E56: Hotel | F56: Industrial Warehouse | G56: IT Park | H56: Metro Station | I56: Residential Tower | J56: Shopping Mall | K56: University Campus | L56: Grand Total
A57: Australia | C57: 0.11293848 | D57: 0.18570627 | E57: 0.22210857 | F57: 0.29553469 | G57: 0.15299023 | H57: 0.09327325 | I57: 0.23322555 | K57: 0.088721909 | L57: 0.16732437
A58: India | B58: 0.13323602 | C58: 0.12639265 | D58: 0.23834115 | E58: 0.074256278 | F58: 0.061148534 | G58: 0.18083416 | H58: 0.057979113 | I58: 0.25865153 | J58: 0.033802807 | K58: 0.27213993 | L58: 0.15763933
A59: New Zealand | C59: -0.018479937 | D59: 0.29905895 | F59: 0.037728288 | G59: 0.24880551 | H59: 0.25808028 | L59: 0.19747604
A60: Grand Total | B60: 0.13323602 | C60: 0.10730588 | D60: 0.25210129 | E60: 0.13762155 | F60: 0.1314705 | G60: 0.18258894 | H60: 0.15213723 | I60: 0.24593854 | J60: 0.033802807 | K60: 0.21100059 | L60: 0.16612198
A62: New Zealand has the highest overall average cost overrun (19.75%). Hospital projects in New Zealand show the highest country-type average (29.91%).
A65: Q6
A68: Total Project | B68: Over Budget | C68: Under Budget | D68: On Budget
A69: =COUNTA('P01-CostOverrun'!A5:A54) -> 50 | B69: =COUNTIF('P01-CostOverrun'!I5:I54,">0")/COUNTA('P01-CostOverrun'!A5:A54) -> 0.9 | C69: =COUNTIF('P01-CostOverrun'!I5:I54,"<0")/COUNTA('P01-CostOverrun'!A5:A54) -> 0.1 | D69: =COUNTIF('P01-CostOverrun'!I5:I54,"=0")/COUNTA('P01-CostOverrun'!A5:A54) -> 0
A71: Out of 50 projects, 90% (45 projects) exceeded their budget, while 10% (5 projects) were completed under budget. No projects were completed exactly on budget.
A77: City | B77: Average of Variance_%
A78: Gold Coast | B78: -0.029764706
A79: Pune | B79: 0.050976818
A80: Ahmedabad | B80: 0.095679451
A81: Brisbane | B81: 0.11293848
A82: Adelaide | B82: 0.14062385 | C82: The city with the lowest average cost overrun percentage is Gold coast and Pune, with an average overrun of -2.98% and 5.10% respectively.
A83: Hamilton | B83: 0.15078802
A84: Mumbai | B84: 0.15776248
A85: Delhi | B85: 0.16715203
A86: Chennai | B86: 0.16725679
A87: Christchurch | B87: 0.17248878
A88: Perth | B88: 0.18796888
A89: Canberra | B89: 0.20543072
A90: Kolkata | B90: 0.2090111
A91: Wellington | B91: 0.25231279
A92: Hyderabad | B92: 0.25865153
A93: Auckland | B93: 0.31097713
A94: Bangalore | B94: 0.312168
... A96: Grand Total | B96: 0.16612198

Sheet P02-MaterialPrice
A1: PROBLEM 2: Material Price Fluctuation Tracker
A2: Scenario: Track monthly prices of 15 key construction materials over 18 months to forecast procurement budgets.
A4: Month | B4: Material | C4: Unit | D4: Base_Price_USD | E4: Current_Price_USD | F4: Supplier_City | G4: Country | H4: Price_Change_% | I4: Procurement Risk
A5: 2024-04 | B5: Waterproofing Membrane | C5: sqm | D5: 15 | E5: 18.73 | F5: Delhi | G5: India | H5: =(E5-D5)/D5 -> 0.24866667 | I5: =IF(H5>15%,"high risk", "Normal") -> high risk
A6: 2024-09 | B6: Cement (OPC 53) | C6: MT | D6: 85 | E6: 105.52 | F6: Hyderabad | G6: India | H6: =(E6-D6)/D6 -> 0.24141176 | I6: =IF(H6>15%,"high risk", "Normal") -> high risk
A7: 2025-01 | B7: Aluminium Facade | C7: sqm | D7: 120 | E7: 147.98 | F7: Brisbane | G7: Australia | H7: =(E7-D7)/D7 -> 0.23316667 | I7: =IF(H7>15%,"high risk", "Normal") -> high risk
A8: 2024-03 | B8: Bricks (AAC) | C8: 1000 nos | D8: 380 | E8: 467.68 | F8: Hamilton | G8: New Zealand | H8: =(E8-D8)/D8 -> 0.23073684 | I8: =IF(H8>15%,"high risk", "Normal") -> high risk
A9: 2024-05 | B9: Tiles (Vitrified) | C9: sqm | D9: 18 | E9: 22.1 | F9: Delhi | G9: India | H9: =(E9-D9)/D9 -> 0.22777778 | I9: =IF(H9>15%,"high risk", "Normal") -> high risk
A10: 2024-09 | B10: PVC Conduits | C10: m | D10: 3 | E10: 3.68 | F10: Ahmedabad | G10: India | H10: =(E10-D10)/D10 -> 0.22666667 | I10: =IF(H10>15%,"high risk", "Normal") -> high risk
A11: 2024-02 | B11: Sand (River) | C11: cum | D11: 25 | E11: 30.58 | F11: Wellington | G11: New Zealand | H11: =(E11-D11)/D11 -> 0.2232 | I11: =IF(H11>15%,"high risk", "Normal") -> high risk
A12: 2024-05 | B12: Structural Steel | C12: MT | D12: 950 | E12: 1149.65 | F12: Perth | G12: Australia | H12: =(E12-D12)/D12 -> 0.21015789 | I12: =IF(H12>15%,"high risk", "Normal") -> high risk
A13: 2024-11 | B13: Aggregate (20mm) | C13: cum | D13: 22 | E13: 26.52 | F13: Sydney | G13: Australia | H13: =(E13-D13)/D13 -> 0.20545455 | I13: =IF(H13>15%,"high risk", "Normal") -> high risk
A14: 2025-05 | B14: Cement (OPC 53) | C14: MT | D14: 85 | E14: 102.04 | F14: Delhi | G14: India | H14: =(E14-D14)/D14 -> 0.20047059 | I14: =IF(H14>15%,"high risk", "Normal") -> high risk
A15: 2024-05 | B15: Aluminium Facade | C15: sqm | D15: 120 | E15: 143.42 | F15: Melbourne | G15: Australia | H15: =(E15-D15)/D15 -> 0.19516667 | I15: =IF(H15>15%,"high risk", "Normal") -> high risk
A16: 2025-03 | B16: MS Pipes | C16: m | D16: 12 | E16: 14.34 | F16: Melbourne | G16: Australia | H16: =(E16-D16)/D16 -> 0.195 | I16: =IF(H16>15%,"high risk", "Normal") -> high risk
... A94: 2025-01 | B94: Glass (DGU) | C94: sqm | D94: 95 | E94: 87.45 | F94: Christchurch | G94: New Zealand | H94: =(E94-D94)/D94 -> -0.079473684 | I94: =IF(H94>15%,"high risk", "Normal") -> Normal
A96: ANALYSIS QUESTIONS
A97: Q1. Which material has shown the highest average price increase over 18 months?
A98: Q2. Create a line chart showing monthly price trend for TMT Steel and Cement.
A99: Q3. Which country has the most volatile material pricing? (Use standard deviation)
A100: Q4. Identify the top 3 materials with price increase > 15% — flag them as procurement risk.
A101: Q5. What is the average price change % by material across all months?
A102: Q6. If WT needs 500 MT of steel next quarter, what is the projected cost based on the trend?

Sheet P02
A1: Material Price Fluctuation
A4: Q1
A7: Materials | B7: Average of Price_Change_%
A8: Aggregate (20mm) | B8: 0.14609091
A9: Aluminium Facade | B9: 0.11697917
A10: Bricks (AAC) | B10: 0.077399123
A11: Cement (OPC 53) | B11: 0.11856863
A12: Copper Wiring | B12: 0.01925
A13: Glass (DGU) | B13: 0.043934211 | C13: RMC M30 has shown the highest average price increase over the 18 month period, with an average price increase of 14.78%.
A14: MS Pipes | B14: 0.099375
A15: Plywood (Marine) | B15: 0.092555556
A16: PVC Conduits | B16: 0.030416667
A17: RMC M30 | B17: 0.1478
A18: Sand (River) | B18: 0.0952
A19: Structural Steel | B19: 0.069677193
A20: Tiles (Vitrified) | B20: 0.083611111
A21: TMT Steel (Fe500) | B21: 0.039138462
A22: Waterproofing Membrane | B22: 0.0252
A23: Grand Total | B23: 0.075402982
A26: Q2
A29: Average of Current_Price_USD | B29: Material Filter
A30: Month timeline | B30: Cement (OPC 53) | C30: TMT Steel (Fe500) | D30: Grand Total
A31: 2024-01 | B31: 96.77 | C31: 1 | D31: 96.77
A32: 2024-02 | B32: 94.59 | C32: 1 | D32: 94.59
A33: 2024-03 | B33: 1 | C33: 710.14 | D33: 710.14
A34: 2024-06 | B34: 81.11 | C34: 1 | D34: 81.11
A35: 2024-09 | B35: 105.52 | C35: 1 | D35: 105.52
A36: 2024-12 | B36: 90.44 | C36: 1 | D36: 90.44
A37: 2025-01 | B37: 1 | C37: 607.52 | D37: 607.52
A38: 2025-02 | B38: 1 | C38: 688.19 | D38: 688.19 | E38: The line chart illustrates the monthly price trends of TMT Steel and Cement over the 18-month period. It helps identify price fluctuations and changes in procurement costs over time.
A39: 2025-05 | B39: 102.04 | C39: 1 | D39: 102.04
A40: 2025-06 | B40: 1 | C40: 695.91 | D40: 695.91
A41: Grand Total | B41: 95.078333 | C41: 675.44 | D41: 327.223
A59: Q3
A62: Country | B62: StdDev of Price_Change_%
A63: Australia | B63: 0.092102807 | C63: India has the most volatile material prices, with a standard deviation of 9.79%, indicating greater fluctuations in price changes compared to other countries.
A64: India | B64: 0.097922415
A65: New Zealand | B65: 0.089924746
A66: Grand Total | B66: 0.093298287
A68: Q4
A72: Row Labels | B72: Max of Price_Change_%
A73: Waterproofing Membrane | B73: 0.24866667
A74: Cement (OPC 53) | B74: 0.24141176
A75: Aluminium Facade | B75: 0.23316667 | C75: The top 3 materials with price increases exceeding 15% are Waterproffing, Cement, and Alluminium. These materials are flagged as procurement risks due to significant price increases.
A76: Bricks (AAC) | B76: 0.23073684
A77: Tiles (Vitrified) | B77: 0.22777778
A78: PVC Conduits | B78: 0.22666667
A79: Sand (River) | B79: 0.2232
A80: Structural Steel | B80: 0.21015789
A81: Aggregate (20mm) | B81: 0.20545455
A82: MS Pipes | B82: 0.195
A83: RMC M30 | B83: 0.18613333
A84: Glass (DGU) | B84: 0.14031579
A85: Copper Wiring | B85: 0.14
A86: Plywood (Marine) | B86: 0.13733333
A87: TMT Steel (Fe500) | B87: 0.092523077
A88: Grand Total | B88: 0.24866667
A90: Q5
A93: Materials | B93: Average of Price_Change_%
A94: RMC M30 | B94: 0.1478
A95: Aggregate (20mm) | B95: 0.14609091
A96: Cement (OPC 53) | B96: 0.11856863
A97: Aluminium Facade | B97: 0.11697917 | C97: The average price change for each material was calculated across the 18-month period using the Average function in a Pivot Table. RMC M30 experienced the highest average price change, while Copper wiring experienced the lowest.
A98: MS Pipes | B98: 0.099375
A99: Sand (River) | B99: 0.0952
A100: Plywood (Marine) | B100: 0.092555556
A101: Tiles (Vitrified) | B101: 0.083611111
A102: Bricks (AAC) | B102: 0.077399123
A103: Structural Steel | B103: 0.069677193
A104: Glass (DGU) | B104: 0.043934211
A105: TMT Steel (Fe500) | B105: 0.039138462
A106: PVC Conduits | B106: 0.030416667
A107: Waterproofing Membrane | B107: 0.0252
A108: Copper Wiring | B108: 0.01925
A109: Grand Total | B109: 0.075402982
A111: Q6
A114: Average of Current_Price_USD | B114: TMT Steel Material
A115: Month | B115: TMT Steel (Fe500) | C115: Grand Total
A116: 2024-03 | B116: 710.14 | C116: 710.14
A117: 2025-01 | B117: 607.52 | C117: 607.52
A118: 2025-02 | B118: 688.19 | C118: 688.19
A119: 2025-06 | B119: 695.91 | C119: 695.91
A120: Grand Total | B120: 675.44 | C120: 675.44
A123: Month Index | B123: Month | C123: AVG TMT Price | D123: forecast
A124: 1 | B124: =TEXT(EDATE(DATE(2024,1,1),A124-1),"yyyy-mm") -> 2024-01 | C124: =IFERROR(AVERAGEIFS('P02-MaterialPrice'!$E:$E,'P02-MaterialPrice'!$A:$A,B124,'P02-MaterialPrice'!$B:$B,"TMT Steel (Fe500)"),"") | D124: {=_xlfn.FORECAST.LINEAR(19,_xlfn._xlws.FILTER($C$124:$C$141,ISNUMBER($C$124:$C$141)),_xlfn._xlws.FILTER($A$124:$A$141,ISNUMBER($C$124:$C$141)))} -> 662.13426
A125: 2 | B125: =TEXT(EDATE(DATE(2024,1,1),A125-1),"yyyy-mm") -> 2024-02 | C125: =IFERROR(AVERAGEIFS('P02-MaterialPrice'!$E:$E,'P02-MaterialPrice'!$A:$A,B125,'P02-MaterialPrice'!$B:$B,"TMT Steel (Fe500)"),"") | D125: {=_xlfn.FORECAST.LINEAR(A125+5,_xlfn._xlws.FILTER($C$124:$C$141,ISNUMBER($C$124:$C$141)),_xlfn._xlws.FILTER($A$124:$A$141,ISNUMBER($C$124:$C$141)))} -> 684.9441
A126: 3 | B126: =TEXT(EDATE(DATE(2024,1,1),A126-1),"yyyy-mm") -> 2024-03 | C126: =IFERROR(AVERAGEIFS('P02-MaterialPrice'!$E:$E,'P02-MaterialPrice'!$A:$A,B126,'P02-MaterialPrice'!$B:$B,"TMT Steel (Fe500)"),"") -> 710.14 | D126: {=_xlfn.FORECAST.LINEAR(21,_xlfn._xlws.FILTER($C$124:$C$141,ISNUMBER($C$124:$C$141)),_xlfn._xlws.FILTER($A$124:$A$141,ISNUMBER($C$124:$C$141)))} -> 658.33262
A127: 4 | B127: =TEXT(EDATE(DATE(2024,1,1),A127-1),"yyyy-mm") -> 2024-04 | C127: =IFERROR(AVERAGEIFS('P02-MaterialPrice'!$E:$E,'P02-MaterialPrice'!$A:$A,B127,'P02-MaterialPrice'!$B:$B,"TMT Steel (Fe500)"),"")
A128: 5 | B128: =TEXT(EDATE(DATE(2024,1,1),A128-1),"yyyy-mm") -> 2024-05 | C128: =IFERROR(AVERAGEIFS('P02-MaterialPrice'!$E:$E,'P02-MaterialPrice'!$A:$A,B128,'P02-MaterialPrice'!$B:$B,"TMT Steel (Fe500)"),"")
A129: 6 | B129: =TEXT(EDATE(DATE(2024,1,1),A129-1),"yyyy-mm") -> 2024-06 | C129: =IFERROR(AVERAGEIFS('P02-MaterialPrice'!$E:$E,'P02-MaterialPrice'!$A:$A,B129,'P02-MaterialPrice'!$B:$B,"TMT Steel (Fe500)"),"") | E129: =AVERAGE(D124:D126)*500 -> 334235.16
A130: 7 | B130: =TEXT(EDATE(DATE(2024,1,1),A130-1),"yyyy-mm") -> 2024-07 | C130: =IFERROR(AVERAGEIFS('P02-MaterialPrice'!$E:$E,'P02-MaterialPrice'!$A:$A,B130,'P02-MaterialPrice'!$B:$B,"TMT Steel (Fe500)"),"")
A131: 8 | B131: =TEXT(EDATE(DATE(2024,1,1),A131-1),"yyyy-mm") -> 2024-08 | C131: =IFERROR(AVERAGEIFS('P02-MaterialPrice'!$E:$E,'P02-MaterialPrice'!$A:$A,B131,'P02-MaterialPrice'!$B:$B,"TMT Steel (Fe500)"),"")
A132: 9 | B132: =TEXT(EDATE(DATE(2024,1,1),A132-1),"yyyy-mm") -> 2024-09 | C132: =IFERROR(AVERAGEIFS('P02-MaterialPrice'!$E:$E,'P02-MaterialPrice'!$A:$A,B132,'P02-MaterialPrice'!$B:$B,"TMT Steel (Fe500)"),"") | E132: Based on the historical TMT Steel price trend, the projected average price for the next quarter is approximately $668.47 per MT. For a requirement of 500 MT, the estimated procurement cost is approximately $334,235.16.
A133: 10 | B133: =TEXT(EDATE(DATE(2024,1,1),A133-1),"yyyy-mm") -> 2024-10 | C133: =IFERROR(AVERAGEIFS('P02-MaterialPrice'!$E:$E,'P02-MaterialPrice'!$A:$A,B133,'P02-MaterialPrice'!$B:$B,"TMT Steel (Fe500)"),"")
A134: 11 | B134: =TEXT(EDATE(DATE(2024,1,1),A134-1),"yyyy-mm") -> 2024-11 | C134: =IFERROR(AVERAGEIFS('P02-MaterialPrice'!$E:$E,'P02-MaterialPrice'!$A:$A,B134,'P02-MaterialPrice'!$B:$B,"TMT Steel (Fe500)"),"")
A135: 12 | B135: =TEXT(EDATE(DATE(2024,1,1),A135-1),"yyyy-mm") -> 2024-12 | C135: =IFERROR(AVERAGEIFS('P02-MaterialPrice'!$E:$E,'P02-MaterialPrice'!$A:$A,B135,'P02-MaterialPrice'!$B:$B,"TMT Steel (Fe500)"),"")
A136: 13 | B136: =TEXT(EDATE(DATE(2024,1,1),A136-1),"yyyy-mm") -> 2025-01 | C136: =IFERROR(AVERAGEIFS('P02-MaterialPrice'!$E:$E,'P02-MaterialPrice'!$A:$A,B136,'P02-MaterialPrice'!$B:$B,"TMT Steel (Fe500)"),"") -> 607.52
A137: 14 | B137: =TEXT(EDATE(DATE(2024,1,1),A137-1),"yyyy-mm") -> 2025-02 | C137: =IFERROR(AVERAGEIFS('P02-MaterialPrice'!$E:$E,'P02-MaterialPrice'!$A:$A,B137,'P02-MaterialPrice'!$B:$B,"TMT Steel (Fe500)"),"") -> 688.19
A138: 15 | B138: =TEXT(EDATE(DATE(2024,1,1),A138-1),"yyyy-mm") -> 2025-03 | C138: =IFERROR(AVERAGEIFS('P02-MaterialPrice'!$E:$E,'P02-MaterialPrice'!$A:$A,B138,'P02-MaterialPrice'!$B:$B,"TMT Steel (Fe500)"),"")
A139: 16 | B139: =TEXT(EDATE(DATE(2024,1,1),A139-1),"yyyy-mm") -> 2025-04 | C139: =IFERROR(AVERAGEIFS('P02-MaterialPrice'!$E:$E,'P02-MaterialPrice'!$A:$A,B139,'P02-MaterialPrice'!$B:$B,"TMT Steel (Fe500)"),"")
...

Sheet P03-BOQVariance
A1: PROBLEM 3: BOQ (Bill of Quantities) Variance Analysis
A2: Scenario: Compare original BOQ quantities vs actual measured quantities for 3 projects across 20 trade items each.
A4: Project_ID | B4: Trade | C4: BOQ_Item | D4: Unit | E4: BOQ_Qty | F4: Actual_Qty | G4: Rate_USD | H4: BOQ_Amount_USD | I4: Actual_Amount_USD | J4: Qty_Variance | K4: Qty_Variance_% | L4: Qty_Status | M4: Overrun_Imapact_USD
A5: WT-HOS-AKL-03 | B5: Civil & Structure | C5: Plastering | D5: rmt | E5: 4879 | F5: 6291 | G5: 107.3 | H5: 523516.7 | I5: =F5*G5 -> 675024.3 | J5: =F5-E5 -> 1412 | K5: =J5/E5 -> 0.28940357 | L5: =IF(F5>E5,"Over BOQ","Within BOQ") -> Over BOQ | M5: =IF(J5>0,J5*G5,0) -> 151507.6
A6: WT-OFF-SYD-02 | B6: MEP - Electrical | C6: LT Panels | D6: set | E6: 4324 | F6: 5554 | G6: 57.67 | H6: 249365.08 | I6: =F6*G6 -> 320299.18 | J6: =F6-E6 -> 1230 | K6: =J6/E6 -> 0.28445883 | L6: =IF(F6>E6,"Over BOQ","Within BOQ") -> Over BOQ | M6: =IF(J6>0,J6*G6,0) -> 70934.1
A7: WT-DC-MUM-01 | B7: Civil & Structure | C7: Excavation | D7: kg | E7: 2649 | F7: 3384 | G7: 178.83 | H7: 473720.67 | I7: =F7*G7 -> 605160.72 | J7: =F7-E7 -> 735 | K7: =J7/E7 -> 0.27746319 | L7: =IF(F7>E7,"Over BOQ","Within BOQ") -> Over BOQ | M7: =IF(J7>0,J7*G7,0) -> 131440.05
A8: WT-HOS-AKL-03 | B8: MEP - Electrical | C8: Conduit Laying | D8: sqm | E8: 4660 | F8: 5951 | G8: 21.61 | H8: 100702.6 | I8: =F8*G8 -> 128601.11 | J8: =F8-E8 -> 1291 | K8: =J8/E8 -> 0.27703863 | L8: =IF(F8>E8,"Over BOQ","Within BOQ") -> Over BOQ | M8: =IF(J8>0,J8*G8,0) -> 27898.51
A9: WT-HOS-AKL-03 | B9: Interior Fit-out | C9: False Ceiling | D9: set | E9: 862 | F9: 1100 | G9: 45.52 | H9: 39238.24 | I9: =F9*G9 -> 50072 | J9: =F9-E9 -> 238 | K9: =J9/E9 -> 0.27610209 | L9: =IF(F9>E9,"Over BOQ","Within BOQ") -> Over BOQ | M9: =IF(J9>0,J9*G9,0) -> 10833.76
A10: WT-OFF-SYD-02 | B10: MEP - Plumbing | C10: CPVC Piping | D10: cum | E10: 2334 | F10: 2909 | G10: 52.55 | H10: 122651.7 | I10: =F10*G10 -> 152867.95 | J10: =F10-E10 -> 575 | K10: =J10/E10 -> 0.24635818 | L10: =IF(F10>E10,"Over BOQ","Within BOQ") -> Over BOQ | M10: =IF(J10>0,J10*G10,0) -> 30216.25
A11: WT-HOS-AKL-03 | B11: MEP - Plumbing | C11: Sanitary Fixtures | D11: nos | E11: 2485 | F11: 3074 | G11: 198.06 | H11: 492179.1 | I11: =F11*G11 -> 608836.44 | J11: =F11-E11 -> 589 | K11: =J11/E11 -> 0.23702213 | L11: =IF(F11>E11,"Over BOQ","Within BOQ") -> Over BOQ | M11: =IF(J11>0,J11*G11,0) -> 116657.34
A12: WT-DC-MUM-01 | B12: MEP - Electrical | C12: Cable Trays | D12: set | E12: 210 | F12: 259 | G12: 154.29 | H12: 32400.9 | I12: =F12*G12 -> 39961.11 | J12: =F12-E12 -> 49 | K12: =J12/E12 -> 0.23333333 | L12: =IF(F12>E12,"Over BOQ","Within BOQ") -> Over BOQ | M12: =IF(J12>0,J12*G12,0) -> 7560.21
A13: WT-OFF-SYD-02 | B13: MEP - Plumbing | C13: Sanitary Fixtures | D13: cum | E13: 4099 | F13: 5053 | G13: 40.46 | H13: 165845.54 | I13: =F13*G13 -> 204444.38 | J13: =F13-E13 -> 954 | K13: =J13/E13 -> 0.23273969 | L13: =IF(F13>E13,"Over BOQ","Within BOQ") -> Over BOQ | M13: =IF(J13>0,J13*G13,0) -> 38598.84
A14: WT-OFF-SYD-02 | B14: MEP - HVAC | C14: Ductwork | D14: cum | E14: 2520 | F14: 3106 | G14: 122.08 | H14: 307641.6 | I14: =F14*G14 -> 379180.48 | J14: =F14-E14 -> 586 | K14: =J14/E14 -> 0.23253968 | L14: =IF(F14>E14,"Over BOQ","Within BOQ") -> Over BOQ | M14: =IF(J14>0,J14*G14,0) -> 71538.88
A15: WT-DC-MUM-01 | B15: MEP - Plumbing | C15: CPVC Piping | D15: nos | E15: 1402 | F15: 1721 | G15: 184.31 | H15: 258402.62 | I15: =F15*G15 -> 317197.51 | J15: =F15-E15 -> 319 | K15: =J15/E15 -> 0.2275321 | L15: =IF(F15>E15,"Over BOQ","Within BOQ") -> Over BOQ | M15: =IF(J15>0,J15*G15,0) -> 58794.89
A16: WT-DC-MUM-01 | B16: Civil & Structure | C16: RCC Slabs | D16: rmt | E16: 2075 | F16: 2547 | G16: 59.08 | H16: 122591 | I16: =F16*G16 -> 150476.76 | J16: =F16-E16 -> 472 | K16: =J16/E16 -> 0.22746988 | L16: =IF(F16>E16,"Over BOQ","Within BOQ") -> Over BOQ | M16: =IF(J16>0,J16*G16,0) -> 27885.76
... A76: WT-DC-MUM-01 | B76: MEP - Electrical | C76: HT Cables | D76: nos | E76: 3957 | F76: 3373 | G76: 73.59 | H76: 291195.63 | I76: =F76*G76 -> 248219.07 | J76: =F76-E76 -> -584 | K76: =J76/E76 -> -0.14758656 | L76: =IF(F76>E76,"Over BOQ","Within BOQ") -> Within BOQ | M76: =IF(J76>0,J76*G76,0) -> 0
A78: ANALYSIS QUESTIONS
A79: Q1. Which project has the highest total BOQ variance (in USD)? | G79: PCC in civil structure has the highest BOQ variance in USD
A80: Q2. Which trade consistently exceeds BOQ quantities across all 3 projects?
A81: Q3. Identify the top 5 BOQ items with the highest quantity variance %.
A82: Q4. What is the total financial impact of quantity overruns per project?
A83: Q5. Create a waterfall chart showing BOQ Amount vs Actual Amount per trade for Project WT-DC-MUM-01.
A84: Q6. Which items have negative variance (came under BOQ)? What's the saving?
D99: ='P03'!D61-'P03'!B62 -> 375655.02

Sheet P03
A1: BOQ Variance Analysis
A4: Q1
A7: Project ID | B7: Sum of BOQ_Amount_USD | C7: Sum of Actual_Amount_USD | D7: Total Variance (USD)
A8: WT-DC-MUM-01 | B8: 5686239.8 | C8: 6061894.8 | D8: =C8-B8 -> 375655.02
A9: WT-HOS-AKL-03 | B9: 4619527.9 | C9: 5117552.2 | D9: =C9-B9 -> 498024.35
A10: WT-OFF-SYD-02 | B10: 5691799.9 | C10: 6408709.9 | D10: =C10-B10 -> 716909.95
A11: Grand Total | B11: 15997568 | C11: 17588157 | D11: =C11-B11 -> 1590589.3
A13: Project ID WT-DC-MUM-01 has the highest BOQ Variance
A16: Q2
A19: Sum of Qty_Variance | B19: Project ID
A20: Row Labels | B20: WT-DC-MUM-01 | C20: WT-HOS-AKL-03 | D20: WT-OFF-SYD-02 | E20: Grand Total
A21: Civil & Structure | B21: 2054 | C21: 1150 | D21: 937 | E21: 4141
A22: Interior Fit-out | B22: 397 | C22: 727 | D22: 1834 | E22: 2958
A23: MEP - Electrical | B23: -78 | C23: 1968 | D23: 2865 | E23: 4755
A24: MEP - HVAC | B24: 502 | C24: 24 | D24: 1952 | E24: 2478
A25: MEP - Plumbing | B25: -519 | C25: 1678 | D25: 2734 | E25: 3893
A26: Grand Total | B26: 2356 | C26: 5547 | D26: 10322 | E26: 18225
A28: Civil & Structure, Interior Fit-Out, and MEP - HVAC consistently exceeded BOQ quantities across all three projects, recording positive quantity variances in each project.
A32: Q3
A35: BOQ_Item | B35: Qty_Variance_%
A36: Plastering | B36: 0.28940357 | C36: The top 5 BOQ items with the highest quantity variance percentages were identified by sorting the quantity variance percentage in descending order.
A37: LT Panels | B37: 0.28445883
A38: Excavation | B38: 0.27746319
A39: Conduit Laying | B39: 0.27703863
A40: False Ceiling | B40: 0.27610209
A42: Q4
A45: Project ID | B45: Sum of Overrun_Imapact_USD
A46: WT-DC-MUM-01 | B46: 502032.7 | C46: The total financial impact of quantity overruns across all three projects is $1,828,491.49. WT-OFF-SYD-02 had the highest overrun impact at $768,547.75, followed by WT-HOS-AKL-03 at $557,911.04 and WT-DC-MUM-01 at $502,032.70.
A47: WT-HOS-AKL-03 | B47: 557911.04
A48: WT-OFF-SYD-02 | B48: 768547.75
A49: Grand Total | B49: 1828491.5
A51: Q5
A55: Trade | B55: BOQ Amount | C55: variance | D55: Actual Amount | F55: Category | G55: Amount
A56: {=_xlfn.UNIQUE('P03-BOQVariance'!B5:B76)} -> Civil & Structure | B56: =SUMIFS('P03-BOQVariance'!$H:$H,'P03-BOQVariance'!$A:$A,"WT-DC-MUM-01",'P03-BOQVariance'!$B:$B,A56) -> 1893094.3 | C56: =SUMIFS('P03-BOQVariance'!$I:$I,'P03-BOQVariance'!$A:$A,"WT-DC-MUM-01",'P03-BOQVariance'!$B:$B,A56)-B56 -> 238929.32 | D56: =SUMIFS('P03-BOQVariance'!$I:$I,'P03-BOQVariance'!$A:$A,"WT-DC-MUM-01",'P03-BOQVariance'!$B:$B,A56) -> 2132023.6 | F56: =A56 -> Civil & Structure | G56: =C56 -> 238929.32
A57: MEP - Electrical | B57: =SUMIFS('P03-BOQVariance'!$H:$H,'P03-BOQVariance'!$A:$A,"WT-DC-MUM-01",'P03-BOQVariance'!$B:$B,A57) -> 986727.76 | C57: =SUMIFS('P03-BOQVariance'!$I:$I,'P03-BOQVariance'!$A:$A,"WT-DC-MUM-01",'P03-BOQVariance'!$B:$B,A57)-B57 -> 20630.29 | D57: =SUMIFS('P03-BOQVariance'!$I:$I,'P03-BOQVariance'!$A:$A,"WT-DC-MUM-01",'P03-BOQVariance'!$B:$B,A57) -> 1007358.1 | F57: =A57 -> MEP - Electrical | G57: =C57 -> 20630.29
A58: Interior Fit-out | B58: =SUMIFS('P03-BOQVariance'!$H:$H,'P03-BOQVariance'!$A:$A,"WT-DC-MUM-01",'P03-BOQVariance'!$B:$B,A58) -> 1202994.9 | C58: =SUMIFS('P03-BOQVariance'!$I:$I,'P03-BOQVariance'!$A:$A,"WT-DC-MUM-01",'P03-BOQVariance'!$B:$B,A58)-B58 -> 88907.45 | D58: =SUMIFS('P03-BOQVariance'!$I:$I,'P03-BOQVariance'!$A:$A,"WT-DC-MUM-01",'P03-BOQVariance'!$B:$B,A58) -> 1291902.4 | F58: =A58 -> Interior Fit-out | G58: =C58 -> 88907.45
A59: MEP - Plumbing | B59: =SUMIFS('P03-BOQVariance'!$H:$H,'P03-BOQVariance'!$A:$A,"WT-DC-MUM-01",'P03-BOQVariance'!$B:$B,A59) -> 765988.47 | C59: =SUMIFS('P03-BOQVariance'!$I:$I,'P03-BOQVariance'!$A:$A,"WT-DC-MUM-01",'P03-BOQVariance'!$B:$B,A59)-B59 -> -9419.5 | D59: =SUMIFS('P03-BOQVariance'!$I:$I,'P03-BOQVariance'!$A:$A,"WT-DC-MUM-01",'P03-BOQVariance'!$B:$B,A59) -> 756568.97 | F59: =A59 -> MEP - Plumbing | G59: =C59 -> -9419.5
A60: MEP - HVAC | B60: =SUMIFS('P03-BOQVariance'!$H:$H,'P03-BOQVariance'!$A:$A,"WT-DC-MUM-01",'P03-BOQVariance'!$B:$B,A60) -> 837434.33 | C60: =SUMIFS('P03-BOQVariance'!$I:$I,'P03-BOQVariance'!$A:$A,"WT-DC-MUM-01",'P03-BOQVariance'!$B:$B,A60)-B60 -> 36607.46 | D60: =SUMIFS('P03-BOQVariance'!$I:$I,'P03-BOQVariance'!$A:$A,"WT-DC-MUM-01",'P03-BOQVariance'!$B:$B,A60) -> 874041.79 | F60: =A60 -> MEP - HVAC | G60: =C60 -> 36607.46
A61: Actual Total | D61: =SUMIFS('P03-BOQVariance'!$I:$I,'P03-BOQVariance'!$A:$A,"WT-DC-MUM-01") -> 6061894.8 | F61: =A61 -> Actual Total | G61: =D61 -> 6061894.8
A62: BOQ baseline | B62: =SUMIFS('P03-BOQVariance'!$H:$H,'P03-BOQVariance'!$A:$A,"WT-DC-MUM-01") -> 5686239.8 | F62: =A62 -> BOQ baseline | G62: =B62 -> 5686239.8

Sheet P04-LabourProd
A1: PROBLEM 4: Labour Productivity by Trade
A2: Scenario: Track daily output of workers across trades to identify low-productivity areas.
A4: Date | B4: Project_ID | C4: Trade | D4: Workers_Count | E4: Hours_Worked | F4: Output_Qty | G4: Output_Unit | H4: City | I4: Productivity_per_ManHour
A5: 2025-03-01 | B5: WT-HOS-AKL-03 | C5: Facade & Cladding | D5: 17 | E5: 7.7 | F5: 470.6 | G5: cum | H5: Hyderabad | I5: =F5/(D5*E5) -> 3.5951108
A6: 2025-02-06 | B6: WT-DC-MUM-01 | C6: Civil & Structure | D6: 15 | E6: 9.2 | F6: 452.4 | G6: rmt | H6: Ahmedabad | I6: =F6/(D6*E6) -> 3.2782609
A7: 2025-02-01 | B7: WT-ITP-BLR-04 | C7: Facade & Cladding | D7: 24 | E7: 8.8 | F7: 1132.6 | G7: nos | H7: Ahmedabad | I7: =F7/(D7*E7) -> 5.3626894
A8: 2025-01-21 | B8: WT-DC-MUM-01 | C8: MEP - Plumbing | D8: 25 | E8: 8.4 | F8: 56.7 | G8: cum | H8: Mumbai | I8: =F8/(D8*E8) -> 0.27
A9: 2025-03-10 | B9: WT-DC-MUM-01 | C9: MEP - HVAC | D9: 35 | E9: 8.1 | F9: 793.4 | G9: rmt | H9: Delhi | I9: =F9/(D9*E9) -> 2.7985891
A10: 2025-05-30 | B10: WT-ITP-BLR-04 | C10: Facade & Cladding | D10: 36 | E10: 9.9 | F10: 865.1 | G10: nos | H10: Pune | I10: =F10/(D10*E10) -> 2.4273288
A11: 2025-03-24 | B11: WT-DC-MUM-01 | C11: MEP - HVAC | D11: 26 | E11: 7.6 | F11: 657.2 | G11: nos | H11: Mumbai | I11: =F11/(D11*E11) -> 3.3259109
A12: 2025-04-27 | B12: WT-DC-MUM-01 | C12: MEP - Electrical | D12: 21 | E12: 7.3 | F12: 1019.3 | G12: nos | H12: Mumbai | I12: =F12/(D12*E12) -> 6.6490541
A13: 2025-05-19 | B13: WT-ITP-BLR-04 | C13: MEP - Plumbing | D13: 8 | E13: 6.8 | F13: 149.8 | G13: nos | H13: Ahmedabad | I13: =F13/(D13*E13) -> 2.7536765
A14: 2025-01-14 | B14: WT-OFF-SYD-02 | C14: MEP - Electrical | D14: 40 | E14: 6.5 | F14: 604.5 | G14: nos | H14: Bangalore | I14: =F14/(D14*E14) -> 2.325
A15: 2025-01-08 | B15: WT-OFF-SYD-02 | C15: Facade & Cladding | D15: 15 | E15: 7.2 | F15: 25.1 | G15: nos | H15: Bangalore | I15: =F15/(D15*E15) -> 0.23240741
A16: 2025-02-27 | B16: WT-DC-MUM-01 | C16: MEP - Plumbing | D16: 12 | E16: 8.6 | F16: 102.5 | G16: rmt | H16: Hyderabad | I16: =F16/(D16*E16) -> 0.99321705
... A84: 2025-01-22 | B84: WT-HOS-AKL-03 | C84: Interior Fit-out | D84: 29 | E84: 8.6 | F84: 495.8 | G84: cum | H84: Bangalore | I84: =F84/(D84*E84) -> 1.9879711
A86: ANALYSIS QUESTIONS
A87: Q1. Which trade has the highest average productivity per man-hour?
A88: Q2. Is there a productivity difference between projects in India vs Australia?
A89: Q3. Create a box plot (or summary stats) of productivity by trade — which has the most variance?
A90: Q4. On which dates did productivity drop below the 25th percentile? What was the trade?
A91: Q5. What is the optimal crew size (workers count) that maximises productivity for Civil & Structure?
A92: Q6. Calculate total man-hours consumed per project and rank them.

Sheet P05-TenderBid
A1: PROBLEM 5: Tender Bid Comparison Analysis
A2: Scenario: WT received bids from multiple contractors for 5 trade packages. Evaluate and rank.
A4: Tender_Package | B4: Contractor | C4: Bid_Amount_USD | D4: Completion_Days | E4: Experience_Years | F4: Safety_Rating | G4: Past_Defect_Rate_% | H4: Financial_Score
A5: Structural Works | B5: Contractor-K | C5: 6124192 | D5: 306 | E5: 18 | F5: 3.4 | G5: 4.7 | H5: 59
A6: Structural Works | B6: Contractor-D | C6: 3366658 | D6: 338 | E6: 8 | F6: 3.1 | G6: 2.1 | H6: 53.9
A7: Structural Works | B7: Contractor-N | C7: 7111231 | D7: 141 | E7: 18 | F7: 4.4 | G7: 10.1 | H7: 94.2
A8: Structural Works | B8: Contractor-A | C8: 6052664 | D8: 262 | E8: 21 | F8: 2.8 | G8: 4.8 | H8: 58.1
A9: Structural Works | B9: Contractor-N | C9: 6312010 | D9: 174 | E9: 25 | F9: 3.6 | G9: 5.2 | H9: 83.8
A10: Structural Works | B10: Contractor-D | C10: 4226208 | D10: 235 | E10: 25 | F10: 4.5 | G10: 3.2 | H10: 62
A11: Structural Works | B11: Contractor-M | C11: 7079774 | D11: 330 | E11: 8 | F11: 3.4 | G11: 11.4 | H11: 99.2
A12: Structural Works | B12: Contractor-H | C12: 6954518 | D12: 234 | E12: 14 | F12: 3.8 | G12: 5.3 | H12: 58.1
A13: MEP Package | B13: Contractor-D | C13: 7221449 | D13: 160 | E13: 10 | F13: 2.6 | G13: 6 | H13: 68.6
A14: MEP Package | B14: Contractor-O | C14: 1360585 | D14: 354 | E14: 5 | F14: 3.2 | G14: 9.3 | H14: 63.6
A15: MEP Package | B15: Contractor-O | C15: 4806314 | D15: 165 | E15: 15 | F15: 2.7 | G15: 11 | H15: 90.8
A16: MEP Package | B16: Contractor-O | C16: 3432532 | D16: 103 | E16: 15 | F16: 2.6 | G16: 6.3 | H16: 61.8
... A44: Landscaping | B44: Contractor-L | C44: 4620485 | D44: 192 | E44: 5 | F44: 2.8 | G44: 1.4 | H44: 58.6
A46: ANALYSIS QUESTIONS
A47: Q1. For each tender package, which contractor offers the lowest bid? Is the lowest bid always the best choice?
A48: Q2. Create a weighted scoring model: 40% Price, 20% Time, 15% Experience, 15% Safety, 10% Defects. Rank contractors.
A49: Q3. Which contractors appear in multiple packages? What is their average bid competitiveness?
A50: Q4. Identify any contractor with Safety Rating < 3.5 AND Defect Rate > 8% — flag as HIGH RISK.
A51: Q5. What is the total project cost if WT selects the lowest bidder for each package vs the highest-scored bidder?
A52: Q6. Create a scatter plot of Bid Amount vs Completion Days — are cheaper bids slower?

Sheet P06-DelayRCA
A1: PROBLEM 6: Project Delay Root Cause Analysis
A2: Scenario: Analyse delay events across projects to find systemic causes.
A4: Delay_ID | B4: Project_ID | C4: Activity | D4: Planned_Start | E4: Actual_Start | F4: Delay_Days | G4: Cause_Category | H4: Responsible_Party
A5: DLY-100 | B5: WT-RES-MEL-05 | C5: Superstructure | D5: 2024-08-11 | E5: 2024-09-23 | F5: 43 | G5: Permit Delay | H5: Force Majeure
A6: DLY-101 | B6: WT-DC-MUM-01 | C6: Handover Prep | D6: 2024-12-03 | E6: 2024-12-22 | F6: 19 | G6: Client Decision Pending | H6: Contractor
A7: DLY-102 | B7: WT-OFF-SYD-02 | C7: Testing & Commissioning | D7: 2024-11-16 | E7: 2024-12-01 | F7: 15 | G7: Material Delay | H7: Contractor
A8: DLY-103 | B8: WT-OFF-SYD-02 | C8: Facade Installation | D8: 2024-11-08 | E8: 2024-11-10 | F8: 2 | G8: Permit Delay | H8: Authority
A9: DLY-104 | B9: WT-MAL-DEL-06 | C9: Testing & Commissioning | D9: 2024-10-26 | E9: 2024-12-01 | F9: 36 | G9: Labour Shortage | H9: Authority
A10: DLY-105 | B10: WT-DC-MUM-01 | C10: Superstructure | D10: 2024-08-06 | E10: 2024-09-01 | F10: 26 | G10: Equipment Breakdown | H10: Authority
A11: DLY-106 | B11: WT-RES-MEL-05 | C11: Landscape | D11: 2024-12-20 | E11: 2024-12-25 | F11: 5 | G11: Labour Shortage | H11: Consultant
A12: DLY-107 | B12: WT-DC-MUM-01 | C12: External Works | D12: 2024-10-25 | E12: 2024-12-08 | F12: 44 | G12: RFI Response Delay | H12: Consultant
A13: DLY-108 | B13: WT-OFF-SYD-02 | C13: Handover Prep | D13: 2024-12-26 | E13: 2025-01-07 | F13: 12 | G13: Labour Shortage | H13: Subcontractor
A14: DLY-109 | B14: WT-MAL-DEL-06 | C14: Foundation | D14: 2024-05-03 | E14: 2024-06-06 | F14: 34 | G14: Labour Shortage | H14: Consultant
A15: DLY-110 | B15: WT-OFF-SYD-02 | C15: MEP Rough-In | D15: 2024-08-13 | E15: 2024-08-28 | F15: 15 | G15: Permit Delay | H15: Authority
A16: DLY-111 | B16: WT-HOS-AKL-03 | C16: Superstructure | D16: 2024-07-07 | E16: 2024-07-20 | F16: 13 | G16: RFI Response Delay | H16: Consultant
... A64: DLY-159 | B64: WT-RES-MEL-05 | C64: External Works | D64: 2024-06-11 | E64: 2024-06-30 | F64: 19 | G64: Permit Delay | H64: Consultant
A66: ANALYSIS QUESTIONS
A67: Q1. What is the most frequent delay cause category? Create a Pareto chart.
A68: Q2. Which responsible party causes the most total delay days?
A69: Q3. For Project WT-DC-MUM-01, what is the cumulative delay and the dominant cause?
A70: Q4. Is there a seasonal pattern in delays? (Hint: check Weather delays by month)
A71: Q5. Which activity is most delay-prone across all projects?
A72: Q6. Calculate the estimated cost of delay per project if the daily burn rate is $15,000.

Sheet P07-CashFlow
A1: PROBLEM 7: Monthly Cash Flow Tracking
A2: Scenario: Track planned vs actual cash inflow/outflow for 4 projects over 12 months.
A4: Month | B4: Project_ID | C4: Planned_Inflow_USD | D4: Actual_Inflow_USD | E4: Planned_Outflow_USD | F4: Actual_Outflow_USD | G4: Net_CashFlow_USD
A5: 2024-01 | B5: WT-DC-MUM-01 | C5: 1554546 | D5: 978713 | E5: 1762133 | F5: 1552987 | G5: =D5-F5 -> -574274
A6: 2024-02 | B6: WT-DC-MUM-01 | C6: 1404044 | D6: 1005450 | E6: 1699137 | F6: 1874303 | G6: =D6-F6 -> -868853
A7: 2024-03 | B7: WT-DC-MUM-01 | C7: 278220 | D7: 293971 | E7: 517137 | F7: 515202 | G7: =D7-F7 -> -221231
A8: 2024-04 | B8: WT-DC-MUM-01 | C8: 1956584 | D8: 1345923 | E8: 226210 | F8: 271228 | G8: =D8-F8 -> 1074695
A9: 2024-05 | B9: WT-DC-MUM-01 | C9: 1032557 | D9: 1026341 | E9: 540723 | F9: 636870 | G9: =D9-F9 -> 389471
A10: 2024-06 | B10: WT-DC-MUM-01 | C10: 807056 | D10: 838024 | E10: 169434 | F10: 161714 | G10: =D10-F10 -> 676310
A11: 2024-07 | B11: WT-DC-MUM-01 | C11: 1464127 | D11: 957027 | E11: 852634 | F11: 809658 | G11: =D11-F11 -> 147369
A12: 2024-08 | B12: WT-DC-MUM-01 | C12: 1544929 | D12: 1346637 | E12: 1185809 | F12: 1377010 | G12: =D12-F12 -> -30373
A13: 2024-09 | B13: WT-DC-MUM-01 | C13: 481437 | D13: 493728 | E13: 1131510 | F13: 1069834 | G13: =D13-F13 -> -576106
A14: 2024-10 | B14: WT-DC-MUM-01 | C14: 1896205 | D14: 1244523 | E14: 490775 | F14: 542744 | G14: =D14-F14 -> 701779
A15: 2024-11 | B15: WT-DC-MUM-01 | C15: 1559552 | D15: 1136340 | E15: 540487 | F15: 462078 | G15: =D15-F15 -> 674262
A16: 2024-12 | B16: WT-DC-MUM-01 | C16: 906975 | D16: 902788 | E16: 1340723 | F16: 1456079 | G16: =D16-F16 -> -553291
... A52: 2024-12 | B52: WT-ITP-BLR-04 | C52: 925949 | D52: 627386 | E52: 545272 | F52: 642381 | G52: =D52-F52 -> -14995
A54: ANALYSIS QUESTIONS
A55: Q1. Which project had negative net cash flow for the most months?
A56: Q2. What is the cumulative cash position for each project at end of December 2024?
A57: Q3. Create a line chart of monthly net cash flow for all 4 projects.
A58: Q4. In which months did actual inflow fall below 70% of planned? Flag as collection risk.
A59: Q5. What is the total cash surplus/deficit across all projects?
A60: Q6. Calculate the cash flow forecast accuracy: (Actual Inflow / Planned Inflow) × 100.

Sheet P08-ChangeOrder
A1: PROBLEM 8: Change Order Impact Analysis
A2: Scenario: Evaluate cost and time impact of change orders (VOs) on ongoing projects.
A4: VO_Number | B4: Project_ID | C4: Description | D4: Initiated_By | E4: Cost_Impact_USD | F4: Time_Impact_Days | G4: Status | H4: Date_Raised
A5: VO-200 | B5: WT-DC-MUM-01 | C5: Additional MEP riser | D5: Architect | E5: 444793 | F5: -4 | G5: Pending | H5: 2024-04-15
A6: VO-201 | B6: WT-DC-MUM-01 | C6: Design revision - column grid | D6: Client | E6: 268127 | F6: -2 | G6: Pending | H6: 2025-01-14
A7: VO-202 | B7: WT-DC-MUM-01 | C7: Upgraded HVAC system | D7: Architect | E7: 45722 | F7: 29 | G7: Pending | H7: 2025-01-21
A8: VO-203 | B8: WT-DC-MUM-01 | C8: Client-requested floor upgrade | D8: Contractor | E8: 45536 | F8: 15 | G8: Rejected | H8: 2024-05-01
A9: VO-204 | B9: WT-HOS-AKL-03 | C9: Basement depth increase | D9: Consultant | E9: 492282 | F9: 28 | G9: Pending | H9: 2024-07-30
A10: VO-205 | B10: WT-HOS-AKL-03 | C10: Scope reduction - parking level | D10: Client | E10: 383761 | F10: 6 | G10: Under Review | H10: 2024-10-11
A11: VO-206 | B11: WT-RES-MEL-05 | C11: Additional MEP riser | D11: Contractor | E11: 787324 | F11: 19 | G11: Rejected | H11: 2024-12-22
A12: VO-207 | B12: WT-RES-MEL-05 | C12: Upgraded HVAC system | D12: Consultant | E12: 114455 | F12: 19 | G12: Pending | H12: 2025-01-21
A13: VO-208 | B13: WT-RES-MEL-05 | C13: Regulatory compliance addition | D13: Consultant | E13: 115344 | F13: 4 | G13: Under Review | H13: 2024-01-30
A14: VO-209 | B14: WT-RES-MEL-05 | C14: Upgraded HVAC system | D14: Consultant | E14: 207286 | F14: 10 | G14: Rejected | H14: 2024-04-14
A15: VO-210 | B15: WT-HOS-AKL-03 | C15: Revised electrical layout | D15: Client | E15: 767024 | F15: 23 | G15: Rejected | H15: 2024-02-17
A16: VO-211 | B16: WT-OFF-SYD-02 | C16: Additional MEP riser | D16: Contractor | E16: 195489 | F16: -3 | G16: Approved | H16: 2024-04-06
... A49: VO-244 | B49: WT-HOS-AKL-03 | C49: Design revision - column grid | D49: Consultant | E49: -108463 | F49: 6 | G49: Under Review | H49: 2024-08-17
A51: ANALYSIS QUESTIONS
A52: Q1. What is the total approved cost impact of all change orders per project?
A53: Q2. Who initiates the most change orders — Client, Consultant, or Contractor?
A54: Q3. What % of change orders are still Pending or Under Review? What is the potential cost exposure?
A55: Q4. Is there a correlation between cost impact and time impact of VOs?
A56: Q5. Which project has the highest change order frequency per month?
A57: Q6. Create a stacked bar chart: Approved vs Pending vs Rejected VO costs per project.

Sheet P09-SubconScore
A1: PROBLEM 9: Subcontractor Performance Scorecard
A2: Scenario: Rate subcontractors on Quality, Time, Safety, Cost, and Communication for vendor management.
A4: Subcontractor | B4: Trade | C4: Project_ID | D4: Quality_Score | E4: Time_Score | F4: Safety_Score | G4: Cost_Score | H4: Communication_Score | I4: Defect_Count | J4: Weighted_Score
A5: Contractor-I | B5: Elevator Installation | C5: WT-HOS-AKL-03 | D5: 3.2 | E5: 2.1 | F5: 3.1 | G5: 2.3 | H5: 3.8 | I5: 10 | J5: =D5*0.3+E5*0.25+F5*0.2+G5*0.15+H5*0.1 -> 2.83
A6: Contractor-N | B6: Landscaping | C6: WT-DC-MUM-01 | D6: 2.9 | E6: 3.2 | F6: 2.3 | G6: 4.7 | H6: 4.7 | I6: 7 | J6: =D6*0.3+E6*0.25+F6*0.2+G6*0.15+H6*0.1 -> 3.305
A7: Contractor-J | B7: Elevator Installation | C7: WT-DC-MUM-01 | D7: 4.1 | E7: 2.5 | F7: 2.8 | G7: 2.8 | H7: 2.4 | I7: 5 | J7: =D7*0.3+E7*0.25+F7*0.2+G7*0.15+H7*0.1 -> 3.075
A8: Contractor-G | B8: Interior Fit-out | C8: WT-OFF-SYD-02 | D8: 2.9 | E8: 4.3 | F8: 3.1 | G8: 4.8 | H8: 4.2 | I8: 15 | J8: =D8*0.3+E8*0.25+F8*0.2+G8*0.15+H8*0.1 -> 3.705
A9: Contractor-J | B9: IT & Low Current | C9: WT-DC-MUM-01 | D9: 3.4 | E9: 2.4 | F9: 2 | G9: 3.2 | H9: 4.5 | I9: 12 | J9: =D9*0.3+E9*0.25+F9*0.2+G9*0.15+H9*0.1 -> 2.95
A10: Contractor-M | B10: Facade & Cladding | C10: WT-OFF-SYD-02 | D10: 3 | E10: 4.4 | F10: 4.6 | G10: 4.9 | H10: 2.4 | I10: 10 | J10: =D10*0.3+E10*0.25+F10*0.2+G10*0.15+H10*0.1 -> 3.895
A11: Contractor-J | B11: MEP - Plumbing | C11: WT-OFF-SYD-02 | D11: 2.9 | E11: 4.9 | F11: 4.9 | G11: 2.9 | H11: 4.1 | I11: 15 | J11: =D11*0.3+E11*0.25+F11*0.2+G11*0.15+H11*0.1 -> 3.92
A12: Contractor-J | B12: MEP - Plumbing | C12: WT-OFF-SYD-02 | D12: 3.1 | E12: 4.4 | F12: 3.2 | G12: 2.3 | H12: 3.7 | I12: 18 | J12: =D12*0.3+E12*0.25+F12*0.2+G12*0.15+H12*0.1 -> 3.385
A13: Contractor-I | B13: MEP - Electrical | C13: WT-HOS-AKL-03 | D13: 4.3 | E13: 2.1 | F13: 4.2 | G13: 4.8 | H13: 2.6 | I13: 25 | J13: =D13*0.3+E13*0.25+F13*0.2+G13*0.15+H13*0.1 -> 3.635
A14: Contractor-E | B14: MEP - HVAC | C14: WT-OFF-SYD-02 | D14: 4 | E14: 2.4 | F14: 2.9 | G14: 2.8 | H14: 2.5 | I14: 13 | J14: =D14*0.3+E14*0.25+F14*0.2+G14*0.15+H14*0.1 -> 3.05
A15: Contractor-M | B15: Landscaping | C15: WT-DC-MUM-01 | D15: 3.3 | E15: 3.8 | F15: 3.7 | G15: 3.6 | H15: 4.8 | I15: 22 | J15: =D15*0.3+E15*0.25+F15*0.2+G15*0.15+H15*0.1 -> 3.7
A16: Contractor-G | B16: Elevator Installation | C16: WT-DC-MUM-01 | D16: 4.4 | E16: 3.1 | F16: 4.7 | G16: 3.6 | H16: 3.9 | I16: 2 | J16: =D16*0.3+E16*0.25+F16*0.2+G16*0.15+H16*0.1 -> 3.965
... A34: Contractor-B | B34: Interior Fit-out | C34: WT-HOS-AKL-03 | D34: 4.5 | E34: 3.1 | F34: 4.5 | G34: 2.1 | H34: 4.2 | I34: 17 | J34: =D34*0.3+E34*0.25+F34*0.2+G34*0.15+H34*0.1 -> 3.76
A36: ANALYSIS QUESTIONS
A37: Q1. Rank all subcontractors by their weighted score. Who are the top 3 and bottom 3?
A38: Q2. Which trade has the lowest average quality score?
A39: Q3. Is there a negative correlation between defect count and quality score?
A40: Q4. Create a radar chart for the top-performing subcontractor showing all 5 dimensions.
A41: Q5. Which subcontractors should be blacklisted (weighted score < 3.0 AND defects > 15)?
A42: Q6. Compare subcontractor performance across the 3 projects — is any project a consistent outlier?

Sheet P10-Benchmark
A1: PROBLEM 10: Construction Cost Benchmarking
A2: Scenario: Compare cost per sqm across project types, cities, and countries for WT's portfolio.
A4: Project_ID | B4: Project_Type | C4: City | D4: Country | E4: GFA_sqm | F4: Total_Cost_USD | G4: Cost_per_sqm_USD | H4: Year
A5: WT-BM-100 | B5: Hospital | C5: Canberra | D5: Australia | E5: 31847 | F5: 148948419 | G5: 4677 | H5: 2024
A6: WT-BM-101 | B6: Commercial Office | C6: Gold Coast | D6: Australia | E6: 73895 | F6: 174096620 | G6: 2356 | H6: 2022
A7: WT-BM-102 | B7: Hospital | C7: Kolkata | D7: India | E7: 96915 | F7: 81408600 | G7: 840 | H7: 2025
A8: WT-BM-103 | B8: Residential Tower | C8: Hyderabad | D8: India | E8: 59164 | F8: 48277824 | G8: 816 | H8: 2024
A9: WT-BM-104 | B9: IT Park | C9: Sydney | D9: Australia | E9: 146234 | F9: 486228050 | G9: 3325 | H9: 2024
A10: WT-BM-105 | B10: Hotel | C10: Sydney | D10: Australia | E10: 139850 | F10: 668762700 | G10: 4782 | H10: 2023
A11: WT-BM-106 | B11: Industrial Warehouse | C11: Bangalore | D11: India | E11: 77698 | F11: 65499414 | G11: 843 | H11: 2023
A12: WT-BM-107 | B12: Hospital | C12: Hyderabad | D12: India | E12: 89435 | F12: 73694440 | G12: 824 | H12: 2025
A13: WT-BM-108 | B13: Residential Tower | C13: Hamilton | D13: New Zealand | E13: 75442 | F13: 251674512 | G13: 3336 | H13: 2025
A14: WT-BM-109 | B14: Data Centre | C14: Delhi | D14: India | E14: 110604 | F14: 73330452 | G14: 663 | H14: 2025
A15: WT-BM-110 | B15: Metro Station | C15: Brisbane | D15: Australia | E15: 5648 | F15: 13447888 | G15: 2381 | H15: 2024
A16: WT-BM-111 | B16: Data Centre | C16: Christchurch | D16: New Zealand | E16: 109258 | F16: 291391086 | G16: 2667 | H16: 2025
... A44: WT-BM-139 | B44: Data Centre | C44: Mumbai | D44: India | E44: 40969 | F44: 31095471 | G44: 759 | H44: 2025
A46: ANALYSIS QUESTIONS
A47: Q1. What is the average cost per sqm by country? Visualise as a bar chart.
A48: Q2. Which project type has the highest and lowest cost per sqm globally?
A49: Q3. Has cost per sqm increased year-over-year? Show the trend by country.
A50: Q4. Create a benchmark table: Project Type × Country showing avg cost/sqm.
A51: Q5. Identify outliers — projects where cost/sqm is >1.5× the country average for that type.
A52: Q6. If WT pitches a 50,000 sqm Data Centre in Mumbai, what should the budget estimate be based on this data?

Sheet P12-EVM
A1: PROBLEM 12: Earned Value Management (EVM)
A2: Scenario: Track EVM metrics for a $25M data centre project over 36 months.
A4: Month | B4: BAC_USD | C4: PV_Planned_USD | D4: EV_Earned_USD | E4: AC_Actual_USD | F4: SV_USD | G4: CV_USD | H4: SPI | I4: CPI | J4: EAC_USD | K4: ETC_USD
A5: Month 1 | B5: 25000000 | C5: 713955 | D5: 583077 | E5: 559427 | F5: =D5-C5 -> -130878 | G5: =D5-E5 -> 23650 | H5: =D5/C5 -> 0.81668593 | I5: =D5/E5 -> 1.0422754 | J5: =B5/I5 -> 23985983 | K5: =(B5-D5)/I5 -> 23426556
A6: Month 2 | B6: 25000000 | C6: 1375080 | D6: 1314419 | E6: 1552686 | F6: =D6-C6 -> -60661 | G6: =D6-E6 -> -238267 | H6: =D6/C6 -> 0.95588548 | I6: =D6/E6 -> 0.84654528 | J6: =B6/I6 -> 29531793 | K6: =(B6-D6)/I6 -> 27979107
A7: Month 3 | B7: 25000000 | C7: 1996674 | D7: 1848591 | E7: 2172516 | F7: =D7-C7 -> -148083 | G7: =D7-E7 -> -323925 | H7: =D7/C7 -> 0.92583516 | I7: =D7/E7 -> 0.85089868 | J7: =B7/I7 -> 29380701 | K7: =(B7-D7)/I7 -> 27208185
A8: Month 4 | B8: 25000000 | C8: 2659718 | D8: 2790438 | E8: 2676937 | F8: =D8-C8 -> 130720 | G8: =D8-E8 -> 113501 | H8: =D8/C8 -> 1.0491481 | I8: =D8/E8 -> 1.0423996 | J8: =B8/I8 -> 23983126 | K8: =(B8-D8)/I8 -> 21306189
A9: Month 5 | B9: 25000000 | C9: 3522912 | D9: 3497510 | E9: 3244267 | F9: =D9-C9 -> -25402 | G9: =D9-E9 -> 253243 | H9: =D9/C9 -> 0.99278949 | I9: =D9/E9 -> 1.0780586 | J9: =B9/I9 -> 23189834 | K9: =(B9-D9)/I9 -> 19945567
A10: Month 6 | B10: 25000000 | C10: 4311364 | D10: 4279745 | E10: 4009086 | F10: =D10-C10 -> -31619 | G10: =D10-E10 -> 270659 | H10: =D10/C10 -> 0.99266613 | I10: =D10/E10 -> 1.0675114 | J10: =B10/I10 -> 23418954 | K10: =(B10-D10)/I10 -> 19409868
A11: Month 7 | B11: 25000000 | C11: 5076108 | D11: 3884193 | E11: 4572625 | F11: =D11-C11 -> -1191915 | G11: =D11-E11 -> -688432 | H11: =D11/C11 -> 0.76519117 | I11: =D11/E11 -> 0.8494449 | J11: =B11/I11 -> 29430985 | K11: =(B11-D11)/I11 -> 24858360
A12: Month 8 | B12: 25000000 | C12: 5518420 | D12: 5338129 | E12: 5598832 | F12: =D12-C12 -> -180291 | G12: =D12-E12 -> -260703 | H12: =D12/C12 -> 0.96732924 | I12: =D12/E12 -> 0.95343618 | J12: =B12/I12 -> 26220947 | K12: =(B12-D12)/I12 -> 20622115
A13: Month 9 | B13: 25000000 | C13: 6176705 | D13: 5423142 | E13: 5456673 | F13: =D13-C13 -> -753563 | G13: =D13-E13 -> -33531 | H13: =D13/C13 -> 0.87799919 | I13: =D13/E13 -> 0.99385505 | J13: =B13/I13 -> 25154574 | K13: =(B13-D13)/I13 -> 19697901
A14: Month 10 | B14: 25000000 | C14: 7227989 | D14: 6017261 | E14: 6220665 | F14: =D14-C14 -> -1210728 | G14: =D14-E14 -> -203404 | H14: =D14/C14 -> 0.83249449 | I14: =D14/E14 -> 0.96730189 | J14: =B14/I14 -> 25845085 | K14: =(B14-D14)/I14 -> 19624420
A15: Month 11 | B15: 25000000 | C15: 7370482 | D15: 6885739 | E15: 7471668 | F15: =D15-C15 -> -484743 | G15: =D15-E15 -> -585929 | H15: =D15/C15 -> 0.93423185 | I15: =D15/E15 -> 0.92157989 | J15: =B15/I15 -> 27127328 | K15: =(B15-D15)/I15 -> 19655660
A16: Month 12 | B16: 25000000 | C16: 8456065 | D16: 7607646 | E16: 8861641 | F16: =D16-C16 -> -848419 | G16: =D16-E16 -> -1253995 | H16: =D16/C16 -> 0.8996674 | I16: =D16/E16 -> 0.85849178 | J16: =B16/I16 -> 29120838 | K16: =(B16-D16)/I16 -> 20259197
... A40: Month 36 | B40: 25000000 | C40: 23898889 | D40: 18983212 | E40: 21098110 | F40: =D40-C40 -> -4915677 | G40: =D40-E40 -> -2114898 | H40: =D40/C40 -> 0.79431358 | I40: =D40/E40 -> 0.89975889 | J40: =B40/I40 -> 27785221 | K40: =(B40-D40)/I40 -> 6687111.5
A42: ANALYSIS QUESTIONS
A43: Q1. In which month does the project first show a negative Schedule Variance (SV)?
A44: Q2. What is the CPI trend? Is the project getting more or less cost-efficient over time?
A45: Q3. Based on EAC at Month 36, what is the projected cost overrun?
A46: Q4. Create a line chart with PV, EV, and AC — the classic S-curve.
A47: Q5. At what month does SPI drop below 0.90 (critical schedule delay)?
A48: Q6. If management wants CPI ≥ 1.0 by Month 24, how much cost needs to be recovered?

Sheet P13-LeadTime
A1: PROBLEM 16: Procurement Lead Time Analysis
A2: Scenario: Analyse procurement cycle times to reduce supply chain delays.
A4: PO_Number | B4: Material | C4: Supplier | D4: Order_Date | E4: Expected_Date | F4: Actual_Delivery | G4: Project_ID | H4: Country
A5: PO-600 | B5: Aluminium Facade | C5: Supplier-E | D5: 2024-03-15 | E5: 2024-05-14 | F5: 2024-05-10 | G5: WT-HOS-AKL-03 | H5: India
A6: PO-601 | B6: Aggregate (20mm) | C6: Supplier-I | D6: 2024-01-17 | E6: 2024-02-15 | F6: 2024-02-24 | G6: WT-DC-MUM-01 | H6: New Zealand
A7: PO-602 | B7: PVC Conduits | C7: Supplier-D | D7: 2024-11-27 | E7: 2025-01-08 | F7: 2025-01-15 | G7: WT-OFF-SYD-02 | H7: New Zealand
A8: PO-603 | B8: Aggregate (20mm) | C8: Supplier-E | D8: 2024-12-06 | E8: 2024-12-16 | F8: 2024-12-23 | G8: WT-ITP-BLR-04 | H8: Australia
A9: PO-604 | B9: Aggregate (20mm) | C9: Supplier-F | D9: 2024-10-09 | E9: 2024-10-19 | F9: 2024-10-14 | G9: WT-HOS-AKL-03 | H9: India
A10: PO-605 | B10: MS Pipes | C10: Supplier-H | D10: 2024-04-25 | E10: 2024-06-11 | F10: 2024-06-28 | G10: WT-HOS-AKL-03 | H10: New Zealand
A11: PO-606 | B11: Tiles (Vitrified) | C11: Supplier-J | D11: 2024-04-10 | E11: 2024-06-05 | F11: 2024-06-23 | G11: WT-OFF-SYD-02 | H11: Australia
A12: PO-607 | B12: Plywood (Marine) | C12: Supplier-C | D12: 2024-12-15 | E12: 2024-12-26 | F12: 2024-12-26 | G12: WT-OFF-SYD-02 | H12: New Zealand
A13: PO-608 | B13: TMT Steel (Fe500) | C13: Supplier-G | D13: 2024-01-21 | E13: 2024-02-24 | F13: 2024-02-27 | G13: WT-HOS-AKL-03 | H13: India
A14: PO-609 | B14: RMC M30 | C14: Supplier-J | D14: 2024-05-10 | E14: 2024-05-17 | F14: 2024-05-22 | G14: WT-ITP-BLR-04 | H14: India
A15: PO-610 | B15: Cement (OPC 53) | C15: Supplier-C | D15: 2024-06-14 | E15: 2024-07-29 | F15: 2024-07-25 | G15: WT-HOS-AKL-03 | H15: New Zealand
... A54: PO-649 | B54: Cement (OPC 53) | C54: Supplier-D | D54: 2024-11-10 | E54: 2024-12-30 | F54: 2024-12-30 | G54: WT-OFF-SYD-02 | H54: Australia
A56: ANALYSIS QUESTIONS
A57: Q1. What is the average lead time (order to delivery) by material?
A58: Q2. Which supplier has the worst on-time delivery rate?
A59: Q3. How many POs were delivered late? What is the average delay in days?
A60: Q4. Is there a country-level difference in procurement lead times?
A61: Q5. Which material has the longest and most unpredictable lead time (highest std deviation)?
A62: Q6. Create a supplier reliability scorecard based on on-time delivery %.

Sheet P14-PaymentAging
A1: PROBLEM 19: Client Payment Aging Tracker
A2: Scenario: Track client invoice payments to manage cash flow and flag overdue accounts.
A4: Invoice_No | B4: Project_ID | C4: Client_Name | D4: Invoice_Date | E4: Due_Date | F4: Amount_USD | G4: Paid_Amount_USD | H4: Payment_Date | I4: Outstanding_USD
A5: INV-700 | B5: WT-HOS-AKL-03 | C5: GPT Group | D5: 2024-06-08 | E5: 2024-07-08 | F5: 1697785 | G5: 1697785 | H5: 2024-08-14 | I5: =F5-G5 -> 0
A6: INV-701 | B6: WT-ITP-BLR-04 | C6: Ascendas REIT | D6: 2024-06-18 | E6: 2024-07-18 | F6: 218240 | G6: 109120 | H6: 2024-07-15 | I6: =F6-G6 -> 109120
A7: INV-702 | B7: WT-HOS-AKL-03 | C7: GPT Group | D7: 2024-02-06 | E7: 2024-03-07 | F7: 1189156 | G7: 1189156 | H7: 2024-03-20 | I7: =F7-G7 -> 0
A8: INV-703 | B8: WT-OFF-SYD-02 | C8: Goodman Group | D8: 2025-02-22 | E8: 2025-03-24 | F8: 850225 | G8: 0 | I8: =F8-G8 -> 850225 | L8: WT-HOS-AKL-03
A9: INV-704 | B9: WT-DC-MUM-01 | C9: Tata Realty | D9: 2024-07-16 | E9: 2024-08-15 | F9: 1667376 | G9: 1667376 | H9: 2024-09-05 | I9: =F9-G9 -> 0
A10: INV-705 | B10: WT-DC-MUM-01 | C10: Tata Realty | D10: 2024-08-23 | E10: 2024-09-22 | F10: 1592083 | G10: 0 | I10: =F10-G10 -> 1592083
A11: INV-706 | B11: WT-RES-MEL-05 | C11: Tata Realty | D11: 2024-08-30 | E11: 2024-09-29 | F11: 866049 | G11: 866049 | H11: 2024-10-28 | I11: =F11-G11 -> 0 | L11: {=_xlfn.XLOOKUP(L8,A4:I31,F4:F31,"data_not_found")} -> #VALUE!
A12: INV-707 | B12: WT-HOS-AKL-03 | C12: Brookfield | D12: 2024-11-18 | E12: 2024-12-18 | F12: 1577223 | G12: 0 | I12: =F12-G12 -> 1577223
A13: INV-708 | B13: WT-RES-MEL-05 | C13: Dexus | D13: 2024-03-03 | E13: 2024-04-02 | F13: 581235 | G13: 581235 | H13: 2024-04-30 | I13: =F13-G13 -> 0
A14: INV-709 | B14: WT-OFF-SYD-02 | C14: Stockland | D14: 2024-01-27 | E14: 2024-02-26 | F14: 1861221 | G14: 1861221 | H14: 2024-03-14 | I14: =F14-G14 -> 0
A15: INV-710 | B15: WT-DC-MUM-01 | C15: Tata Realty | D15: 2024-11-20 | E15: 2024-12-20 | F15: 960502 | G15: 720376 | H15: 2024-12-11 | I15: =F15-G15 -> 240126
A16: INV-711 | B16: WT-OFF-SYD-02 | C16: Goodman Group | D16: 2024-10-26 | E16: 2024-11-25 | F16: 300923 | G16: 300923 | H16: 2024-12-16 | I16: =F16-G16 -> 0
A17: INV-712 | B17: WT-DC-MUM-01 | C17: Ascendas REIT | D17: 2024-10-24 | E17: 2024-11-23 | F17: 1693066 | G17: 1693066 | H17: 2025-01-12 | I17: =F17-G17 -> 0
A18: INV-713 | B18: WT-RES-MEL-05 | C18: Brookfield | D18: 2024-07-09 | E18: 2024-08-08 | F18: 1666478 | G18: 0 | I18: =F18-G18 -> 1666478
A19: INV-714 | B19: WT-OFF-SYD-02 | C19: Brookfield | D19: 2024-09-12 | E19: 2024-10-12 | F19: 241682 | G19: 241682 | H19: 2024-11-14 | I19: =F19-G19 -> 0
A20: INV-715 | B20: WT-DC-MUM-01 | C20: Ascendas REIT | D20: 2024-07-01 | E20: 2024-07-31 | F20: 1401771 | G20: 700885 | H20: 2024-09-27 | I20: =F20-G20 -> 700886
A21: INV-716 | B21: WT-DC-MUM-01 | C21: Brookfield | D21: 2024-09-06 | E21: 2024-10-06 | F21: 537954 | G21: 403465 | H21: 2024-11-09 | I21: =F21-G21 -> 134489
A22: INV-717 | B22: WT-ITP-BLR-04 | C22: Tata Realty | D22: 2024-01-11 | E22: 2024-02-10 | F22: 1495461 | G22: 1495461 | H22: 2024-03-16 | I22: =F22-G22 -> 0
A23: INV-718 | B23: WT-OFF-SYD-02 | C23: Goodman Group | D23: 2024-01-21 | E23: 2024-02-20 | F23: 1067752 | G23: 1067752 | H23: 2024-04-06 | I23: =F23-G23 -> 0
A24: INV-719 | B24: WT-RES-MEL-05 | C24: Goodman Group | D24: 2024-10-04 | E24: 2024-11-03 | F24: 1511794 | G24: 1511794 | H24: 2024-11-17 | I24: =F24-G24 -> 0
A25: INV-720 | B25: WT-RES-MEL-05 | C25: Brookfield | D25: 2024-10-05 | E25: 2024-11-04 | F25: 779105 | G25: 584328 | H25: 2024-12-23 | I25: =F25-G25 -> 194777
A26: INV-721 | B26: WT-HOS-AKL-03 | C26: Embassy Group | D26: 2025-03-16 | E26: 2025-04-15 | F26: 1212913 | G26: 606456 | H26: 2025-04-13 | I26: =F26-G26 -> 606457
A27: INV-722 | B27: WT-RES-MEL-05 | C27: Brookfield | D27: 2024-08-18 | E27: 2024-09-17 | F27: 670070 | G27: 502552 | H27: 2024-11-15 | I27: =F27-G27 -> 167518
A28: INV-723 | B28: WT-HOS-AKL-03 | C28: Mirvac | D28: 2024-01-01 | E28: 2024-01-31 | F28: 1677217 | G28: 1677217 | H28: 2024-03-25 | I28: =F28-G28 -> 0
A29: INV-724 | B29: WT-ITP-BLR-04 | C29: Brookfield | D29: 2024-01-10 | E29: 2024-02-09 | F29: 1349677 | G29: 1012257 | H29: 2024-02-29 | I29: =F29-G29 -> 337420
A30: INV-725 | B30: WT-HOS-AKL-03 | C30: Lendlease | D30: 2024-12-03 | E30: 2025-01-02 | F30: 1180273 | G30: 1180273 | H30: 2025-01-16 | I30: =F30-G30 -> 0
A31: INV-726 | B31: WT-RES-MEL-05 | C31: Mirvac | D31: 2025-01-27 | E31: 2025-02-26 | F31: 1206511 | G31: 603255 | H31: 2025-03-24 | I31: =F31-G31 -> 603256
A32: INV-727 | B32: WT-HOS-AKL-03 | C32: GPT Group | D32: 2024-11-24 | E32: 2024-12-24 | F32: 725333 | G32: 0 | I32: =F32-G32 -> 725333
A33: INV-728 | B33: WT-DC-MUM-01 | C33: Dexus | D33: 2024-12-03 | E33: 2025-01-02 | F33: 189837 | G33: 0 | I33: =F33-G33 -> 189837
A34: INV-729 | B34: WT-OFF-SYD-02 | C34: Brookfield | D34: 2025-03-23 | E34: 2025-04-22 | F34: 115585 | G34: 57792 | H34: 2025-04-25 | I34: =F34-G34 -> 57793
A35: INV-730 | B35: WT-ITP-BLR-04 | C35: Tata Realty | D35: 2024-02-20 | E35: 2024-03-21 | F35: 116725 | G35: 116725 | H35: 2024-04-29 | I35: =F35-G35 -> 0
A36: INV-731 | B36: WT-ITP-BLR-04 | C36: Dexus | D36: 2024-11-15 | E36: 2024-12-15 | F36: 1520762 | G36: 1520762 | H36: 2025-01-06 | I36: =F36-G36 -> 0
A37: INV-732 | B37: WT-DC-MUM-01 | C37: Stockland | D37: 2024-04-23 | E37: 2024-05-23 | F37: 1320776 | G37: 1320776 | H37: 2024-05-22 | I37: =F37-G37 -> 0
A38: INV-733 | B38: WT-DC-MUM-01 | C38: Tata Realty | D38: 2024-12-01 | E38: 2024-12-31 | F38: 1080552 | G38: 0 | I38: =F38-G38 -> 1080552
A39: INV-734 | B39: WT-ITP-BLR-04 | C39: Ascendas REIT | D39: 2024-07-03 | E39: 2024-08-02 | F39: 1220252 | G39: 1220252 | H39: 2024-09-14 | I39: =F39-G39 -> 0
A40: INV-735 | B40: WT-HOS-AKL-03 | C40: Ascendas REIT | D40: 2025-02-25 | E40: 2025-03-27 | F40: 1343802 | G40: 1007851 | H40: 2025-05-23 | I40: =F40-G40 -> 335951
A41: INV-736 | B41: WT-DC-MUM-01 | C41: Lendlease | D41: 2025-03-03 | E41: 2025-04-02 | F41: 687334 | G41: 0 | I41: =F41-G41 -> 687334
A42: INV-737 | B42: WT-OFF-SYD-02 | C42: Dexus | D42: 2024-02-19 | E42: 2024-03-20 | F42: 262284 | G42: 262284 | H42: 2024-04-08 | I42: =F42-G42 -> 0
A43: INV-738 | B43: WT-RES-MEL-05 | C43: GPT Group | D43: 2024-04-07 | E43: 2024-05-07 | F43: 455000 | G43: 455000 | H43: 2024-05-28 | I43: =F43-G43 -> 0
A44: INV-739 | B44: WT-RES-MEL-05 | C44: Brookfield | D44: 2024-10-12 | E44: 2024-11-11 | F44: 1621174 | G44: 1621174 | H44: 2024-12-24 | I44: =F44-G44 -> 0
A46: ANALYSIS QUESTIONS
A47: Q1. What is the total outstanding amount across all projects?
A48: Q2. Which client has the highest overdue amount (paid after due date)?
A49: Q3. Create an aging bucket analysis: 0–30 days, 31–60 days, 61–90 days, 90+ days.
A50: Q4. What is the average days-to-pay by client?
A51: Q5. Which project has the worst collection rate (Paid / Invoiced)?
A52: Q6. If WT charges 1.5% monthly interest on overdue amounts, what is the total interest receivable?

Sheet P15-Portfolio
A1: PROBLEM 20: Multi-Project Portfolio Dashboard Data
A2: Scenario: Build a portfolio-level dashboard summarising all WT projects for executive reporting.
A4: Project_ID | B4: Project_Name | C4: Country | D4: Type | E4: Status | F4: Budget_USD | G4: Spent_USD | H4: Completion_% | I4: SPI | J4: CPI | K4: Risk_Level | L4: Budget_Variance_USD
A5: WT-2000 | B5: Hotel Chennai | C5: India | D5: Hotel | E5: Completed | F5: 95528859 | G5: 71188774 | H5: 68 | I5: 0.91 | J5: 0.79 | K5: Medium | L5: =G5-F5*H5/100 -> 6229149.9
A6: WT-2001 | B6: Industrial Warehouse Christchurch | C6: New Zealand | D6: Industrial Warehouse | E6: Completed | F6: 93252435 | G6: 29007060 | H6: 30 | I6: 1 | J6: 1.12 | K6: High | L6: =G6-F6*H6/100 -> 1031329.5
A7: WT-2002 | B7: Shopping Mall Christchurch | C7: New Zealand | D7: Shopping Mall | E7: Completed | F7: 60343779 | G7: 54951597 | H7: 91 | I7: 1.06 | J7: 0.99 | K7: Medium | L7: =G7-F7*H7/100 -> 38758.11
A8: WT-2003 | B8: IT Park Adelaide | C8: Australia | D8: IT Park | E8: Completed | F8: 53319528 | G8: 35960753 | H8: 67 | I8: 0.9 | J8: 1.04 | K8: High | L8: =G8-F8*H8/100 -> 236669.24
A9: WT-2004 | B9: IT Park Mumbai | C9: India | D9: IT Park | E9: On Hold | F9: 45512501 | G9: 4346975 | H9: 10 | I9: 0.81 | J9: 1.09 | K9: Low | L9: =G9-F9*H9/100 -> -204275.1
A10: WT-2005 | B10: IT Park Sydney | C10: Australia | D10: IT Park | E10: On Hold | F10: 17655004 | G10: 2499209 | H10: 14 | I10: 0.78 | J10: 0.86 | K10: Medium | L10: =G10-F10*H10/100 -> 27508.44
A11: WT-2006 | B11: University Campus Ahmedabad | C11: India | D11: University Campus | E11: Completed | F11: 17335296 | G11: 14243396 | H11: 83 | I11: 1.16 | J11: 1.04 | K11: High | L11: =G11-F11*H11/100 -> -144899.68
A12: WT-2007 | B12: Residential Tower Auckland | C12: New Zealand | D12: Residential Tower | E12: Planning | F12: 97555887 | G12: 0 | H12: 0 | I12: 1.11 | J12: 0.79 | K12: High | L12: =G12-F12*H12/100 -> 0
A13: WT-2008 | B13: Hotel Bangalore | C13: India | D13: Hotel | E13: Planning | F13: 15533057 | G13: 0 | H13: 0 | I13: 1.16 | J13: 0.88 | K13: Critical | L13: =G13-F13*H13/100 -> 0
A14: WT-2009 | B14: Data Centre Canberra | C14: Australia | D14: Data Centre | E14: On Hold | F14: 92614538 | G14: 94677516 | H14: 87 | I14: 1.02 | J14: 1 | K14: Low | L14: =G14-F14*H14/100 -> 14102868
A15: WT-2010 | B15: IT Park Melbourne | C15: Australia | D15: IT Park | E15: In Progress | F15: 47857940 | G15: 39611941 | H15: 79 | I15: 0.86 | J15: 1.03 | K15: Medium | L15: =G15-F15*H15/100 -> 1804168.4
A16: WT-2011 | B16: Industrial Warehouse Bangalore | C16: India | D16: Industrial Warehouse | E16: Planning | F16: 84877290 | G16: 0 | H16: 0 | I16: 0.75 | J16: 0.92 | K16: Critical | L16: =G16-F16*H16/100 -> 0
... A29: WT-2024 | B29: Hospital Bangalore | C29: India | D29: Hospital | E29: Completed | F29: 49770958 | G29: 35393957 | H29: 72 | I29: 0.78 | J29: 0.89 | K29: High | L29: =G29-F29*H29/100 -> -441132.76
A31: ANALYSIS QUESTIONS
A32: Q1. How many projects are In Progress, On Hold, Completed, and Planning? Show as a pie chart.
A33: Q2. What is the total portfolio budget and total spent? What is the overall budget variance?
A34: Q3. Which projects have CPI < 0.90 AND SPI < 0.90? These are 'red zone' — list them.
A35: Q4. Create a bubble chart: X = SPI, Y = CPI, Size = Budget. Which quadrant has the most projects?
A36: Q5. What is the average completion % by country?
A37: Q6. Build a traffic-light summary: Green (CPI≥1, SPI≥1), Amber (either <1), Red (both <0.9). Count per category.
A38: Q7. If WT's board asks 'how is our portfolio doing?' — write a 3-line executive summary using this data.

Sheet Analysis report
A1: ANALYSIS REPORT — WT PARTNERSHIP CONSTRUCTION DATA (20 PROBLEMS)
A2: Every figure below is a live formula referencing the source sheets. Update source data and answers refresh automatically.
A5: PROBLEM 01 — Project Cost Overrun Analysis | Source sheet: P01-CostOverrun (50 projects) | H5: CONTENTS — jump to row
A6: Q1. Which country has the highest average cost overrun percentage? | H6: Problem 01 — Cost Overrun (7 questions) | I6: row 5
A7: Country | B7: Avg Overrun % | C7: No. of Projects | D7: Total Budget USD | E7: Total Actual USD | F7: Portfolio Overrun % | H7: Problem 02 — Material Price Fluctuation (6) | I7: row 86
A8: Australia | B8: =AVERAGEIF('P01-CostOverrun'!$D$5:$D$54,$A8,'P01-CostOverrun'!$J$5:$J$54) -> 0.16732437 | C8: =COUNTIF('P01-CostOverrun'!$D$5:$D$54,$A8) -> 15 | D8: =SUMIF('P01-CostOverrun'!$D$5:$D$54,$A8,'P01-CostOverrun'!$F$5:$F$54) -> 690300200 | E8: =SUMIF('P01-CostOverrun'!$D$5:$D$54,$A8,'P01-CostOverrun'!$G$5:$G$54) -> 826447969 | F8: =E8/D8-1 -> 0.1972298 | H8: Problem 03 — BOQ Variance (6) | I8: row 159
A9: India | B9: =AVERAGEIF('P01-CostOverrun'!$D$5:$D$54,$A9,'P01-CostOverrun'!$J$5:$J$54) -> 0.15763933 | C9: =COUNTIF('P01-CostOverrun'!$D$5:$D$54,$A9) -> 28 | D9: =SUMIF('P01-CostOverrun'!$D$5:$D$54,$A9,'P01-CostOverrun'!$F$5:$F$54) -> 1171274510 | E9: =SUMIF('P01-CostOverrun'!$D$5:$D$54,$A9,'P01-CostOverrun'!$G$5:$G$54) -> 1361321621 | F9: =E9/D9-1 -> 0.16225668 | H9: Problem 04 — Labour Productivity (6) | I9: row 212
A10: New Zealand | B10: =AVERAGEIF('P01-CostOverrun'!$D$5:$D$54,$A10,'P01-CostOverrun'!$J$5:$J$54) -> 0.19747604 | C10: =COUNTIF('P01-CostOverrun'!$D$5:$D$54,$A10) -> 7 | D10: =SUMIF('P01-CostOverrun'!$D$5:$D$54,$A10,'P01-CostOverrun'!$F$5:$F$54) -> 290824343 | E10: =SUMIF('P01-CostOverrun'!$D$5:$D$54,$A10,'P01-CostOverrun'!$G$5:$G$54) -> 344177656 | F10: =E10/D10-1 -> 0.18345546 | H10: Problem 05 — Tender Bid Comparison (6) | I10: row 276
A11: ="ANSWER: "&INDEX($A$8:$A$10,MATCH(MAX($B$8:$B$10),$B$8:$B$10,0))&" has the highest average cost overrun at "&TEXT(MAX($B$8:$B$10),"0.0%")&", vs "&INDEX($A$8:$A$10,MATCH(MIN($B$8:$B$10),$B$8:$B$10,0))&" the lowest at "&TEXT(MIN($B$8:$B$10),"0.0%")&"." -> ANSWER: New Zealand has the highest average cost overrun at 19.7%, vs India the lowest at 15.8%. | H11: Problem 06 — Delay Root Cause (6) | I11: row 372
H12: Problem 07 — Cash Flow (6) | I12: row 465
A13: Q2. What is the total budget vs actual cost for each project type? Which type has the worst variance? | H13: Problem 08 — Change Orders (6) | I13: row 534
A14: Project Type | B14: Total Budget USD | C14: Total Actual USD | D14: Variance USD | E14: Variance % | F14: No. of Projects | H14: Problem 09 — Subcontractor Scorecard (6) | I14: row 584
A15: Residential Tower | B15: =SUMIF('P01-CostOverrun'!$E$5:$E$54,$A15,'P01-CostOverrun'!$F$5:$F$54) -> 238232594 | C15: =SUMIF('P01-CostOverrun'!$E$5:$E$54,$A15,'P01-CostOverrun'!$G$5:$G$54) -> 300895518 | D15: =C15-B15 -> 62662924 | E15: =D15/B15 -> 0.26303254 | F15: =COUNTIF('P01-CostOverrun'!$E$5:$E$54,$A15) -> 4 | H15: Problem 10 — Cost Benchmarking (6) | I15: row 649
A16: IT Park | B16: =SUMIF('P01-CostOverrun'!$E$5:$E$54,$A16,'P01-CostOverrun'!$F$5:$F$54) -> 207257585 | C16: =SUMIF('P01-CostOverrun'!$E$5:$E$54,$A16,'P01-CostOverrun'!$G$5:$G$54) -> 251957838 | D16: =C16-B16 -> 44700253 | E16: =D16/B16 -> 0.21567487 | F16: =COUNTIF('P01-CostOverrun'!$E$5:$E$54,$A16) -> 7 | H16: Problem 12 — Earned Value Management (6) | I16: row 714
A17: University Campus | B17: =SUMIF('P01-CostOverrun'!$E$5:$E$54,$A17,'P01-CostOverrun'!$F$5:$F$54) -> 304580669 | C17: =SUMIF('P01-CostOverrun'!$E$5:$E$54,$A17,'P01-CostOverrun'!$G$5:$G$54) -> 370758337 | D17: =C17-B17 -> 66177668 | E17: =D17/B17 -> 0.21727468 | F17: =COUNTIF('P01-CostOverrun'!$E$5:$E$54,$A17) -> 6 | H17: Problem 13 — Procurement Lead Time (6) | I17: row 781
A18: Industrial Warehouse | B18: =SUMIF('P01-CostOverrun'!$E$5:$E$54,$A18,'P01-CostOverrun'!$F$5:$F$54) -> 162936980 | C18: =SUMIF('P01-CostOverrun'!$E$5:$E$54,$A18,'P01-CostOverrun'!$G$5:$G$54) -> 186876390 | D18: =C18-B18 -> 23939410 | E18: =D18/B18 -> 0.14692435 | F18: =COUNTIF('P01-CostOverrun'!$E$5:$E$54,$A18) -> 3 | H18: Problem 14 — Client Payment Aging (6) | I18: row 846
A19: Data Centre | B19: =SUMIF('P01-CostOverrun'!$E$5:$E$54,$A19,'P01-CostOverrun'!$F$5:$F$54) -> 377404871 | C19: =SUMIF('P01-CostOverrun'!$E$5:$E$54,$A19,'P01-CostOverrun'!$G$5:$G$54) -> 423300399 | D19: =C19-B19 -> 45895528 | E19: =D19/B19 -> 0.1216082 | F19: =COUNTIF('P01-CostOverrun'!$E$5:$E$54,$A19) -> 9 | H19: Problem 15 — Portfolio Dashboard (7) | I19: row 916
A20: Hospital | B20: =SUMIF('P01-CostOverrun'!$E$5:$E$54,$A20,'P01-CostOverrun'!$F$5:$F$54) -> 202218749 | C20: =SUMIF('P01-CostOverrun'!$E$5:$E$54,$A20,'P01-CostOverrun'!$G$5:$G$54) -> 252196787 | D20: =C20-B20 -> 49978038 | E20: =D20/B20 -> 0.24714839 | F20: =COUNTIF('P01-CostOverrun'!$E$5:$E$54,$A20) -> 5 | H20: Note: grey blocks in columns H–V are helper calculations.
A21: Commercial Office | B21: =SUMIF('P01-CostOverrun'!$E$5:$E$54,$A21,'P01-CostOverrun'!$F$5:$F$54) -> 139292114 | C21: =SUMIF('P01-CostOverrun'!$E$5:$E$54,$A21,'P01-CostOverrun'!$G$5:$G$54) -> 159577657 | D21: =C21-B21 -> 20285543 | E21: =D21/B21 -> 0.1456331 | F21: =COUNTIF('P01-CostOverrun'!$E$5:$E$54,$A21) -> 3 | H21: Note: P11 and P16–P20 have no data sheet in this workbook.
A22: Hotel | B22: =SUMIF('P01-CostOverrun'!$E$5:$E$54,$A22,'P01-CostOverrun'!$F$5:$F$54) -> 276402274 | C22: =SUMIF('P01-CostOverrun'!$E$5:$E$54,$A22,'P01-CostOverrun'!$G$5:$G$54) -> 314328476 | D22: =C22-B22 -> 37926202 | E22: =D22/B22 -> 0.13721378 | F22: =COUNTIF('P01-CostOverrun'!$E$5:$E$54,$A22) -> 7
A23: Metro Station | B23: =SUMIF('P01-CostOverrun'!$E$5:$E$54,$A23,'P01-CostOverrun'!$F$5:$F$54) -> 194389591 | C23: =SUMIF('P01-CostOverrun'!$E$5:$E$54,$A23,'P01-CostOverrun'!$G$5:$G$54) -> 220692772 | D23: =C23-B23 -> 26303181 | E23: =D23/B23 -> 0.13531167 | F23: =COUNTIF('P01-CostOverrun'!$E$5:$E$54,$A23) -> 5
A24: Shopping Mall | B24: =SUMIF('P01-CostOverrun'!$E$5:$E$54,$A24,'P01-CostOverrun'!$F$5:$F$54) -> 49683626 | C24: =SUMIF('P01-CostOverrun'!$E$5:$E$54,$A24,'P01-CostOverrun'!$G$5:$G$54) -> 51363072 | D24: =C24-B24 -> 1679446 | E24: =D24/B24 -> 0.033802807 | F24: =COUNTIF('P01-CostOverrun'!$E$5:$E$54,$A24) -> 1
A25: TOTAL | B25: =SUM(B15:B24) -> 2152399053 | C25: =SUM(C15:C24) -> 2531947246 | D25: =C25-B25 -> 379548193 | E25: =D25/B25 -> 0.17633728 | F25: =SUM(F15:F24) -> 50
A26: ="ANSWER: Worst variance = "&INDEX($A$15:$A$24,MATCH(MAX($E$15:$E$24),$E$15:$E$24,0))&" at "&TEXT(MAX($E$15:$E$24),"0.0%")&" ("&TEXT(INDEX($D$15:$D$24,MATCH(MAX($E$15:$E$24),$E$15:$E$24,0)),"""$""#,##0")&" over budget). Best = "&INDEX($A$15:$A$24,MATCH(MIN($E$15:$E$24),$E$15:$E$24,0))&" at "&TEXT(MIN($E$15:$E$24),"0.0%")&". Portfolio total: "&TEXT($B$25,"""$""#,##0")&" budget vs "&TEXT($C$25,"""$""#,##0")&" actual ("&TEXT($E$25,"0.0%")&")." -> ANSWER: Worst variance = Residential Tower at 26.3% ($6,26,62,924 over budget). Best = Shopping Mall at 3.4%. Portfolio total: $2,15,23,99,053 budget vs $2,53,19,47,246 actual (17.6%).
A28: Q3. Top 5 projects with the highest absolute cost overrun (USD)
A29: Rank | B29: Project_ID | C29: Project Name | D29: Type | E29: Absolute Overrun USD | F29: Overrun %
A30: 1 | B30: =INDEX('P01-CostOverrun'!$A$5:$A$54,MATCH($E30,'P01-CostOverrun'!$K$5:$K$54,0)) -> WT-1028 | C30: =INDEX('P01-CostOverrun'!$B$5:$B$54,MATCH($E30,'P01-CostOverrun'!$K$5:$K$54,0)) -> Residential Tower Per-29 | D30: =INDEX('P01-CostOverrun'!$E$5:$E$54,MATCH($E30,'P01-CostOverrun'!$K$5:$K$54,0)) -> Residential Tower | E30: =LARGE('P01-CostOverrun'!$K$5:$K$54,$A30) -> 24654239 | F30: =INDEX('P01-CostOverrun'!$J$5:$J$54,MATCH($E30,'P01-CostOverrun'!$K$5:$K$54,0)) -> 0.33139989
A31: 2 | B31: =INDEX('P01-CostOverrun'!$A$5:$A$54,MATCH($E31,'P01-CostOverrun'!$K$5:$K$54,0)) -> WT-1032 | C31: =INDEX('P01-CostOverrun'!$B$5:$B$54,MATCH($E31,'P01-CostOverrun'!$K$5:$K$54,0)) -> Residential Tower Hyd-33 | D31: =INDEX('P01-CostOverrun'!$E$5:$E$54,MATCH($E31,'P01-CostOverrun'!$K$5:$K$54,0)) -> Residential Tower | E31: =LARGE('P01-CostOverrun'!$K$5:$K$54,$A31) -> 21628203 | F31: =INDEX('P01-CostOverrun'!$J$5:$J$54,MATCH($E31,'P01-CostOverrun'!$K$5:$K$54,0)) -> 0.32873946
A32: 3 | B32: =INDEX('P01-CostOverrun'!$A$5:$A$54,MATCH($E32,'P01-CostOverrun'!$K$5:$K$54,0)) -> WT-1033 | C32: =INDEX('P01-CostOverrun'!$B$5:$B$54,MATCH($E32,'P01-CostOverrun'!$K$5:$K$54,0)) -> IT Park Syd-34 | D32: =INDEX('P01-CostOverrun'!$E$5:$E$54,MATCH($E32,'P01-CostOverrun'!$K$5:$K$54,0)) -> IT Park | E32: =LARGE('P01-CostOverrun'!$K$5:$K$54,$A32) -> 19739335 | F32: =INDEX('P01-CostOverrun'!$J$5:$J$54,MATCH($E32,'P01-CostOverrun'!$K$5:$K$54,0)) -> 0.33574516
A33: 4 | B33: =INDEX('P01-CostOverrun'!$A$5:$A$54,MATCH($E33,'P01-CostOverrun'!$K$5:$K$54,0)) -> WT-1034 | C33: =INDEX('P01-CostOverrun'!$B$5:$B$54,MATCH($E33,'P01-CostOverrun'!$K$5:$K$54,0)) -> University Campus Kol-35 | D33: =INDEX('P01-CostOverrun'!$E$5:$E$54,MATCH($E33,'P01-CostOverrun'!$K$5:$K$54,0)) -> University Campus | E33: =LARGE('P01-CostOverrun'!$K$5:$K$54,$A33) -> 19335358 | F33: =INDEX('P01-CostOverrun'!$J$5:$J$54,MATCH($E33,'P01-CostOverrun'!$K$5:$K$54,0)) -> 0.34805973
A34: 5 | B34: =INDEX('P01-CostOverrun'!$A$5:$A$54,MATCH($E34,'P01-CostOverrun'!$K$5:$K$54,0)) -> WT-1043 | C34: =INDEX('P01-CostOverrun'!$B$5:$B$54,MATCH($E34,'P01-CostOverrun'!$K$5:$K$54,0)) -> Industrial Warehouse Can-44 | D34: =INDEX('P01-CostOverrun'!$E$5:$E$54,MATCH($E34,'P01-CostOverrun'!$K$5:$K$54,0)) -> Industrial Warehouse | E34: =LARGE('P01-CostOverrun'!$K$5:$K$54,$A34) -> 19116067 | F34: =INDEX('P01-CostOverrun'!$J$5:$J$54,MATCH($E34,'P01-CostOverrun'!$K$5:$K$54,0)) -> 0.29553469
A35: ="ANSWER: Largest single overrun is "&$C$30&" ("&$B$30&") at "&TEXT($E$30,"""$""#,##0")&" ("&TEXT($F$30,"0.0%")&"). The top 5 together account for "&TEXT(SUM($E$30:$E$34),"""$""#,##0")&" of overrun." -> ANSWER: Largest single overrun is Residential Tower Per-29 (WT-1028) at $2,46,54,239 (33.1%). The top 5 together account for $10,44,73,202 of overrun.
A37: Q4. Is there a correlation between project duration and cost overrun percentage?
A38: Correlation coefficient (Duration months vs Overrun %) | B38: =CORREL('P01-CostOverrun'!$H$5:$H$54,'P01-CostOverrun'!$J$5:$J$54) -> -0.15637931
A39: ="ANSWER: r = "&TEXT($B$38,"0.000")&" — "&IF(ABS($B$38)<0.2,"effectively no linear relationship; duration does not explain cost overrun in this portfolio",IF(ABS($B$38)<0.5,"a weak "&IF($B$38>0,"positive","negative")&" relationship","a strong "&IF($B$38>0,"positive","negative")&" relationship"))&"." -> ANSWER: r = -0.156 — effectively no linear relationship; duration does not explain cost overrun in this portfolio.
A41: Q5. Pivot — average overrun % by Country × Project Type
A42: Project Type | B42: Australia | C42: India | D42: New Zealand | E42: Grand Average | F42: Projects
A43: Residential Tower | B43: =IFERROR(AVERAGEIFS('P01-CostOverrun'!$J$5:$J$54,'P01-CostOverrun'!$E$5:$E$54,$A43,'P01-CostOverrun'!$D$5:$D$54,B$42),"-") -> 0.23322555 | C43: =IFERROR(AVERAGEIFS('P01-CostOverrun'!$J$5:$J$54,'P01-CostOverrun'!$E$5:$E$54,$A43,'P01-CostOverrun'!$D$5:$D$54,C$42),"-") -> 0.25865153 | D43: =IFERROR(AVERAGEIFS('P01-CostOverrun'!$J$5:$J$54,'P01-CostOverrun'!$E$5:$E$54,$A43,'P01-CostOverrun'!$D$5:$D$54,D$42),"-") -> - | E43: =AVERAGEIF('P01-CostOverrun'!$E$5:$E$54,$A43,'P01-CostOverrun'!$J$5:$J$54) -> 0.24593854 | F43: =COUNTIF('P01-CostOverrun'!$E$5:$E$54,$A43) -> 4
A44: IT Park | B44: =IFERROR(AVERAGEIFS('P01-CostOverrun'!$J$5:$J$54,'P01-CostOverrun'!$E$5:$E$54,$A44,'P01-CostOverrun'!$D$5:$D$54,B$42),"-") -> 0.15299023 | C44: =IFERROR(AVERAGEIFS('P01-CostOverrun'!$J$5:$J$54,'P01-CostOverrun'!$E$5:$E$54,$A44,'P01-CostOverrun'!$D$5:$D$54,C$42),"-") -> 0.18083416 | D44: =IFERROR(AVERAGEIFS('P01-CostOverrun'!$J$5:$J$54,'P01-CostOverrun'!$E$5:$E$54,$A44,'P01-CostOverrun'!$D$5:$D$54,D$42),"-") -> 0.24880551 | E44: =AVERAGEIF('P01-CostOverrun'!$E$5:$E$54,$A44,'P01-CostOverrun'!$J$5:$J$54) -> 0.18258894 | F44: =COUNTIF('P01-CostOverrun'!$E$5:$E$54,$A44) -> 7
A45: University Campus | B45: =IFERROR(AVERAGEIFS('P01-CostOverrun'!$J$5:$J$54,'P01-CostOverrun'!$E$5:$E$54,$A45,'P01-CostOverrun'!$D$5:$D$54,B$42),"-") -> 0.088721909 | C45: =IFERROR(AVERAGEIFS('P01-CostOverrun'!$J$5:$J$54,'P01-CostOverrun'!$E$5:$E$54,$A45,'P01-CostOverrun'!$D$5:$D$54,C$42),"-") -> 0.27213993 | D45: =IFERROR(AVERAGEIFS('P01-CostOverrun'!$J$5:$J$54,'P01-CostOverrun'!$E$5:$E$54,$A45,'P01-CostOverrun'!$D$5:$D$54,D$42),"-") -> - | E45: =AVERAGEIF('P01-CostOverrun'!$E$5:$E$54,$A45,'P01-CostOverrun'!$J$5:$J$54) -> 0.21100059 | F45: =COUNTIF('P01-CostOverrun'!$E$5:$E$54,$A45) -> 6
A46: Industrial Warehouse | B46: =IFERROR(AVERAGEIFS('P01-CostOverrun'!$J$5:$J$54,'P01-CostOverrun'!$E$5:$E$54,$A46,'P01-CostOverrun'!$D$5:$D$54,B$42),"-") -> 0.29553469 | C46: =IFERROR(AVERAGEIFS('P01-CostOverrun'!$J$5:$J$54,'P01-CostOverrun'!$E$5:$E$54,$A46,'P01-CostOverrun'!$D$5:$D$54,C$42),"-") -> 0.061148534 | D46: =IFERROR(AVERAGEIFS('P01-CostOverrun'!$J$5:$J$54,'P01-CostOverrun'!$E$5:$E$54,$A46,'P01-CostOverrun'!$D$5:$D$54,D$42),"-") -> 0.037728288 | E46: =AVERAGEIF('P01-CostOverrun'!$E$5:$E$54,$A46,'P01-CostOverrun'!$J$5:$J$54) -> 0.1314705 | F46: =COUNTIF('P01-CostOverrun'!$E$5:$E$54,$A46) -> 3
A47: Data Centre | B47: =IFERROR(AVERAGEIFS('P01-CostOverrun'!$J$5:$J$54,'P01-CostOverrun'!$E$5:$E$54,$A47,'P01-CostOverrun'!$D$5:$D$54,B$42),"-") -> 0.11293848 | C47: =IFERROR(AVERAGEIFS('P01-CostOverrun'!$J$5:$J$54,'P01-CostOverrun'!$E$5:$E$54,$A47,'P01-CostOverrun'!$D$5:$D$54,C$42),"-") -> 0.12639265 | D47: =IFERROR(AVERAGEIFS('P01-CostOverrun'!$J$5:$J$54,'P01-CostOverrun'!$E$5:$E$54,$A47,'P01-CostOverrun'!$D$5:$D$54,D$42),"-") -> -0.018479937 | E47: =AVERAGEIF('P01-CostOverrun'!$E$5:$E$54,$A47,'P01-CostOverrun'!$J$5:$J$54) -> 0.10730588 | F47: =COUNTIF('P01-CostOverrun'!$E$5:$E$54,$A47) -> 9
A48: Hospital | B48: =IFERROR(AVERAGEIFS('P01-CostOverrun'!$J$5:$J$54,'P01-CostOverrun'!$E$5:$E$54,$A48,'P01-CostOverrun'!$D$5:$D$54,B$42),"-") -> 0.18570627 | C48: =IFERROR(AVERAGEIFS('P01-CostOverrun'!$J$5:$J$54,'P01-CostOverrun'!$E$5:$E$54,$A48,'P01-CostOverrun'!$D$5:$D$54,C$42),"-") -> 0.23834115 | D48: =IFERROR(AVERAGEIFS('P01-CostOverrun'!$J$5:$J$54,'P01-CostOverrun'!$E$5:$E$54,$A48,'P01-CostOverrun'!$D$5:$D$54,D$42),"-") -> 0.29905895 | E48: =AVERAGEIF('P01-CostOverrun'!$E$5:$E$54,$A48,'P01-CostOverrun'!$J$5:$J$54) -> 0.25210129 | F48: =COUNTIF('P01-CostOverrun'!$E$5:$E$54,$A48) -> 5
A49: Commercial Office | B49: =IFERROR(AVERAGEIFS('P01-CostOverrun'!$J$5:$J$54,'P01-CostOverrun'!$E$5:$E$54,$A49,'P01-CostOverrun'!$D$5:$D$54,B$42),"-") -> - | C49: =IFERROR(AVERAGEIFS('P01-CostOverrun'!$J$5:$J$54,'P01-CostOverrun'!$E$5:$E$54,$A49,'P01-CostOverrun'!$D$5:$D$54,C$42),"-") -> 0.13323602 | D49: =IFERROR(AVERAGEIFS('P01-CostOverrun'!$J$5:$J$54,'P01-CostOverrun'!$E$5:$E$54,$A49,'P01-CostOverrun'!$D$5:$D$54,D$42),"-") -> - | E49: =AVERAGEIF('P01-CostOverrun'!$E$5:$E$54,$A49,'P01-CostOverrun'!$J$5:$J$54) -> 0.13323602 | F49: =COUNTIF('P01-CostOverrun'!$E$5:$E$54,$A49) -> 3
A50: Hotel | B50: =IFERROR(AVERAGEIFS('P01-CostOverrun'!$J$5:$J$54,'P01-CostOverrun'!$E$5:$E$54,$A50,'P01-CostOverrun'!$D$5:$D$54,B$42),"-") -> 0.22210857 | C50: =IFERROR(AVERAGEIFS('P01-CostOverrun'!$J$5:$J$54,'P01-CostOverrun'!$E$5:$E$54,$A50,'P01-CostOverrun'!$D$5:$D$54,C$42),"-") -> 0.074256278 | D50: =IFERROR(AVERAGEIFS('P01-CostOverrun'!$J$5:$J$54,'P01-CostOverrun'!$E$5:$E$54,$A50,'P01-CostOverrun'!$D$5:$D$54,D$42),"-") -> - | E50: =AVERAGEIF('P01-CostOverrun'!$E$5:$E$54,$A50,'P01-CostOverrun'!$J$5:$J$54) -> 0.13762155 | F50: =COUNTIF('P01-CostOverrun'!$E$5:$E$54,$A50) -> 7
A51: Metro Station | B51: =IFERROR(AVERAGEIFS('P01-CostOverrun'!$J$5:$J$54,'P01-CostOverrun'!$E$5:$E$54,$A51,'P01-CostOverrun'!$D$5:$D$54,B$42),"-") -> 0.09327325 | C51: =IFERROR(AVERAGEIFS('P01-CostOverrun'!$J$5:$J$54,'P01-CostOverrun'!$E$5:$E$54,$A51,'P01-CostOverrun'!$D$5:$D$54,C$42),"-") -> 0.057979113 | D51: =IFERROR(AVERAGEIFS('P01-CostOverrun'!$J$5:$J$54,'P01-CostOverrun'!$E$5:$E$54,$A51,'P01-CostOverrun'!$D$5:$D$54,D$42),"-") -> 0.25808028 | E51: =AVERAGEIF('P01-CostOverrun'!$E$5:$E$54,$A51,'P01-CostOverrun'!$J$5:$J$54) -> 0.15213723 | F51: =COUNTIF('P01-CostOverrun'!$E$5:$E$54,$A51) -> 5
A52: Shopping Mall | B52: =IFERROR(AVERAGEIFS('P01-CostOverrun'!$J$5:$J$54,'P01-CostOverrun'!$E$5:$E$54,$A52,'P01-CostOverrun'!$D$5:$D$54,B$42),"-") -> - | C52: =IFERROR(AVERAGEIFS('P01-CostOverrun'!$J$5:$J$54,'P01-CostOverrun'!$E$5:$E$54,$A52,'P01-CostOverrun'!$D$5:$D$54,C$42),"-") -> 0.033802807 | D52: =IFERROR(AVERAGEIFS('P01-CostOverrun'!$J$5:$J$54,'P01-CostOverrun'!$E$5:$E$54,$A52,'P01-CostOverrun'!$D$5:$D$54,D$42),"-") -> - | E52: =AVERAGEIF('P01-CostOverrun'!$E$5:$E$54,$A52,'P01-CostOverrun'!$J$5:$J$54) -> 0.033802807 | F52: =COUNTIF('P01-CostOverrun'!$E$5:$E$54,$A52) -> 1
A53: Grand Average | B53: =AVERAGEIF('P01-CostOverrun'!$D$5:$D$54,B$42,'P01-CostOverrun'!$J$5:$J$54) -> 0.16732437 | C53: =AVERAGEIF('P01-CostOverrun'!$D$5:$D$54,C$42,'P01-CostOverrun'!$J$5:$J$54) -> 0.15763933 | D53: =AVERAGEIF('P01-CostOverrun'!$D$5:$D$54,D$42,'P01-CostOverrun'!$J$5:$J$54) -> 0.19747604 | E53: =AVERAGE('P01-CostOverrun'!$J$5:$J$54) -> 0.16612198 | F53: =SUM(F43:F52) -> 50
A54: Max-cell locator (row offset, col offset) | B54: {=SUMPRODUCT(MAX(($B$43:$D$52=MAX($B$43:$D$52))*ROW($B$43:$D$52)))-42} -> 6 | C54: {=SUMPRODUCT(MAX(($B$43:$D$52=MAX($B$43:$D$52))*COLUMN($B$43:$D$52)))-1} -> 3
A55: {="ANSWER: Highest average overrun combination is "&INDEX($A$43:$A$52,$B$54)&" in "&INDEX($B$42:$D$42,$C$54)&" at "&TEXT(MAX($B$43:$D$52),"0.0%")&". Portfolio average overrun is "&TEXT($E$53,"0.0%")&"."} -> ANSWER: Highest average overrun combination is Hospital in New Zealand at 29.9%. Portfolio average overrun is 16.6%.
A57: Q6. What percentage of projects came in under budget vs over budget?
A58: Category | B58: No. of Projects | C58: % of Portfolio
A59: Over budget (variance > 0) | B59: =COUNTIF('P01-CostOverrun'!$J$5:$J$54,">0") -> 45 | C59: =B59/$B$61 -> 0.9
A60: Under budget (variance < 0) | B60: =COUNTIF('P01-CostOverrun'!$J$5:$J$54,"<0") -> 5 | C60: =B60/$B$61 -> 0.1
A61: Total | B61: =COUNT('P01-CostOverrun'!$J$5:$J$54) -> 50 | C61: =B61/$B$61 -> 1
A62: ="ANSWER: "&TEXT($C$59,"0.0%")&" of projects ("&$B$59&" of "&$B$61&") came in over budget and "&TEXT($C$60,"0.0%")&" ("&$B$60&") under budget." -> ANSWER: 90.0% of projects (45 of 50) came in over budget and 10.0% (5) under budget.
A64: Q7. Which city has the most cost-efficient project delivery?
A65: City | B65: Avg Overrun % | C65: No. of Projects | D65: Total Budget USD | E65: Total Actual USD
A66: Perth | B66: =AVERAGEIF('P01-CostOverrun'!$C$5:$C$54,$A66,'P01-CostOverrun'!$J$5:$J$54) -> 0.18796888 | C66: =COUNTIF('P01-CostOverrun'!$C$5:$C$54,$A66) -> 5 | D66: =SUMIF('P01-CostOverrun'!$C$5:$C$54,$A66,'P01-CostOverrun'!$F$5:$F$54) -> 245312751 | E66: =SUMIF('P01-CostOverrun'!$C$5:$C$54,$A66,'P01-CostOverrun'!$G$5:$G$54) -> 295064019 | F66: =E66/D66-1 -> 0.20280751
A67: Hyderabad | B67: =AVERAGEIF('P01-CostOverrun'!$C$5:$C$54,$A67,'P01-CostOverrun'!$J$5:$J$54) -> 0.25865153 | C67: =COUNTIF('P01-CostOverrun'!$C$5:$C$54,$A67) -> 2 | D67: =SUMIF('P01-CostOverrun'!$C$5:$C$54,$A67,'P01-CostOverrun'!$F$5:$F$54) -> 124452671 | E67: =SUMIF('P01-CostOverrun'!$C$5:$C$54,$A67,'P01-CostOverrun'!$G$5:$G$54) -> 157142270 | F67: =E67/D67-1 -> 0.26266691
A68: Sydney | B68: =AVERAGEIF('P01-CostOverrun'!$C$5:$C$54,$A68,'P01-CostOverrun'!$J$5:$J$54) -> 0.33574516 | C68: =COUNTIF('P01-CostOverrun'!$C$5:$C$54,$A68) -> 1 | D68: =SUMIF('P01-CostOverrun'!$C$5:$C$54,$A68,'P01-CostOverrun'!$F$5:$F$54) -> 58792612 | E68: =SUMIF('P01-CostOverrun'!$C$5:$C$54,$A68,'P01-CostOverrun'!$G$5:$G$54) -> 78531947 | F68: =E68/D68-1 -> 0.33574516
A69: Kolkata | B69: =AVERAGEIF('P01-CostOverrun'!$C$5:$C$54,$A69,'P01-CostOverrun'!$J$5:$J$54) -> 0.2090111 | C69: =COUNTIF('P01-CostOverrun'!$C$5:$C$54,$A69) -> 4 | D69: =SUMIF('P01-CostOverrun'!$C$5:$C$54,$A69,'P01-CostOverrun'!$F$5:$F$54) -> 134555617 | E69: =SUMIF('P01-CostOverrun'!$C$5:$C$54,$A69,'P01-CostOverrun'!$G$5:$G$54) -> 163376489 | F69: =E69/D69-1 -> 0.21419301
A70: Canberra | B70: =AVERAGEIF('P01-CostOverrun'!$C$5:$C$54,$A70,'P01-CostOverrun'!$J$5:$J$54) -> 0.20543072 | C70: =COUNTIF('P01-CostOverrun'!$C$5:$C$54,$A70) -> 3 | D70: =SUMIF('P01-CostOverrun'!$C$5:$C$54,$A70,'P01-CostOverrun'!$F$5:$F$54) -> 166360502 | E70: =SUMIF('P01-CostOverrun'!$C$5:$C$54,$A70,'P01-CostOverrun'!$G$5:$G$54) -> 202363636 | F70: =E70/D70-1 -> 0.21641636
A71: Delhi | B71: =AVERAGEIF('P01-CostOverrun'!$C$5:$C$54,$A71,'P01-CostOverrun'!$J$5:$J$54) -> 0.16715203 | C71: =COUNTIF('P01-CostOverrun'!$C$5:$C$54,$A71) -> 3 | D71: =SUMIF('P01-CostOverrun'!$C$5:$C$54,$A71,'P01-CostOverrun'!$F$5:$F$54) -> 126142816 | E71: =SUMIF('P01-CostOverrun'!$C$5:$C$54,$A71,'P01-CostOverrun'!$G$5:$G$54) -> 150895749 | F71: =E71/D71-1 -> 0.19622943
A72: Mumbai | B72: =AVERAGEIF('P01-CostOverrun'!$C$5:$C$54,$A72,'P01-CostOverrun'!$J$5:$J$54) -> 0.15776248 | C72: =COUNTIF('P01-CostOverrun'!$C$5:$C$54,$A72) -> 6 | D72: =SUMIF('P01-CostOverrun'!$C$5:$C$54,$A72,'P01-CostOverrun'!$F$5:$F$54) -> 282524903 | E72: =SUMIF('P01-CostOverrun'!$C$5:$C$54,$A72,'P01-CostOverrun'!$G$5:$G$54) -> 334004416 | F72: =E72/D72-1 -> 0.1822123
A73: Auckland | B73: =AVERAGEIF('P01-CostOverrun'!$C$5:$C$54,$A73,'P01-CostOverrun'!$J$5:$J$54) -> 0.31097713 | C73: =COUNTIF('P01-CostOverrun'!$C$5:$C$54,$A73) -> 1 | D73: =SUMIF('P01-CostOverrun'!$C$5:$C$54,$A73,'P01-CostOverrun'!$F$5:$F$54) -> 55826716 | E73: =SUMIF('P01-CostOverrun'!$C$5:$C$54,$A73,'P01-CostOverrun'!$G$5:$G$54) -> 73187548 | F73: =E73/D73-1 -> 0.31097713
A74: Chennai | B74: =AVERAGEIF('P01-CostOverrun'!$C$5:$C$54,$A74,'P01-CostOverrun'!$J$5:$J$54) -> 0.16725679 | C74: =COUNTIF('P01-CostOverrun'!$C$5:$C$54,$A74) -> 4 | D74: =SUMIF('P01-CostOverrun'!$C$5:$C$54,$A74,'P01-CostOverrun'!$F$5:$F$54) -> 178758813 | E74: =SUMIF('P01-CostOverrun'!$C$5:$C$54,$A74,'P01-CostOverrun'!$G$5:$G$54) -> 210269197 | F74: =E74/D74-1 -> 0.17627318
A75: Christchurch | B75: =AVERAGEIF('P01-CostOverrun'!$C$5:$C$54,$A75,'P01-CostOverrun'!$J$5:$J$54) -> 0.17248878 | C75: =COUNTIF('P01-CostOverrun'!$C$5:$C$54,$A75) -> 3 | D75: =SUMIF('P01-CostOverrun'!$C$5:$C$54,$A75,'P01-CostOverrun'!$F$5:$F$54) -> 135595096 | E75: =SUMIF('P01-CostOverrun'!$C$5:$C$54,$A75,'P01-CostOverrun'!$G$5:$G$54) -> 156962814 | F75: =E75/D75-1 -> 0.15758474
A76: Adelaide | B76: =AVERAGEIF('P01-CostOverrun'!$C$5:$C$54,$A76,'P01-CostOverrun'!$J$5:$J$54) -> 0.14062385 | C76: =COUNTIF('P01-CostOverrun'!$C$5:$C$54,$A76) -> 3 | D76: =SUMIF('P01-CostOverrun'!$C$5:$C$54,$A76,'P01-CostOverrun'!$F$5:$F$54) -> 148852192 | E76: =SUMIF('P01-CostOverrun'!$C$5:$C$54,$A76,'P01-CostOverrun'!$G$5:$G$54) -> 173354770 | F76: =E76/D76-1 -> 0.16461013
A77: Hamilton | B77: =AVERAGEIF('P01-CostOverrun'!$C$5:$C$54,$A77,'P01-CostOverrun'!$J$5:$J$54) -> 0.15078802 | C77: =COUNTIF('P01-CostOverrun'!$C$5:$C$54,$A77) -> 2 | D77: =SUMIF('P01-CostOverrun'!$C$5:$C$54,$A77,'P01-CostOverrun'!$F$5:$F$54) -> 85200877 | E77: =SUMIF('P01-CostOverrun'!$C$5:$C$54,$A77,'P01-CostOverrun'!$G$5:$G$54) -> 96242381 | F77: =E77/D77-1 -> 0.12959378
... A83: Gold Coast | B83: =AVERAGEIF('P01-CostOverrun'!$C$5:$C$54,$A83,'P01-CostOverrun'!$J$5:$J$54) -> -0.029764706 | C83: =COUNTIF('P01-CostOverrun'!$C$5:$C$54,$A83) -> 1 | D83: =SUMIF('P01-CostOverrun'!$C$5:$C$54,$A83,'P01-CostOverrun'!$F$5:$F$54) -> 15141087 | E83: =SUMIF('P01-CostOverrun'!$C$5:$C$54,$A83,'P01-CostOverrun'!$G$5:$G$54) -> 14690417 | F83: =E83/D83-1 -> -0.029764706
A84: ="ANSWER: "&INDEX($A$66:$A$83,MATCH(MIN($B$66:$B$83),$B$66:$B$83,0))&" is the most cost-efficient city (avg overrun "&TEXT(MIN($B$66:$B$83),"0.0%")&"), while "&INDEX($A$66:$A$83,MATCH(MAX($B$66:$B$83),$B$66:$B$83,0))&" is the least efficient ("&TEXT(MAX($B$66:$B$83),"0.0%")&"). Note: small samples per city." -> ANSWER: Gold Coast is the most cost-efficient city (avg overrun -3.0%), while Sydney is the least efficient (33.6%). Note: small samples per city.
A86: PROBLEM 02 — Material Price Fluctuation Tracker | Source sheet: P02-MaterialPrice (90 records, 15 materials, 18 months)
A87: Q1. Which material has shown the highest average price increase over 18 months?
A88: Material | B88: Unit | C88: Avg Price Change % | D88: Data Points | E88: Avg Base Price USD | F88: Avg Current Price USD
A89: Waterproofing Membrane | B89: =INDEX('P02-MaterialPrice'!$C$5:$C$94,MATCH($A89,'P02-MaterialPrice'!$B$5:$B$94,0)) -> sqm | C89: =AVERAGEIF('P02-MaterialPrice'!$B$5:$B$94,$A89,'P02-MaterialPrice'!$H$5:$H$94) -> 0.0252 | D89: =COUNTIF('P02-MaterialPrice'!$B$5:$B$94,$A89) -> 10 | E89: =AVERAGEIF('P02-MaterialPrice'!$B$5:$B$94,$A89,'P02-MaterialPrice'!$D$5:$D$94) -> 15 | F89: =AVERAGEIF('P02-MaterialPrice'!$B$5:$B$94,$A89,'P02-MaterialPrice'!$E$5:$E$94) -> 15.378
A90: Cement (OPC 53) | B90: =INDEX('P02-MaterialPrice'!$C$5:$C$94,MATCH($A90,'P02-MaterialPrice'!$B$5:$B$94,0)) -> MT | C90: =AVERAGEIF('P02-MaterialPrice'!$B$5:$B$94,$A90,'P02-MaterialPrice'!$H$5:$H$94) -> 0.11856863 | D90: =COUNTIF('P02-MaterialPrice'!$B$5:$B$94,$A90) -> 6 | E90: =AVERAGEIF('P02-MaterialPrice'!$B$5:$B$94,$A90,'P02-MaterialPrice'!$D$5:$D$94) -> 85 | F90: =AVERAGEIF('P02-MaterialPrice'!$B$5:$B$94,$A90,'P02-MaterialPrice'!$E$5:$E$94) -> 95.078333
A91: Aluminium Facade | B91: =INDEX('P02-MaterialPrice'!$C$5:$C$94,MATCH($A91,'P02-MaterialPrice'!$B$5:$B$94,0)) -> sqm | C91: =AVERAGEIF('P02-MaterialPrice'!$B$5:$B$94,$A91,'P02-MaterialPrice'!$H$5:$H$94) -> 0.11697917 | D91: =COUNTIF('P02-MaterialPrice'!$B$5:$B$94,$A91) -> 8 | E91: =AVERAGEIF('P02-MaterialPrice'!$B$5:$B$94,$A91,'P02-MaterialPrice'!$D$5:$D$94) -> 120 | F91: =AVERAGEIF('P02-MaterialPrice'!$B$5:$B$94,$A91,'P02-MaterialPrice'!$E$5:$E$94) -> 134.0375
A92: Bricks (AAC) | B92: =INDEX('P02-MaterialPrice'!$C$5:$C$94,MATCH($A92,'P02-MaterialPrice'!$B$5:$B$94,0)) -> 1000 nos | C92: =AVERAGEIF('P02-MaterialPrice'!$B$5:$B$94,$A92,'P02-MaterialPrice'!$H$5:$H$94) -> 0.077399123 | D92: =COUNTIF('P02-MaterialPrice'!$B$5:$B$94,$A92) -> 6 | E92: =AVERAGEIF('P02-MaterialPrice'!$B$5:$B$94,$A92,'P02-MaterialPrice'!$D$5:$D$94) -> 380 | F92: =AVERAGEIF('P02-MaterialPrice'!$B$5:$B$94,$A92,'P02-MaterialPrice'!$E$5:$E$94) -> 409.41167
A93: Tiles (Vitrified) | B93: =INDEX('P02-MaterialPrice'!$C$5:$C$94,MATCH($A93,'P02-MaterialPrice'!$B$5:$B$94,0)) -> sqm | C93: =AVERAGEIF('P02-MaterialPrice'!$B$5:$B$94,$A93,'P02-MaterialPrice'!$H$5:$H$94) -> 0.083611111 | D93: =COUNTIF('P02-MaterialPrice'!$B$5:$B$94,$A93) -> 6 | E93: =AVERAGEIF('P02-MaterialPrice'!$B$5:$B$94,$A93,'P02-MaterialPrice'!$D$5:$D$94) -> 18 | F93: =AVERAGEIF('P02-MaterialPrice'!$B$5:$B$94,$A93,'P02-MaterialPrice'!$E$5:$E$94) -> 19.505
A94: PVC Conduits | B94: =INDEX('P02-MaterialPrice'!$C$5:$C$94,MATCH($A94,'P02-MaterialPrice'!$B$5:$B$94,0)) -> m | C94: =AVERAGEIF('P02-MaterialPrice'!$B$5:$B$94,$A94,'P02-MaterialPrice'!$H$5:$H$94) -> 0.030416667 | D94: =COUNTIF('P02-MaterialPrice'!$B$5:$B$94,$A94) -> 8 | E94: =AVERAGEIF('P02-MaterialPrice'!$B$5:$B$94,$A94,'P02-MaterialPrice'!$D$5:$D$94) -> 3 | F94: =AVERAGEIF('P02-MaterialPrice'!$B$5:$B$94,$A94,'P02-MaterialPrice'!$E$5:$E$94) -> 3.09125
A95: Sand (River) | B95: =INDEX('P02-MaterialPrice'!$C$5:$C$94,MATCH($A95,'P02-MaterialPrice'!$B$5:$B$94,0)) -> cum | C95: =AVERAGEIF('P02-MaterialPrice'!$B$5:$B$94,$A95,'P02-MaterialPrice'!$H$5:$H$94) -> 0.0952 | D95: =COUNTIF('P02-MaterialPrice'!$B$5:$B$94,$A95) -> 4 | E95: =AVERAGEIF('P02-MaterialPrice'!$B$5:$B$94,$A95,'P02-MaterialPrice'!$D$5:$D$94) -> 25 | F95: =AVERAGEIF('P02-MaterialPrice'!$B$5:$B$94,$A95,'P02-MaterialPrice'!$E$5:$E$94) -> 27.38
A96: Structural Steel | B96: =INDEX('P02-MaterialPrice'!$C$5:$C$94,MATCH($A96,'P02-MaterialPrice'!$B$5:$B$94,0)) -> MT | C96: =AVERAGEIF('P02-MaterialPrice'!$B$5:$B$94,$A96,'P02-MaterialPrice'!$H$5:$H$94) -> 0.069677193 | D96: =COUNTIF('P02-MaterialPrice'!$B$5:$B$94,$A96) -> 6 | E96: =AVERAGEIF('P02-MaterialPrice'!$B$5:$B$94,$A96,'P02-MaterialPrice'!$D$5:$D$94) -> 950 | F96: =AVERAGEIF('P02-MaterialPrice'!$B$5:$B$94,$A96,'P02-MaterialPrice'!$E$5:$E$94) -> 1016.1933
A97: Aggregate (20mm) | B97: =INDEX('P02-MaterialPrice'!$C$5:$C$94,MATCH($A97,'P02-MaterialPrice'!$B$5:$B$94,0)) -> cum | C97: =AVERAGEIF('P02-MaterialPrice'!$B$5:$B$94,$A97,'P02-MaterialPrice'!$H$5:$H$94) -> 0.14609091 | D97: =COUNTIF('P02-MaterialPrice'!$B$5:$B$94,$A97) -> 5 | E97: =AVERAGEIF('P02-MaterialPrice'!$B$5:$B$94,$A97,'P02-MaterialPrice'!$D$5:$D$94) -> 22 | F97: =AVERAGEIF('P02-MaterialPrice'!$B$5:$B$94,$A97,'P02-MaterialPrice'!$E$5:$E$94) -> 25.214
A98: MS Pipes | B98: =INDEX('P02-MaterialPrice'!$C$5:$C$94,MATCH($A98,'P02-MaterialPrice'!$B$5:$B$94,0)) -> m | C98: =AVERAGEIF('P02-MaterialPrice'!$B$5:$B$94,$A98,'P02-MaterialPrice'!$H$5:$H$94) -> 0.099375 | D98: =COUNTIF('P02-MaterialPrice'!$B$5:$B$94,$A98) -> 4 | E98: =AVERAGEIF('P02-MaterialPrice'!$B$5:$B$94,$A98,'P02-MaterialPrice'!$D$5:$D$94) -> 12 | F98: =AVERAGEIF('P02-MaterialPrice'!$B$5:$B$94,$A98,'P02-MaterialPrice'!$E$5:$E$94) -> 13.1925
A99: RMC M30 | B99: =INDEX('P02-MaterialPrice'!$C$5:$C$94,MATCH($A99,'P02-MaterialPrice'!$B$5:$B$94,0)) -> cum | C99: =AVERAGEIF('P02-MaterialPrice'!$B$5:$B$94,$A99,'P02-MaterialPrice'!$H$5:$H$94) -> 0.1478 | D99: =COUNTIF('P02-MaterialPrice'!$B$5:$B$94,$A99) -> 4 | E99: =AVERAGEIF('P02-MaterialPrice'!$B$5:$B$94,$A99,'P02-MaterialPrice'!$D$5:$D$94) -> 75 | F99: =AVERAGEIF('P02-MaterialPrice'!$B$5:$B$94,$A99,'P02-MaterialPrice'!$E$5:$E$94) -> 86.085
A100: Glass (DGU) | B100: =INDEX('P02-MaterialPrice'!$C$5:$C$94,MATCH($A100,'P02-MaterialPrice'!$B$5:$B$94,0)) -> sqm | C100: =AVERAGEIF('P02-MaterialPrice'!$B$5:$B$94,$A100,'P02-MaterialPrice'!$H$5:$H$94) -> 0.043934211 | D100: =COUNTIF('P02-MaterialPrice'!$B$5:$B$94,$A100) -> 8 | E100: =AVERAGEIF('P02-MaterialPrice'!$B$5:$B$94,$A100,'P02-MaterialPrice'!$D$5:$D$94) -> 95 | F100: =AVERAGEIF('P02-MaterialPrice'!$B$5:$B$94,$A100,'P02-MaterialPrice'!$E$5:$E$94) -> 99.17375
... A103: TMT Steel (Fe500) | B103: =INDEX('P02-MaterialPrice'!$C$5:$C$94,MATCH($A103,'P02-MaterialPrice'!$B$5:$B$94,0)) -> MT | C103: =AVERAGEIF('P02-MaterialPrice'!$B$5:$B$94,$A103,'P02-MaterialPrice'!$H$5:$H$94) -> 0.039138462 | D103: =COUNTIF('P02-MaterialPrice'!$B$5:$B$94,$A103) -> 4 | E103: =AVERAGEIF('P02-MaterialPrice'!$B$5:$B$94,$A103,'P02-MaterialPrice'!$D$5:$D$94) -> 650 | F103: =AVERAGEIF('P02-MaterialPrice'!$B$5:$B$94,$A103,'P02-MaterialPrice'!$E$5:$E$94) -> 675.44
A104: ="ANSWER: "&INDEX($A$89:$A$103,MATCH(MAX($C$89:$C$103),$C$89:$C$103,0))&" shows the highest average price increase at "&TEXT(MAX($C$89:$C$103),"0.0%")&"; the lowest is "&INDEX($A$89:$A$103,MATCH(MIN($C$89:$C$103),$C$89:$C$103,0))&" at "&TEXT(MIN($C$89:$C$103),"0.0%")&"." -> ANSWER: RMC M30 shows the highest average price increase at 14.8%; the lowest is Copper Wiring at 1.9%.
A106: Q2. Monthly price trend for TMT Steel and Cement (line chart placed to the right)
A107: Month | B107: TMT Steel (Fe500) USD/MT | C107: Cement (OPC 53) USD/MT | D107: Month Index
A108: 2024-01 | B108: =IFERROR(AVERAGEIFS('P02-MaterialPrice'!$E$5:$E$94,'P02-MaterialPrice'!$B$5:$B$94,"TMT Steel (Fe500)",'P02-MaterialPrice'!$A$5:$A$94,$A108),NA()) -> #N/A | C108: =IFERROR(AVERAGEIFS('P02-MaterialPrice'!$E$5:$E$94,'P02-MaterialPrice'!$B$5:$B$94,"Cement (OPC 53)",'P02-MaterialPrice'!$A$5:$A$94,$A108),NA()) -> 96.77 | D108: 1
A109: 2024-02 | B109: =IFERROR(AVERAGEIFS('P02-MaterialPrice'!$E$5:$E$94,'P02-MaterialPrice'!$B$5:$B$94,"TMT Steel (Fe500)",'P02-MaterialPrice'!$A$5:$A$94,$A109),NA()) -> #N/A | C109: =IFERROR(AVERAGEIFS('P02-MaterialPrice'!$E$5:$E$94,'P02-MaterialPrice'!$B$5:$B$94,"Cement (OPC 53)",'P02-MaterialPrice'!$A$5:$A$94,$A109),NA()) -> 94.59 | D109: 2
A110: 2024-03 | B110: =IFERROR(AVERAGEIFS('P02-MaterialPrice'!$E$5:$E$94,'P02-MaterialPrice'!$B$5:$B$94,"TMT Steel (Fe500)",'P02-MaterialPrice'!$A$5:$A$94,$A110),NA()) -> 710.14 | C110: =IFERROR(AVERAGEIFS('P02-MaterialPrice'!$E$5:$E$94,'P02-MaterialPrice'!$B$5:$B$94,"Cement (OPC 53)",'P02-MaterialPrice'!$A$5:$A$94,$A110),NA()) -> #N/A | D110: 3
A111: 2024-04 | B111: =IFERROR(AVERAGEIFS('P02-MaterialPrice'!$E$5:$E$94,'P02-MaterialPrice'!$B$5:$B$94,"TMT Steel (Fe500)",'P02-MaterialPrice'!$A$5:$A$94,$A111),NA()) -> #N/A | C111: =IFERROR(AVERAGEIFS('P02-MaterialPrice'!$E$5:$E$94,'P02-MaterialPrice'!$B$5:$B$94,"Cement (OPC 53)",'P02-MaterialPrice'!$A$5:$A$94,$A111),NA()) -> #N/A | D111: 4
A112: 2024-05 | B112: =IFERROR(AVERAGEIFS('P02-MaterialPrice'!$E$5:$E$94,'P02-MaterialPrice'!$B$5:$B$94,"TMT Steel (Fe500)",'P02-MaterialPrice'!$A$5:$A$94,$A112),NA()) -> #N/A | C112: =IFERROR(AVERAGEIFS('P02-MaterialPrice'!$E$5:$E$94,'P02-MaterialPrice'!$B$5:$B$94,"Cement (OPC 53)",'P02-MaterialPrice'!$A$5:$A$94,$A112),NA()) -> #N/A | D112: 5
A113: 2024-06 | B113: =IFERROR(AVERAGEIFS('P02-MaterialPrice'!$E$5:$E$94,'P02-MaterialPrice'!$B$5:$B$94,"TMT Steel (Fe500)",'P02-MaterialPrice'!$A$5:$A$94,$A113),NA()) -> #N/A | C113: =IFERROR(AVERAGEIFS('P02-MaterialPrice'!$E$5:$E$94,'P02-MaterialPrice'!$B$5:$B$94,"Cement (OPC 53)",'P02-MaterialPrice'!$A$5:$A$94,$A113),NA()) -> 81.11 | D113: 6
A114: 2024-07 | B114: =IFERROR(AVERAGEIFS('P02-MaterialPrice'!$E$5:$E$94,'P02-MaterialPrice'!$B$5:$B$94,"TMT Steel (Fe500)",'P02-MaterialPrice'!$A$5:$A$94,$A114),NA()) -> #N/A | C114: =IFERROR(AVERAGEIFS('P02-MaterialPrice'!$E$5:$E$94,'P02-MaterialPrice'!$B$5:$B$94,"Cement (OPC 53)",'P02-MaterialPrice'!$A$5:$A$94,$A114),NA()) -> #N/A | D114: 7
A115: 2024-08 | B115: =IFERROR(AVERAGEIFS('P02-MaterialPrice'!$E$5:$E$94,'P02-MaterialPrice'!$B$5:$B$94,"TMT Steel (Fe500)",'P02-MaterialPrice'!$A$5:$A$94,$A115),NA()) -> #N/A | C115: =IFERROR(AVERAGEIFS('P02-MaterialPrice'!$E$5:$E$94,'P02-MaterialPrice'!$B$5:$B$94,"Cement (OPC 53)",'P02-MaterialPrice'!$A$5:$A$94,$A115),NA()) -> #N/A | D115: 8
A116: 2024-09 | B116: =IFERROR(AVERAGEIFS('P02-MaterialPrice'!$E$5:$E$94,'P02-MaterialPrice'!$B$5:$B$94,"TMT Steel (Fe500)",'P02-MaterialPrice'!$A$5:$A$94,$A116),NA()) -> #N/A | C116: =IFERROR(AVERAGEIFS('P02-MaterialPrice'!$E$5:$E$94,'P02-MaterialPrice'!$B$5:$B$94,"Cement (OPC 53)",'P02-MaterialPrice'!$A$5:$A$94,$A116),NA()) -> 105.52 | D116: 9
...

Sheet Q&A Chart Dashboard
B1: WT PARTNERSHIP | 86-QUESTION CHART DASHBOARD | BA1: CHART DATA — every cell is a live formula link to 'Analysis report' (or the named source sheet). Do not delete; all 86 charts on this dashboard read from these tables.
BA2: H1 — P01 Q3 — top 5 absolute overruns
B3: One chart per question for all 86 analysis questions listed on the 'Analysis Dashboard ' sheet. Every chart, question title and answer line is a live formula link to the 'Analysis report' sheet — no value is retyped. Chart source tables sit in columns BA:BE of this sheet. | BA3: Project | BB3: Absolute overrun USD
BA4: ='Analysis report'!C30 -> Residential Tower Per-29 | BB4: ='Analysis report'!E30 -> 24654239
B5: CONTENTS — jump to row | BA5: ='Analysis report'!C31 -> Residential Tower Hyd-33 | BB5: ='Analysis report'!E31 -> 21628203
B6: ="P01 — row 13" -> P01 — row 13 | E6: ="P02 — row 82" -> P02 — row 82 | H6: ="P03 — row 129" -> P03 — row 129 | K6: ="P04 — row 176" -> P04 — row 176 | N6: ="P05 — row 223" -> P05 — row 223 | Q6: ="P06 — row 270" -> P06 — row 270 | T6: ="P07 — row 317" -> P07 — row 317 | BA6: ='Analysis report'!C32 -> IT Park Syd-34 | BB6: ='Analysis report'!E32 -> 19739335
B7: ="P08 — row 364" -> P08 — row 364 | E7: ="P09 — row 411" -> P09 — row 411 | H7: ="P10 — row 458" -> P10 — row 458 | K7: ="P12 — row 505" -> P12 — row 505 | N7: ="P13 — row 552" -> P13 — row 552 | Q7: ="P14 — row 599" -> P14 — row 599 | T7: ="P15 — row 646" -> P15 — row 646 | BA7: ='Analysis report'!C33 -> University Campus Kol-35 | BB7: ='Analysis report'!E33 -> 19335358
BA8: ='Analysis report'!C34 -> Industrial Warehouse Can-44 | BB8: ='Analysis report'!E34 -> 19116067
BA10: H2 — P01 Q4 — duration vs overrun (50 projects)
BA11: Duration (months) | BB11: Cost overrun %
BA12: ='P01-CostOverrun'!H5 -> 39 | BB12: ='P01-CostOverrun'!J5 -> 0.33139989
B13: ='Analysis report'!A5 -> PROBLEM 01 — Project Cost Overrun Analysis | Source sheet: P01-CostOverrun (50 projects) | BA13: ='P01-CostOverrun'!H6 -> 16 | BB13: ='P01-CostOverrun'!J6 -> 0.32873946
BA14: ='P01-CostOverrun'!H7 -> 40 | BB14: ='P01-CostOverrun'!J7 -> 0.33574516
B15: ='Analysis report'!A6 -> Q1. Which country has the highest average cost overrun percentage? | I15: ='Analysis report'!A13 -> Q2. What is the total budget vs actual cost for each project type? Which type has the worst variance? | P15: ='Analysis report'!A28 -> Q3. Top 5 projects with the highest absolute cost overrun (USD) | BA15: ='P01-CostOverrun'!H8 -> 47 | BB15: ='P01-CostOverrun'!J8 -> 0.34805973
BA16: ='P01-CostOverrun'!H9 -> 9 | BB16: ='P01-CostOverrun'!J9 -> 0.29553469
B17: ='Analysis report'!A11 -> ANSWER: New Zealand has the highest average cost overrun at 19.7%, vs India the lowest at 15.8%. | I17: ='Analysis report'!A26 -> ANSWER: Worst variance = Residential Tower at 26.3% ($6,26,62,924 over budget). Best = Shopping Mall at 3.4%. Portfolio total: $2,15,23,99,053 budget vs $2,53,19,47,246 actual (17.6%). | P17: ='Analysis report'!A35 -> ANSWER: Largest single overrun is Residential Tower Per-29 (WT-1028) at $2,46,54,239 (33.1%). The top 5 together account for $10,44,73,202 of overrun. | BA17: ='P01-CostOverrun'!H10 -> 40 | BB17: ='P01-CostOverrun'!J10 -> 0.2764093
BA18: ='P01-CostOverrun'!H11 -> 47 | BB18: ='P01-CostOverrun'!J11 -> 0.25035112
BA19: ='P01-CostOverrun'!H12 -> 38 | BB19: ='P01-CostOverrun'!J12 -> 0.25478487
BA20: ='P01-CostOverrun'!H13 -> 16 | BB20: ='P01-CostOverrun'!J13 -> 0.31097713
BA21: ='P01-CostOverrun'!H14 -> 15 | BB21: ='P01-CostOverrun'!J14 -> 0.19358807
BA22: ='P01-CostOverrun'!H15 -> 12 | BB22: ='P01-CostOverrun'!J15 -> 0.24128543
BA23: ='P01-CostOverrun'!H16 -> 9 | BB23: ='P01-CostOverrun'!J16 -> 0.28714076
BA24: ='P01-CostOverrun'!H17 -> 29 | BB24: ='P01-CostOverrun'!J17 -> 0.20427377
BA25: ='P01-CostOverrun'!H18 -> 6 | BB25: ='P01-CostOverrun'!J18 -> 0.18570627
BA26: ='P01-CostOverrun'!H19 -> 30 | BB26: ='P01-CostOverrun'!J19 -> 0.18856361
BA27: ='P01-CostOverrun'!H20 -> 41 | BB27: ='P01-CostOverrun'!J20 -> 0.16164573
BA28: ='P01-CostOverrun'!H21 -> 35 | BB28: ='P01-CostOverrun'!J21 -> 0.27285129
BA29: ='P01-CostOverrun'!H22 -> 21 | BB29: ='P01-CostOverrun'!J22 -> 0.13059445
... BA36: ='P01-CostOverrun'!H29 -> 35 | BB36: ='P01-CostOverrun'!J29 -> 0.12390609
B37: ='Analysis report'!A37 -> Q4. Is there a correlation between project duration and cost overrun percentage? | I37: ='Analysis report'!A41 -> Q5. Pivot — average overrun % by Country × Project Type | P37: ='Analysis report'!A57 -> Q6. What percentage of projects came in under budget vs over budget? | BA37: ='P01-CostOverrun'!H30 -> 10 | BB37: ='P01-CostOverrun'!J30 -> 0.11046591
BA38: ='P01-CostOverrun'!H31 -> 42 | BB38: ='P01-CostOverrun'!J31 -> 0.23934101
B39: ='Analysis report'!A39 -> ANSWER: r = -0.156 — effectively no linear relationship; duration does not explain cost overrun in this portfolio. | I39: ='Analysis report'!A55 -> ANSWER: Highest average overrun combination is Hospital in New Zealand at 29.9%. Portfolio average overrun is 16.6%. | P39: ='Analysis report'!A62 -> ANSWER: 90.0% of projects (45 of 50) came in over budget and 10.0% (5) under budget. | BA39: ='P01-CostOverrun'!H32 -> 14 | BB39: ='P01-CostOverrun'!J32 -> 0.1645143
BA40: ='P01-CostOverrun'!H33 -> 21 | BB40: ='P01-CostOverrun'!J33 -> 0.16365591
BA41: ='P01-CostOverrun'!H34 -> 12 | BB41: ='P01-CostOverrun'!J34 -> 0.29212706
BA42: ='P01-CostOverrun'!H35 -> 13 | BB42: ='P01-CostOverrun'!J35 -> 0.25231279
BA43: ='P01-CostOverrun'!H36 -> 27 | BB43: ='P01-CostOverrun'!J36 -> 0.312168
BA44: ='P01-CostOverrun'!H37 -> 28 | BB44: ='P01-CostOverrun'!J37 -> 0.21359305
BA45: ='P01-CostOverrun'!H38 -> 46 | BB45: ='P01-CostOverrun'!J38 -> 0.057979113
BA46: ='P01-CostOverrun'!H39 -> 19 | BB46: ='P01-CostOverrun'!J39 -> 0.061148534
BA47: ='P01-CostOverrun'!H40 -> 8 | BB47: ='P01-CostOverrun'!J40 -> 0.18619693
BA48: ='P01-CostOverrun'!H41 -> 37 | BB48: ='P01-CostOverrun'!J41 -> 0.061390877
BA49: ='P01-CostOverrun'!H42 -> 41 | BB49: ='P01-CostOverrun'!J42 -> -0.041586315
BA50: ='P01-CostOverrun'!H43 -> 14 | BB50: ='P01-CostOverrun'!J43 -> 0.037728288
BA51: ='P01-CostOverrun'!H44 -> 14 | BB51: ='P01-CostOverrun'!J44 -> 0.047956728
... BA58: ='P01-CostOverrun'!H51 -> 24 | BB58: ='P01-CostOverrun'!J51 -> -0.018479937
B59: ='Analysis report'!A64 -> Q7. Which city has the most cost-efficient project delivery? | BA59: ='P01-CostOverrun'!H52 -> 42 | BB59: ='P01-CostOverrun'!J52 -> -0.026829955
BA60: ='P01-CostOverrun'!H53 -> 37 | BB60: ='P01-CostOverrun'!J53 -> 0.016524425
B61: ='Analysis report'!A84 -> ANSWER: Gold Coast is the most cost-efficient city (avg overrun -3.0%), while Sydney is the least efficient (33.6%). Note: small samples per city. | BA61: ='P01-CostOverrun'!H54 -> 40 | BB61: ='P01-CostOverrun'!J54 -> -0.029764706
BA63: H3 — P02 Q1/Q5 — avg price change by material
BA64: Material | BB64: Avg price change %
BA65: ='Analysis report'!A89 -> Waterproofing Membrane | BB65: ='Analysis report'!C89 -> 0.0252
BA66: ='Analysis report'!A90 -> Cement (OPC 53) | BB66: ='Analysis report'!C90 -> 0.11856863
BA67: ='Analysis report'!A91 -> Aluminium Facade | BB67: ='Analysis report'!C91 -> 0.11697917
BA68: ='Analysis report'!A92 -> Bricks (AAC) | BB68: ='Analysis report'!C92 -> 0.077399123
BA69: ='Analysis report'!A93 -> Tiles (Vitrified) | BB69: ='Analysis report'!C93 -> 0.083611111
BA70: ='Analysis report'!A94 -> PVC Conduits | BB70: ='Analysis report'!C94 -> 0.030416667
BA71: ='Analysis report'!A95 -> Sand (River) | BB71: ='Analysis report'!C95 -> 0.0952
BA72: ='Analysis report'!A96 -> Structural Steel | BB72: ='Analysis report'!C96 -> 0.069677193
BA73: ='Analysis report'!A97 -> Aggregate (20mm) | BB73: ='Analysis report'!C97 -> 0.14609091
BA74: ='Analysis report'!A98 -> MS Pipes | BB74: ='Analysis report'!C98 -> 0.099375
BA75: ='Analysis report'!A99 -> RMC M30 | BB75: ='Analysis report'!C99 -> 0.1478
BA76: ='Analysis report'!A100 -> Glass (DGU) | BB76: ='Analysis report'!C100 -> 0.043934211
... BA79: ='Analysis report'!A103 -> TMT Steel (Fe500) | BB79: ='Analysis report'!C103 -> 0.039138462
BA81: H4 — P02 Q6 — TMT Steel observed + forecast
B82: ='Analysis report'!A86 -> PROBLEM 02 — Material Price Fluctuation Tracker | Source sheet: P02-MaterialPrice (90 records, 15 materials, 18 months) | BA82: Month | BB82: TMT Steel USD/MT
BA83: ='Analysis report'!B149 -> 2024-03 | BB83: ='Analysis report'!D149 -> 710.14
B84: ='Analysis report'!A87 -> Q1. Which material has shown the highest average price increase over 18 months? | I84: ='Analysis report'!A106 -> Q2. Monthly price trend for TMT Steel and Cement (line chart placed to the right) | P84: ='Analysis report'!A128 -> Q3. Which country has the most volatile material pricing? (standard deviation) | BA84: ='Analysis report'!B150 -> 2025-01 | BB84: ='Analysis report'!D150 -> 607.52
BA85: ='Analysis report'!B151 -> 2025-02 | BB85: ='Analysis report'!D151 -> 688.19
B86: ='Analysis report'!A104 -> ANSWER: RMC M30 shows the highest average price increase at 14.8%; the lowest is Copper Wiring at 1.9%. | I86: ='Analysis report'!A126 -> ANSWER: Both series trend upward overall but the dataset is sampled — only 4 of 18 months carry a TMT Steel price and 6 carry a Cement price (#N/A = no data that month). TMT Steel averages $675/MT (avg change 3.9%) and Cement $95/MT (avg change 11.9%). See the line chart to the right. | P86: ='Analysis report'!A133 -> ANSWER: India has the most volatile material pricing (std dev of price change = 9.8% pts), the least volatile is New Zealand at 9.0%. | BA86: ='Analysis report'!B152 -> 2025-06 | BB86: ='Analysis report'!D152 -> 695.91
BA87: Forecast · month 21 | BB87: ='Analysis report'!B155 -> 658.33262
BA89: H5 — P03 Q6 — savings on items under BOQ
BA90: Project | BB90: Savings USD (items under BOQ)
BA91: ='Analysis report'!A188 -> WT-DC-MUM-01 | BB91: ='Analysis report'!C188 -> -126377.68
BA92: ='Analysis report'!A189 -> WT-OFF-SYD-02 | BB92: ='Analysis report'!C189 -> -51637.8
BA93: ='Analysis report'!A190 -> WT-HOS-AKL-03 | BB93: ='Analysis report'!C190 -> -59886.69
BA95: H6 — P04 Q2 — productivity by country
BA96: Country | BB96: Avg productivity / man-hour
BA97: ='Analysis report'!A225 -> India | BB97: ='Analysis report'!D225 -> 3.2471035
BA98: ='Analysis report'!A226 -> Australia | BB98: ='Analysis report'!D226 -> 3.0498317
BA99: ='Analysis report'!A227 -> New Zealand | BB99: ='Analysis report'!D227 -> 2.5591892
BA101: H7 — P04 Q4 — 10 worst productivity days
BA102: Date · Trade | BB102: Productivity / man-hour
BA103: =TEXT('Analysis report'!B244,"dd-mmm-yy")&" · "&'Analysis report'!C244 -> 08-Jan-25 · Facade & Cladding | BB103: ='Analysis report'!E244 -> 0.23240741
BA104: =TEXT('Analysis report'!B245,"dd-mmm-yy")&" · "&'Analysis report'!C245 -> 21-Jan-25 · MEP - Plumbing | BB104: ='Analysis report'!E245 -> 0.27
BA105: =TEXT('Analysis report'!B246,"dd-mmm-yy")&" · "&'Analysis report'!C246 -> 09-May-25 · Civil & Structure | BB105: ='Analysis report'!E246 -> 0.32695035
B106: ='Analysis report'!A135 -> Q4. Top 3 materials with price increase > 15% — flag as procurement risk | I106: ='Analysis report'!A142 -> Q5. Average price change % by material across all months | P106: ='Analysis report'!A147 -> Q6. Projected cost of 500 MT of TMT Steel next quarter (trend-based) | BA106: =TEXT('Analysis report'!B247,"dd-mmm-yy")&" · "&'Analysis report'!C247 -> 01-Apr-25 · MEP - Electrical | BB106: ='Analysis report'!E247 -> 0.48567119
BA107: =TEXT('Analysis report'!B248,"dd-mmm-yy")&" · "&'Analysis report'!C248 -> 21-Mar-25 · MEP - HVAC | BB107: ='Analysis report'!E248 -> 0.52113271
B108: ='Analysis report'!A140 -> ANSWER: No material's AVERAGE increase exceeds 15% (highest is RMC M30 at 14.8%), though 20 of 90 individual monthly records are above 15%. Treat the top 3 — RMC M30 (14.8%), Aggregate (20mm) (14.6%), Cement (OPC 53) (11.9%) — as procurement risk and forward-buy / lock rates. | I108: ='Analysis report'!A145 -> ANSWER: The portfolio-wide average material price change is 7.5% (median 7.2%). 9 of 15 materials sit above that average — see column C of the Q1 table for the material-by-material figures. | P108: ='Analysis report'!A157 -> ANSWER: Fitting a linear trend to the 4 observed TMT Steel price points gives a slope of -$1.90/MT per month. Projected price for next quarter (month index 21) is $658/MT, so 500 MT ≈ $3,29,166 (vs $3,47,955 at the latest observed price). Caveat: only 4 data points — treat as indicative. | BA108: =TEXT('Analysis report'!B249,"dd-mmm-yy")&" · "&'Analysis report'!C249 -> 16-May-25 · MEP - Plumbing | BB108: ='Analysis report'!E249 -> 0.6975547
BA109: =TEXT('Analysis report'!B250,"dd-mmm-yy")&" · "&'Analysis report'!C250 -> 17-Jan-25 · Facade & Cladding | BB109: ='Analysis report'!E250 -> 0.78100775
BA110: =TEXT('Analysis report'!B251,"dd-mmm-yy")&" · "&'Analysis report'!C251 -> 08-Jan-25 · MEP - Plumbing | BB110: ='Analysis report'!E251 -> 0.81688312
BA111: =TEXT('Analysis report'!B252,"dd-mmm-yy")&" · "&'Analysis report'!C252 -> 27-Feb-25 · MEP - Plumbing | BB111: ='Analysis report'!E252 -> 0.99321705
BA112: =TEXT('Analysis report'!B253,"dd-mmm-yy")&" · "&'Analysis report'!C253 -> 17-Apr-25 · MEP - Plumbing | BB112: ='Analysis report'!E253 -> 1.0365385
BA114: H8 — P04 Q5 — productivity by crew band
BA115: Crew size band | BB115: Avg productivity / man-hour
BA116: ='Analysis report'!A258 -> Small crew (up to 10 workers) | BB116: ='Analysis report'!C258 -> -
BA117: ='Analysis report'!A259 -> Medium crew (11 to 15) | BB117: ='Analysis report'!C259 -> 4.1639753
BA118: ='Analysis report'!A260 -> Large crew (16 to 20) | BB118: ='Analysis report'!C260 -> 2.6779221
BA119: ='Analysis report'!A261 -> Very large crew (21+) | BB119: ='Analysis report'!C261 -> 3.221108
BA121: H9 — P05 Q1 — lowest bid vs highest-scored bid
BA122: Tender package | BB122: Lowest bid USD | BC122: Bid of highest-scored USD
...
